Workbook

Sheet Leeme
A1: Tablas V8 (F6). Generado por src/v8/f6_tablas.py a partir de salidas versionadas; no estima nada.
A2: Capas: C3s (svar_hd, H8-1…H8-4) condicionada a las restricciones de signo; C4 (asociación) el resto: sin lectura causal.
A3: Fuentes: output/v8/M0…M9 (coeficientes.csv, hipotesis_*.csv, resumen_multiverso.csv, fuera_muestra*), output/v8/F5 (regla_s9, ranking, atribucion_combinada, regional_ranking, fuera_muestra_comun).
A4: Convenciones de color:
A5: AZUL (0000FF): entrada tomada de un fichero de datos o salida; la columna «fuente» da la ruta del fichero.
A6: NEGRO (000000): cálculo hecho en la hoja con fórmula de Excel (=SUM, =COUNTIF, =SUMIFS, cocientes).
A7: VERDE (008000): vínculo a otra hoja del libro (=Hoja!A1).
A8: Sin paneles inmovilizados. Estrellas (si las hay) basadas en el p AJUSTADO. Modelos destacados: véase tablas_modelos_destacados.md.
A9: Hojas: Destacados, Hipotesis, Votos_s9, Atribucion, Ranking, Fuera_muestra, Regional, Multiverso.
A11: Resumen enlazado (verde = vínculo a otra hoja)
A12: Celdas designadas (hoja Votos_s9) | B12: =Votos_s9!B13
A13: Hipótesis tabuladas (hoja Hipotesis, filas) | B13: =COUNTA(Hipotesis!A2:A200)

Sheet Destacados
A1: modelo_id | B1: modulo | C1: familia_modelo | D1: mercado | E1: ambito | F1: periodo | G1: dependiente | H1: transformacion | I1: medida_precio | J1: variable | K1: beta | L1: ee | M1: tipo_ee | N1: t | O1: p | P1: p_ajustado | Q1: metodo_ajuste | R1: ic95_lo | S1: ic95_hi | T1: beta_std | U1: elasticidad | V1: n | W1: r2 | X1: r2_adj | Y1: aic | Z1: bic | AA1: vel_ajuste | AB1: semivida | AC1: coint_p | AD1: bg_p | AE1: bp_p | AF1: jb_p | AG1: reset_p | AH1: cusum_estable | AI1: vif_max | AJ1: f1_etapa | AK1: ar_lo | AL1: ar_hi | AM1: capa | AN1: n_multiverso | AO1: pct_mismo_signo | AP1: pct_sig_bh | AQ1: cumple_regla_m0 | AR1: cumple_multiverso | AS1: destacado | AT1: motivo_destacado | AU1: script | AV1: criterio_destacado | AW1: oos_ref | AX1: no_cumple_regla | AY1: fuente | AZ1: rmse_oos (vínculo) | BA1: rmse_ar4_oos (vínculo) | BB1: ratio_rmse_vs_ar4_calc
A2: M0_compra_base_P1 | B2: M0 | C2: ols_tramos_hac | D2: compra | E2: nacional | F2: P1 | G2: d4_ln_p_tasado_real | H2: d4_ln*100 | I2: valor tasado MIVAU, real (IPC general) | J2: d4_pob_total | K2: -3.6695463 | L2: 1.5114349 | M2: HAC-NW(4), t(32) | N2: -2.427856 | O2: 0.02099081 | P2: 0.045917396 | Q2: BH | R2: -6.7482385 | S2: -0.59085415 | T2: -0.62215703 | V2: 38 | W2: 0.69611677 | X2: 0.64863502 | Y2: 173.70026 | Z2: 183.52578 | AM2: C4 | AN2: 96 | AO2: 0.5 | AP2: 0.13541667 | AQ2: no_evaluable | AR2: no | AS2: si | AT2: (b) mejor de la familia ols_tramos_hac: ecuacion AR1+X por periodo; unico candidato con OOS en la familia; NO CUMPLE LA REGLA (§8 y multiverso) en ninguna variable; RMSE 1.802 vs AR(4) 1.216 (peor que AR(4)) | AU2: src/v8/m0_periodos.py | AV2: (b) mejor de la familia ols_tramos_hac: ecuacion AR1+X por periodo; unico candidato con OOS en la familia | AW2: M0:AR1+X_por_periodo | AX2: si | AY2: output/v8/M0/coeficientes.csv | AZ2: =Fuera_muestra!F16 | BA2: =Fuera_muestra!G16 | BB2: =AZ2/BA2
A3: M0_compra_base_P1 | B3: M0 | C3: ols_tramos_hac | D3: compra | E3: nacional | F3: P1 | G3: d4_ln_p_tasado_real | H3: d4_ln*100 | I3: valor tasado MIVAU, real (IPC general) | J3: d4_pib_vol | K3: -3.5195761 | L3: 0.88831237 | M3: HAC-NW(4), t(32) | N3: -3.9620928 | O3: 0.0003895504 | P3: 0.0015198921 | Q3: BH | R3: -5.3290091 | S3: -1.710143 | T3: -0.68910399 | V3: 38 | W3: 0.69611677 | X3: 0.64863502 | Y3: 173.70026 | Z3: 183.52578 | AM3: C4 | AN3: 96 | AO3: 0.875 | AP3: 0.03125 | AQ3: no_evaluable | AR3: no | AS3: si | AT3: (b) mejor de la familia ols_tramos_hac: ecuacion AR1+X por periodo; unico candidato con OOS en la familia; NO CUMPLE LA REGLA (§8 y multiverso) en ninguna variable; RMSE 1.802 vs AR(4) 1.216 (peor que AR(4)) | AU3: src/v8/m0_periodos.py | AV3: (b) mejor de la familia ols_tramos_hac: ecuacion AR1+X por periodo; unico candidato con OOS en la familia | AW3: M0:AR1+X_por_periodo | AX3: si | AY3: output/v8/M0/coeficientes.csv | AZ3: =Fuera_muestra!F16 | BA3: =Fuera_muestra!G16 | BB3: =AZ3/BA3
A4: M0_compra_base_P1 | B4: M0 | C4: ols_tramos_hac | D4: compra | E4: nacional | F4: P1 | G4: d4_ln_p_tasado_real | H4: d4_ln*100 | I4: valor tasado MIVAU, real (IPC general) | J4: tipo_hip_real | K4: -2.2040111 | L4: 0.43568509 | M4: HAC-NW(4), t(32) | N4: -5.0587251 | O4: 1.6752769e-05 | P4: 0.00011115901 | Q4: BH | R4: -3.0914726 | S4: -1.3165496 | T4: -0.73447329 | V4: 38 | W4: 0.69611677 | X4: 0.64863502 | Y4: 173.70026 | Z4: 183.52578 | AM4: C4 | AN4: 96 | AO4: 0.95833333 | AP4: 0.65625 | AQ4: no_evaluable | AR4: sí | AS4: si | AT4: (b) mejor de la familia ols_tramos_hac: ecuacion AR1+X por periodo; unico candidato con OOS en la familia; NO CUMPLE LA REGLA (§8 y multiverso) en ninguna variable; RMSE 1.802 vs AR(4) 1.216 (peor que AR(4)) | AU4: src/v8/m0_periodos.py | AV4: (b) mejor de la familia ols_tramos_hac: ecuacion AR1+X por periodo; unico candidato con OOS en la familia | AW4: M0:AR1+X_por_periodo | AX4: si | AY4: output/v8/M0/coeficientes.csv | AZ4: =Fuera_muestra!F16 | BA4: =Fuera_muestra!G16 | BB4: =AZ4/BA4
A5: M0_compra_base_P1 | B5: M0 | C5: ols_tramos_hac | D5: compra | E5: nacional | F5: P1 | G5: d4_ln_p_tasado_real | H5: d4_ln*100 | I5: valor tasado MIVAU, real (IPC general) | J5: d4_credito_vivienda_real | K5: -0.086771298 | L5: 0.11049968 | M5: HAC-NW(4), t(32) | N5: -0.7852629 | O5: 0.43807508 | P5: 0.53798694 | Q5: BH | R5: -0.31185178 | S5: 0.13830918 | T5: -0.10157474 | V5: 38 | W5: 0.69611677 | X5: 0.64863502 | Y5: 173.70026 | Z5: 183.52578 | AM5: C4 | AQ5: no_evaluable | AR5: no_evaluable | AS5: si | AT5: (b) mejor de la familia ols_tramos_hac: ecuacion AR1+X por periodo; unico candidato con OOS en la familia; NO CUMPLE LA REGLA (§8 y multiverso) en ninguna variable; RMSE 1.802 vs AR(4) 1.216 (peor que AR(4)) | AU5: src/v8/m0_periodos.py | AV5: (b) mejor de la familia ols_tramos_hac: ecuacion AR1+X por periodo; unico candidato con OOS en la familia | AW5: M0:AR1+X_por_periodo | AX5: si | AY5: output/v8/M0/coeficientes.csv | AZ5: =Fuera_muestra!F16 | BA5: =Fuera_muestra!G16 | BB5: =AZ5/BA5
A6: M0_compra_base_P1 | B6: M0 | C6: ols_tramos_hac | D6: compra | E6: nacional | F6: P1 | G6: d4_ln_p_tasado_real | H6: d4_ln*100 | I6: valor tasado MIVAU, real (IPC general) | J6: d4_terminadas | K6: -0.043045333 | L6: 0.047215423 | M6: HAC-NW(4), t(32) | N6: -0.91167949 | O6: 0.36875468 | P6: 0.47801533 | Q6: BH | R6: -0.13922 | S6: 0.053129337 | T6: -0.11942732 | V6: 38 | W6: 0.69611677 | X6: 0.64863502 | Y6: 173.70026 | Z6: 183.52578 | AM6: C4 | AN6: 84 | AO6: 0.52380952 | AP6: 0.14285714 | AQ6: no_evaluable | AR6: no | AS6: si | AT6: (b) mejor de la familia ols_tramos_hac: ecuacion AR1+X por periodo; unico candidato con OOS en la familia; NO CUMPLE LA REGLA (§8 y multiverso) en ninguna variable; RMSE 1.802 vs AR(4) 1.216 (peor que AR(4)) | AU6: src/v8/m0_periodos.py | AV6: (b) mejor de la familia ols_tramos_hac: ecuacion AR1+X por periodo; unico candidato con OOS en la familia | AW6: M0:AR1+X_por_periodo | AX6: si | AY6: output/v8/M0/coeficientes.csv | AZ6: =Fuera_muestra!F16 | BA6: =Fuera_muestra!G16 | BB6: =AZ6/BA6
A7: M0_compra_base_P2 | B7: M0 | C7: ols_tramos_hac | D7: compra | E7: nacional | F7: P2 | G7: d4_ln_p_tasado_real | H7: d4_ln*100 | I7: valor tasado MIVAU, real (IPC general) | J7: d4_pob_total | K7: -1.897405 | L7: 0.54384567 | M7: HAC-NW(4), t(16) | N7: -3.4888666 | O7: 0.0030340583 | P7: 0.0084953632 | Q7: BH | R7: -3.0503063 | S7: -0.74450365 | T7: -0.41838559 | V7: 22 | W7: 0.9372564 | X7: 0.91764902 | Y7: 53.427308 | Z7: 59.973563 | AM7: C4 | AN7: 192 | AO7: 0.72916667 | AP7: 0.125 | AQ7: no | AR7: no | AS7: si | AT7: (b) mejor de la familia ols_tramos_hac: ecuacion AR1+X por periodo; unico candidato con OOS en la familia; NO CUMPLE LA REGLA (§8 y multiverso) en ninguna variable; RMSE 1.802 vs AR(4) 1.216 (peor que AR(4)) | AU7: src/v8/m0_periodos.py | AV7: (b) mejor de la familia ols_tramos_hac: ecuacion AR1+X por periodo; unico candidato con OOS en la familia | AW7: M0:AR1+X_por_periodo | AX7: si | AY7: output/v8/M0/coeficientes.csv | AZ7: =Fuera_muestra!F16 | BA7: =Fuera_muestra!G16 | BB7: =AZ7/BA7
A8: M0_compra_base_P2 | B8: M0 | C8: ols_tramos_hac | D8: compra | E8: nacional | F8: P2 | G8: d4_ln_p_tasado_real | H8: d4_ln*100 | I8: valor tasado MIVAU, real (IPC general) | J8: d4_pib_vol | K8: 1.3792567 | L8: 0.13502259 | M8: HAC-NW(4), t(16) | N8: 10.215007 | O8: 2.0414556e-08 | P8: 2.8580378e-07 | Q8: BH | R8: 1.0930216 | S8: 1.6654918 | T8: 0.87455114 | V8: 22 | W8: 0.9372564 | X8: 0.91764902 | Y8: 53.427308 | Z8: 59.973563 | AM8: C4 | AN8: 192 | AO8: 0.75 | AP8: 0.30729167 | AQ8: si | AR8: no | AS8: si | AT8: (b) mejor de la familia ols_tramos_hac: ecuacion AR1+X por periodo; unico candidato con OOS en la familia; NO CUMPLE LA REGLA (§8 y multiverso) en ninguna variable; RMSE 1.802 vs AR(4) 1.216 (peor que AR(4)) | AU8: src/v8/m0_periodos.py | AV8: (b) mejor de la familia ols_tramos_hac: ecuacion AR1+X por periodo; unico candidato con OOS en la familia | AW8: M0:AR1+X_por_periodo | AX8: si | AY8: output/v8/M0/coeficientes.csv | AZ8: =Fuera_muestra!F16 | BA8: =Fuera_muestra!G16 | BB8: =AZ8/BA8
A9: M0_compra_base_P2 | B9: M0 | C9: ols_tramos_hac | D9: compra | E9: nacional | F9: P2 | G9: d4_ln_p_tasado_real | H9: d4_ln*100 | I9: valor tasado MIVAU, real (IPC general) | J9: tipo_hip_real | K9: 1.1695795 | L9: 0.19990836 | M9: HAC-NW(4), t(16) | N9: 5.8505785 | O9: 2.4603182e-05 | P9: 0.00013247867 | Q9: BH | R9: 0.74579275 | S9: 1.5933663 | T9: 0.65363243 | V9: 22 | W9: 0.9372564 | X9: 0.91764902 | Y9: 53.427308 | Z9: 59.973563 | AM9: C4 | AN9: 192 | AO9: 0.63541667 | AP9: 0.265625 | AQ9: no | AR9: no | AS9: si | AT9: (b) mejor de la familia ols_tramos_hac: ecuacion AR1+X por periodo; unico candidato con OOS en la familia; NO CUMPLE LA REGLA (§8 y multiverso) en ninguna variable; RMSE 1.802 vs AR(4) 1.216 (peor que AR(4)) | AU9: src/v8/m0_periodos.py | AV9: (b) mejor de la familia ols_tramos_hac: ecuacion AR1+X por periodo; unico candidato con OOS en la familia | AW9: M0:AR1+X_por_periodo | AX9: si | AY9: output/v8/M0/coeficientes.csv | AZ9: =Fuera_muestra!F16 | BA9: =Fuera_muestra!G16 | BB9: =AZ9/BA9
A10: M0_compra_base_P2 | B10: M0 | C10: ols_tramos_hac | D10: compra | E10: nacional | F10: P2 | G10: d4_ln_p_tasado_real | H10: d4_ln*100 | I10: valor tasado MIVAU, real (IPC general) | J10: d4_credito_vivienda_real | K10: 0.52750169 | L10: 0.14945028 | M10: HAC-NW(4), t(16) | N10: 3.5296132 | O10: 0.0027838559 | P10: 0.0081221688 | Q10: BH | R10: 0.21068125 | S10: 0.84432214 | T10: 0.62245652 | V10: 22 | W10: 0.9372564 | X10: 0.91764902 | Y10: 53.427308 | Z10: 59.973563 | AM10: C4 | AQ10: no | AR10: no_evaluable | AS10: si | AT10: (b) mejor de la familia ols_tramos_hac: ecuacion AR1+X por periodo; unico candidato con OOS en la familia; NO CUMPLE LA REGLA (§8 y multiverso) en ninguna variable; RMSE 1.802 vs AR(4) 1.216 (peor que AR(4)) | AU10: src/v8/m0_periodos.py | AV10: (b) mejor de la familia ols_tramos_hac: ecuacion AR1+X por periodo; unico candidato con OOS en la familia | AW10: M0:AR1+X_por_periodo | AX10: si | AY10: output/v8/M0/coeficientes.csv | AZ10: =Fuera_muestra!F16 | BA10: =Fuera_muestra!G16 | BB10: =AZ10/BA10
A11: M0_compra_base_P2 | B11: M0 | C11: ols_tramos_hac | D11: compra | E11: nacional | F11: P2 | G11: d4_ln_p_tasado_real | H11: d4_ln*100 | I11: valor tasado MIVAU, real (IPC general) | J11: d4_terminadas | K11: 0.0042193887 | L11: 0.0075889186 | M11: HAC-NW(4), t(16) | N11: 0.5559934 | O11: 0.58590728 | P11: 0.66087919 | Q11: BH | R11: -0.0118684 | S11: 0.020307177 | T11: 0.028597206 | V11: 22 | W11: 0.9372564 | X11: 0.91764902 | Y11: 53.427308 | Z11: 59.973563 | AM11: C4 | AN11: 192 | AO11: 0.59375 | AP11: 0.10416667 | AQ11: no | AR11: no | AS11: si | AT11: (b) mejor de la familia ols_tramos_hac: ecuacion AR1+X por periodo; unico candidato con OOS en la familia; NO CUMPLE LA REGLA (§8 y multiverso) en ninguna variable; RMSE 1.802 vs AR(4) 1.216 (peor que AR(4)) | AU11: src/v8/m0_periodos.py | AV11: (b) mejor de la familia ols_tramos_hac: ecuacion AR1+X por periodo; unico candidato con OOS en la familia | AW11: M0:AR1+X_por_periodo | AX11: si | AY11: output/v8/M0/coeficientes.csv | AZ11: =Fuera_muestra!F16 | BA11: =Fuera_muestra!G16 | BB11: =AZ11/BA11
A12: M0_compra_base_P3 | B12: M0 | C12: ols_tramos_hac | D12: compra | E12: nacional | F12: P3 | G12: d4_ln_p_tasado_real | H12: d4_ln*100 | I12: valor tasado MIVAU, real (IPC general) | J12: d4_pob_total | K12: 4.0791809 | L12: 0.84917918 | M12: HAC-NW(4), t(18) | N12: 4.8036752 | O12: 0.00014225215 | P12: 0.00066384336 | Q12: BH | R12: 2.2951217 | S12: 5.8632402 | T12: 0.79136062 | V12: 24 | W12: 0.8902504 | X12: 0.85976439 | Y12: 55.981075 | Z12: 63.049398 | AM12: C4 | AN12: 192 | AO12: 0.71875 | AP12: 0.140625 | AQ12: no | AR12: no | AS12: si | AT12: (b) mejor de la familia ols_tramos_hac: ecuacion AR1+X por periodo; unico candidato con OOS en la familia; NO CUMPLE LA REGLA (§8 y multiverso) en ninguna variable; RMSE 1.802 vs AR(4) 1.216 (peor que AR(4)) | AU12: src/v8/m0_periodos.py | AV12: (b) mejor de la familia ols_tramos_hac: ecuacion AR1+X por periodo; unico candidato con OOS en la familia | AW12: M0:AR1+X_por_periodo | AX12: si | AY12: output/v8/M0/coeficientes.csv | AZ12: =Fuera_muestra!F16 | BA12: =Fuera_muestra!G16 | BB12: =AZ12/BA12
A13: M0_compra_base_P3 | B13: M0 | C13: ols_tramos_hac | D13: compra | E13: nacional | F13: P3 | G13: d4_ln_p_tasado_real | H13: d4_ln*100 | I13: valor tasado MIVAU, real (IPC general) | J13: d4_pib_vol | K13: 1.4539043 | L13: 0.1936462 | M13: HAC-NW(4), t(18) | N13: 7.5080445 | O13: 5.9783509e-07 | P13: 5.2310571e-06 | Q13: BH | R13: 1.0470687 | S13: 1.8607399 | T13: 0.72317695 | V13: 24 | W13: 0.8902504 | X13: 0.85976439 | Y13: 55.981075 | Z13: 63.049398 | AM13: C4 | AN13: 192 | AO13: 0.94791667 | AP13: 0.43229167 | AQ13: no | AR13: no | AS13: si | AT13: (b) mejor de la familia ols_tramos_hac: ecuacion AR1+X por periodo; unico candidato con OOS en la familia; NO CUMPLE LA REGLA (§8 y multiverso) en ninguna variable; RMSE 1.802 vs AR(4) 1.216 (peor que AR(4)) | AU13: src/v8/m0_periodos.py | AV13: (b) mejor de la familia ols_tramos_hac: ecuacion AR1+X por periodo; unico candidato con OOS en la familia | AW13: M0:AR1+X_por_periodo | AX13: si | AY13: output/v8/M0/coeficientes.csv | AZ13: =Fuera_muestra!F16 | BA13: =Fuera_muestra!G16 | BB13: =AZ13/BA13
A14: M0_compra_base_P3 | B14: M0 | C14: ols_tramos_hac | D14: compra | E14: nacional | F14: P3 | G14: d4_ln_p_tasado_real | H14: d4_ln*100 | I14: valor tasado MIVAU, real (IPC general) | J14: tipo_hip_real | K14: 0.21910839 | L14: 0.16985097 | M14: HAC-NW(4), t(18) | N14: 1.2900038 | O14: 0.213377 | P14: 0.30482429 | Q14: BH | R14: -0.13773525 | S14: 0.57595203 | T14: 0.15358176 | V14: 24 | W14: 0.8902504 | X14: 0.85976439 | Y14: 55.981075 | Z14: 63.049398 | AM14: C4 | AN14: 192 | AO14: 0.78125 | AP14: 0.19270833 | AQ14: no | AR14: no | AS14: si | AT14: (b) mejor de la familia ols_tramos_hac: ecuacion AR1+X por periodo; unico candidato con OOS en la familia; NO CUMPLE LA REGLA (§8 y multiverso) en ninguna variable; RMSE 1.802 vs AR(4) 1.216 (peor que AR(4)) | AU14: src/v8/m0_periodos.py | AV14: (b) mejor de la familia ols_tramos_hac: ecuacion AR1+X por periodo; unico candidato con OOS en la familia | AW14: M0:AR1+X_por_periodo | AX14: si | AY14: output/v8/M0/coeficientes.csv | AZ14: =Fuera_muestra!F16 | BA14: =Fuera_muestra!G16 | BB14: =AZ14/BA14
A15: M0_compra_base_P3 | B15: M0 | C15: ols_tramos_hac | D15: compra | E15: nacional | F15: P3 | G15: d4_ln_p_tasado_real | H15: d4_ln*100 | I15: valor tasado MIVAU, real (IPC general) | J15: d4_credito_vivienda_real | K15: 0.28219487 | L15: 0.20801528 | M15: HAC-NW(4), t(18) | N15: 1.3566065 | O15: 0.19167832 | P15: 0.28547835 | Q15: BH | R15: -0.15482901 | S15: 0.71921875 | T15: 0.16327856 | V15: 24 | W15: 0.8902504 | X15: 0.85976439 | Y15: 55.981075 | Z15: 63.049398 | AM15: C4 | AQ15: no | AR15: no_evaluable | AS15: si | AT15: (b) mejor de la familia ols_tramos_hac: ecuacion AR1+X por periodo; unico candidato con OOS en la familia; NO CUMPLE LA REGLA (§8 y multiverso) en ninguna variable; RMSE 1.802 vs AR(4) 1.216 (peor que AR(4)) | AU15: src/v8/m0_periodos.py | AV15: (b) mejor de la familia ols_tramos_hac: ecuacion AR1+X por periodo; unico candidato con OOS en la familia | AW15: M0:AR1+X_por_periodo | AX15: si | AY15: output/v8/M0/coeficientes.csv | AZ15: =Fuera_muestra!F16 | BA15: =Fuera_muestra!G16 | BB15: =AZ15/BA15
A16: M0_compra_base_P3 | B16: M0 | C16: ols_tramos_hac | D16: compra | E16: nacional | F16: P3 | G16: d4_ln_p_tasado_real | H16: d4_ln*100 | I16: valor tasado MIVAU, real (IPC general) | J16: d4_terminadas | K16: -0.013674199 | L16: 0.0086162836 | M16: HAC-NW(4), t(18) | N16: -1.5870183 | O16: 0.12991913 | P16: 0.21149626 | Q16: BH | R16: -0.03177634 | S16: 0.0044279407 | T16: -0.17565484 | V16: 24 | W16: 0.8902504 | X16: 0.85976439 | Y16: 55.981075 | Z16: 63.049398 | AM16: C4 | AN16: 192 | AO16: 0.57291667 | AP16: 0.1875 | AQ16: no | AR16: no | AS16: si | AT16: (b) mejor de la familia ols_tramos_hac: ecuacion AR1+X por periodo; unico candidato con OOS en la familia; NO CUMPLE LA REGLA (§8 y multiverso) en ninguna variable; RMSE 1.802 vs AR(4) 1.216 (peor que AR(4)) | AU16: src/v8/m0_periodos.py | AV16: (b) mejor de la familia ols_tramos_hac: ecuacion AR1+X por periodo; unico candidato con OOS en la familia | AW16: M0:AR1+X_por_periodo | AX16: si | AY16: output/v8/M0/coeficientes.csv | AZ16: =Fuera_muestra!F16 | BA16: =Fuera_muestra!G16 | BB16: =AZ16/BA16
A17: M0_compra_base_P4 | B17: M0 | C17: ols_tramos_hac | D17: compra | E17: nacional | F17: P4 | G17: d4_ln_p_tasado_real | H17: d4_ln*100 | I17: valor tasado MIVAU, real (IPC general) | J17: d4_pob_total | K17: 0.19554702 | L17: 3.094337 | M17: HAC-NW(4), t(3) | N17: 0.063195126 | O17: 0.95358611 | P17: 0.95358611 | Q17: BH | R17: -9.6520144 | S17: 10.043108 | T17: 0.054769703 | V17: 9 | W17: 0.89261072 | X17: 0.71362859 | Y17: 14.15451 | Z17: 15.337857 | AM17: C4 | AN17: 240 | AO17: 0.66666667 | AP17: 0.24166667 | AQ17: no | AR17: no | AS17: si | AT17: (b) mejor de la familia ols_tramos_hac: ecuacion AR1+X por periodo; unico candidato con OOS en la familia; NO CUMPLE LA REGLA (§8 y multiverso) en ninguna variable; RMSE 1.802 vs AR(4) 1.216 (peor que AR(4)) | AU17: src/v8/m0_periodos.py | AV17: (b) mejor de la familia ols_tramos_hac: ecuacion AR1+X por periodo; unico candidato con OOS en la familia | AW17: M0:AR1+X_por_periodo | AX17: si | AY17: output/v8/M0/coeficientes.csv | AZ17: =Fuera_muestra!F16 | BA17: =Fuera_muestra!G16 | BB17: =AZ17/BA17
A18: M0_compra_base_P4 | B18: M0 | C18: ols_tramos_hac | D18: compra | E18: nacional | F18: P4 | G18: d4_ln_p_tasado_real | H18: d4_ln*100 | I18: valor tasado MIVAU, real (IPC general) | J18: d4_pib_vol | K18: -0.14704456 | L18: 0.028814289 | M18: HAC-NW(4), t(3) | N18: -5.1031822 | O18: 0.014552864 | P18: 0.035127602 | Q18: BH | R18: -0.23874449 | S18: -0.055344638 | T18: -2.0955713 | V18: 9 | W18: 0.89261072 | X18: 0.71362859 | Y18: 14.15451 | Z18: 15.337857 | AM18: C4 | AN18: 240 | AO18: 0.525 | AP18: 0.2625 | AQ18: no | AR18: no | AS18: si | AT18: (b) mejor de la familia ols_tramos_hac: ecuacion AR1+X por periodo; unico candidato con OOS en la familia; NO CUMPLE LA REGLA (§8 y multiverso) en ninguna variable; RMSE 1.802 vs AR(4) 1.216 (peor que AR(4)) | AU18: src/v8/m0_periodos.py | AV18: (b) mejor de la familia ols_tramos_hac: ecuacion AR1+X por periodo; unico candidato con OOS en la familia | AW18: M0:AR1+X_por_periodo | AX18: si | AY18: output/v8/M0/coeficientes.csv | AZ18: =Fuera_muestra!F16 | BA18: =Fuera_muestra!G16 | BB18: =AZ18/BA18
A19: M0_compra_base_P4 | B19: M0 | C19: ols_tramos_hac | D19: compra | E19: nacional | F19: P4 | G19: d4_ln_p_tasado_real | H19: d4_ln*100 | I19: valor tasado MIVAU, real (IPC general) | J19: tipo_hip_real | K19: -1.4423387 | L19: 0.88310688 | M19: HAC-NW(4), t(3) | N19: -1.633255 | O19: 0.20092229 | P19: 0.29301167 | Q19: BH | R19: -4.252779 | S19: 1.3681015 | T19: -6.0423175 | V19: 9 | W19: 0.89261072 | X19: 0.71362859 | Y19: 14.15451 | Z19: 15.337857 | AM19: C4 | AN19: 240 | AO19: 0.525 | AP19: 0.225 | AQ19: no | AR19: no | AS19: si | AT19: (b) mejor de la familia ols_tramos_hac: ecuacion AR1+X por periodo; unico candidato con OOS en la familia; NO CUMPLE LA REGLA (§8 y multiverso) en ninguna variable; RMSE 1.802 vs AR(4) 1.216 (peor que AR(4)) | AU19: src/v8/m0_periodos.py | AV19: (b) mejor de la familia ols_tramos_hac: ecuacion AR1+X por periodo; unico candidato con OOS en la familia | AW19: M0:AR1+X_por_periodo | AX19: si | AY19: output/v8/M0/coeficientes.csv | AZ19: =Fuera_muestra!F16 | BA19: =Fuera_muestra!G16 | BB19: =AZ19/BA19
A20: M0_compra_base_P4 | B20: M0 | C20: ols_tramos_hac | D20: compra | E20: nacional | F20: P4 | G20: d4_ln_p_tasado_real | H20: d4_ln*100 | I20: valor tasado MIVAU, real (IPC general) | J20: d4_credito_vivienda_real | K20: 1.7856297 | L20: 1.2107281 | M20: HAC-NW(4), t(3) | N20: 1.4748395 | O20: 0.23671084 | P20: 0.32394163 | Q20: BH | R20: -2.0674476 | S20: 5.638707 | T20: 4.9513316 | V20: 9 | W20: 0.89261072 | X20: 0.71362859 | Y20: 14.15451 | Z20: 15.337857 | AM20: C4 | AQ20: no | AR20: no_evaluable | AS20: si | AT20: (b) mejor de la familia ols_tramos_hac: ecuacion AR1+X por periodo; unico candidato con OOS en la familia; NO CUMPLE LA REGLA (§8 y multiverso) en ninguna variable; RMSE 1.802 vs AR(4) 1.216 (peor que AR(4)) | AU20: src/v8/m0_periodos.py | AV20: (b) mejor de la familia ols_tramos_hac: ecuacion AR1+X por periodo; unico candidato con OOS en la familia | AW20: M0:AR1+X_por_periodo | AX20: si | AY20: output/v8/M0/coeficientes.csv | AZ20: =Fuera_muestra!F16 | BA20: =Fuera_muestra!G16 | BB20: =AZ20/BA20
A21: M0_compra_base_P4 | B21: M0 | C21: ols_tramos_hac | D21: compra | E21: nacional | F21: P4 | G21: d4_ln_p_tasado_real | H21: d4_ln*100 | I21: valor tasado MIVAU, real (IPC general) | J21: d4_terminadas | K21: 0.065167699 | L21: 0.018470034 | M21: HAC-NW(4), t(3) | N21: 3.5282935 | O21: 0.038686491 | P21: 0.079648658 | Q21: BH | R21: 0.0063878085 | S21: 0.12394759 | T21: 1.3022608 | V21: 9 | W21: 0.89261072 | X21: 0.71362859 | Y21: 14.15451 | Z21: 15.337857 | AM21: C4 | AN21: 240 | AO21: 0.61666667 | AP21: 0.11666667 | AQ21: si | AR21: no | AS21: si | AT21: (b) mejor de la familia ols_tramos_hac: ecuacion AR1+X por periodo; unico candidato con OOS en la familia; NO CUMPLE LA REGLA (§8 y multiverso) en ninguna variable; RMSE 1.802 vs AR(4) 1.216 (peor que AR(4)) | AU21: src/v8/m0_periodos.py | AV21: (b) mejor de la familia ols_tramos_hac: ecuacion AR1+X por periodo; unico candidato con OOS en la familia | AW21: M0:AR1+X_por_periodo | AX21: si | AY21: output/v8/M0/coeficientes.csv | AZ21: =Fuera_muestra!F16 | BA21: =Fuera_muestra!G16 | BB21: =AZ21/BA21
A22: M0_compra_base_P5 | B22: M0 | C22: ols_tramos_hac | D22: compra | E22: nacional | F22: P5 | G22: d4_ln_p_tasado_real | H22: d4_ln*100 | I22: valor tasado MIVAU, real (IPC general) | J22: d4_pob_total | K22: -10.182187 | L22: 2.0248415 | M22: HAC-NW(4), t(10) | N22: -5.028634 | O22: 0.00051515768 | P22: 0.0018979493 | Q22: BH | R22: -14.693815 | S22: -5.6705588 | T22: -0.20573425 | V22: 16 | W22: 0.98349136 | X22: 0.97523704 | Y22: 40.195018 | Z22: 44.830551 | AM22: C4 | AN22: 192 | AO22: 0.59375 | AP22: 0.19791667 | AQ22: no | AR22: no | AS22: si | AT22: (b) mejor de la familia ols_tramos_hac: ecuacion AR1+X por periodo; unico candidato con OOS en la familia; NO CUMPLE LA REGLA (§8 y multiverso) en ninguna variable; RMSE 1.802 vs AR(4) 1.216 (peor que AR(4)) | AU22: src/v8/m0_periodos.py | AV22: (b) mejor de la familia ols_tramos_hac: ecuacion AR1+X por periodo; unico candidato con OOS en la familia | AW22: M0:AR1+X_por_periodo | AX22: si | AY22: output/v8/M0/coeficientes.csv | AZ22: =Fuera_muestra!F16 | BA22: =Fuera_muestra!G16 | BB22: =AZ22/BA22
A23: M0_compra_base_P5 | B23: M0 | C23: ols_tramos_hac | D23: compra | E23: nacional | F23: P5 | G23: d4_ln_p_tasado_real | H23: d4_ln*100 | I23: valor tasado MIVAU, real (IPC general) | J23: d4_pib_vol | K23: -1.155329 | L23: 0.26917651 | M23: HAC-NW(4), t(10) | N23: -4.2920869 | O23: 0.0015810058 | P23: 0.0050304731 | Q23: BH | R23: -1.7550916 | S23: -0.55556633 | T23: -0.27151887 | V23: 16 | W23: 0.98349136 | X23: 0.97523704 | Y23: 40.195018 | Z23: 44.830551 | AM23: C4 | AN23: 192 | AO23: 0.85416667 | AP23: 0.28645833 | AQ23: no | AR23: no | AS23: si | AT23: (b) mejor de la familia ols_tramos_hac: ecuacion AR1+X por periodo; unico candidato con OOS en la familia; NO CUMPLE LA REGLA (§8 y multiverso) en ninguna variable; RMSE 1.802 vs AR(4) 1.216 (peor que AR(4)) | AU23: src/v8/m0_periodos.py | AV23: (b) mejor de la familia ols_tramos_hac: ecuacion AR1+X por periodo; unico candidato con OOS en la familia | AW23: M0:AR1+X_por_periodo | AX23: si | AY23: output/v8/M0/coeficientes.csv | AZ23: =Fuera_muestra!F16 | BA23: =Fuera_muestra!G16 | BB23: =AZ23/BA23
A24: M0_compra_base_P5 | B24: M0 | C24: ols_tramos_hac | D24: compra | E24: nacional | F24: P5 | G24: d4_ln_p_tasado_real | H24: d4_ln*100 | I24: valor tasado MIVAU, real (IPC general) | J24: tipo_hip_real | K24: 0.19636616 | L24: 0.12653838 | M24: HAC-NW(4), t(10) | N24: 1.5518308 | O24: 0.15174994 | P24: 0.23605547 | Q24: BH | R24: -0.085578918 | S24: 0.47831123 | T24: 0.09430851 | V24: 16 | W24: 0.98349136 | X24: 0.97523704 | Y24: 40.195018 | Z24: 44.830551 | AM24: C4 | AN24: 192 | AO24: 0.875 | AP24: 0.5 | AQ24: no | AR24: sí | AS24: si | AT24: (b) mejor de la familia ols_tramos_hac: ecuacion AR1+X por periodo; unico candidato con OOS en la familia; NO CUMPLE LA REGLA (§8 y multiverso) en ninguna variable; RMSE 1.802 vs AR(4) 1.216 (peor que AR(4)) | AU24: src/v8/m0_periodos.py | AV24: (b) mejor de la familia ols_tramos_hac: ecuacion AR1+X por periodo; unico candidato con OOS en la familia | AW24: M0:AR1+X_por_periodo | AX24: si | AY24: output/v8/M0/coeficientes.csv | AZ24: =Fuera_muestra!F16 | BA24: =Fuera_muestra!G16 | BB24: =AZ24/BA24
A25: M0_compra_base_P5 | B25: M0 | C25: ols_tramos_hac | D25: compra | E25: nacional | F25: P5 | G25: d4_ln_p_tasado_real | H25: d4_ln*100 | I25: valor tasado MIVAU, real (IPC general) | J25: d4_credito_vivienda_real | K25: 1.0467998 | L25: 0.080231014 | M25: HAC-NW(4), t(10) | N25: 13.047322 | O25: 1.3250259e-07 | P25: 1.5458635e-06 | Q25: BH | R25: 0.86803399 | S25: 1.2255657 | T25: 0.72656099 | V25: 16 | W25: 0.98349136 | X25: 0.97523704 | Y25: 40.195018 | Z25: 44.830551 | AM25: C4 | AQ25: no | AR25: no_evaluable | AS25: si | AT25: (b) mejor de la familia ols_tramos_hac: ecuacion AR1+X por periodo; unico candidato con OOS en la familia; NO CUMPLE LA REGLA (§8 y multiverso) en ninguna variable; RMSE 1.802 vs AR(4) 1.216 (peor que AR(4)) | AU25: src/v8/m0_periodos.py | AV25: (b) mejor de la familia ols_tramos_hac: ecuacion AR1+X por periodo; unico candidato con OOS en la familia | AW25: M0:AR1+X_por_periodo | AX25: si | AY25: output/v8/M0/coeficientes.csv | AZ25: =Fuera_muestra!F16 | BA25: =Fuera_muestra!G16 | BB25: =AZ25/BA25
A26: M0_compra_base_P5 | B26: M0 | C26: ols_tramos_hac | D26: compra | E26: nacional | F26: P5 | G26: d4_ln_p_tasado_real | H26: d4_ln*100 | I26: valor tasado MIVAU, real (IPC general) | J26: d4_terminadas | K26: -0.0059417541 | L26: 0.016916515 | M26: HAC-NW(4), t(10) | N26: -0.35123985 | O26: 0.73269609 | P26: 0.77710191 | Q26: BH | R26: -0.043634097 | S26: 0.031750589 | T26: -0.010223354 | V26: 16 | W26: 0.98349136 | X26: 0.97523704 | Y26: 40.195018 | Z26: 44.830551 | AM26: C4 | AN26: 192 | AO26: 0.52083333 | AP26: 0.098958333 | AQ26: no | AR26: no | AS26: si | AT26: (b) mejor de la familia ols_tramos_hac: ecuacion AR1+X por periodo; unico candidato con OOS en la familia; NO CUMPLE LA REGLA (§8 y multiverso) en ninguna variable; RMSE 1.802 vs AR(4) 1.216 (peor que AR(4)) | AU26: src/v8/m0_periodos.py | AV26: (b) mejor de la familia ols_tramos_hac: ecuacion AR1+X por periodo; unico candidato con OOS en la familia | AW26: M0:AR1+X_por_periodo | AX26: si | AY26: output/v8/M0/coeficientes.csv | AZ26: =Fuera_muestra!F16 | BA26: =Fuera_muestra!G16 | BB26: =AZ26/BA26
A27: M4_compra_C1_sin_rupturas_ardl | B27: M4 | C27: ardl_bounds_uecm | D27: compra | E27: nacional | F27: completo | G27: ln_p_tasado_real | H27: ln niveles; tipo en pp | I27: valor tasado MIVAU, real (IPC general) | J27: renta | K27: -0.69059925 | L27: 1.2340515 | M27: delta (OLS clasico) | N27: -0.55961949 | O27: 0.57573901 | P27: 0.74059734 | Q27: BH | R27: -3.1093401 | S27: 1.7281416 | T27: -0.44808162 | U27: -0.69059925 | V27: 113 | W27: 0.31575678 | X27: 0.27702603 | Y27: -582.91065 | Z27: -563.81894 | AA27: -0.017257219 | AB27: 39.818057 | AC27: 0.1 | AD27: 1.6662665e-18 | AE27: 0.034617396 | AF27: 0.32078518 | AG27: 0.21544114 | AH27: 1 | AI27: 1.2670878 | AM27: C4 | AQ27: no_evaluable | AR27: no_evaluable | AS27: si | AT27: (b) mejor de la familia dols/fmols/ardl: especificacion C1 de menor RMSE (ECM); el OOS se hace con beta OLS estatico y es comun a los tres estimadores; NO CUMPLE LA REGLA (§8 y multiverso) en ninguna variable; RMSE 1.407 vs AR(4) 1.283 (peor que AR(4)) | AU27: src/v8/m4_largo_plazo.py | AV27: (b) mejor de la familia dols/fmols/ardl: especificacion C1 de menor RMSE (ECM); el OOS se hace con beta OLS estatico y es comun a los tres estimadores | AW27: M4:C1_sin_rupturas_ECM | AX27: si | AY27: output/v8/M4/coeficientes.csv | AZ27: =Fuera_muestra!F22 | BA27: =Fuera_muestra!G22 | BB27: =AZ27/BA27
A28: M4_compra_C1_sin_rupturas_ardl | B28: M4 | C28: ardl_bounds_uecm | D28: compra | E28: nacional | F28: completo | G28: ln_p_tasado_real | H28: ln niveles; tipo en pp | I28: valor tasado MIVAU, real (IPC general) | J28: tipo | K28: 0.00065753919 | L28: 0.057032015 | M28: delta (OLS clasico) | N28: 0.0115293 | O28: 0.99080115 | P28: 0.99189545 | Q28: BH | R28: -0.11112521 | S28: 0.11244029 | T28: 0.0069807824 | V28: 113 | W28: 0.31575678 | X28: 0.27702603 | Y28: -582.91065 | Z28: -563.81894 | AA28: -0.017257219 | AB28: 39.818057 | AC28: 0.1 | AD28: 1.6662665e-18 | AE28: 0.034617396 | AF28: 0.32078518 | AG28: 0.21544114 | AH28: 1 | AI28: 1.2670878 | AM28: C4 | AQ28: no_evaluable | AR28: no_evaluable | AS28: si | AT28: (b) mejor de la familia dols/fmols/ardl: especificacion C1 de menor RMSE (ECM); el OOS se hace con beta OLS estatico y es comun a los tres estimadores; NO CUMPLE LA REGLA (§8 y multiverso) en ninguna variable; RMSE 1.407 vs AR(4) 1.283 (peor que AR(4)) | AU28: src/v8/m4_largo_plazo.py | AV28: (b) mejor de la familia dols/fmols/ardl: especificacion C1 de menor RMSE (ECM); el OOS se hace con beta OLS estatico y es comun a los tres estimadores | AW28: M4:C1_sin_rupturas_ECM | AX28: si | AY28: output/v8/M4/coeficientes.csv | AZ28: =Fuera_muestra!F22 | BA28: =Fuera_muestra!G22 | BB28: =AZ28/BA28
A29: M4_compra_C1_sin_rupturas_dols | B29: M4 | C29: dols | D29: compra | E29: nacional | F29: completo | G29: ln_p_tasado_real | H29: ln niveles; tipo en pp | I29: valor tasado MIVAU, real (IPC general) | J29: renta | K29: 0.68815749 | L29: 0.30112114 | M29: HAC-NW(4) | N29: 2.2853177 | O29: 0.022294204 | P29: 0.063974671 | Q29: BH | R29: 0.097970893 | S29: 1.2783441 | T29: 0.44649733 | U29: 0.68815749 | V29: 113 | W29: 0.20013756 | X29: 0.13860968 | Y29: -65.141199 | Z29: -40.594708 | AA29: -0.016358797 | AB29: 42.023998 | AC29: 0.62515886 | AD29: 1.1307661e-72 | AE29: 0.80967642 | AF29: 0.00031753395 | AG29: 3.4334947e-08 | AH29: 0 | AI29: 1.2670878 | AM29: C4 | AQ29: no_evaluable | AR29: no_evaluable | AS29: si | AT29: (b) mejor de la familia dols/fmols/ardl: especificacion C1 de menor RMSE (ECM); el OOS se hace con beta OLS estatico y es comun a los tres estimadores; NO CUMPLE LA REGLA (§8 y multiverso) en ninguna variable; RMSE 1.407 vs AR(4) 1.283 (peor que AR(4)) | AU29: src/v8/m4_largo_plazo.py | AV29: (b) mejor de la familia dols/fmols/ardl: especificacion C1 de menor RMSE (ECM); el OOS se hace con beta OLS estatico y es comun a los tres estimadores | AW29: M4:C1_sin_rupturas_ECM | AX29: si | AY29: output/v8/M4/coeficientes.csv | AZ29: =Fuera_muestra!F22 | BA29: =Fuera_muestra!G22 | BB29: =AZ29/BA29
A30: M4_compra_C1_sin_rupturas_dols | B30: M4 | C30: dols | D30: compra | E30: nacional | F30: completo | G30: ln_p_tasado_real | H30: ln niveles; tipo en pp | I30: valor tasado MIVAU, real (IPC general) | J30: tipo | K30: 0.0059963734 | L30: 0.019582482 | M30: HAC-NW(4) | N30: 0.3062111 | O30: 0.75944392 | P30: 0.8553464 | Q30: BH | R30: -0.032384587 | S30: 0.044377334 | T30: 0.063660659 | V30: 113 | W30: 0.20013756 | X30: 0.13860968 | Y30: -65.141199 | Z30: -40.594708 | AA30: -0.016358797 | AB30: 42.023998 | AC30: 0.62515886 | AD30: 1.1307661e-72 | AE30: 0.80967642 | AF30: 0.00031753395 | AG30: 3.4334947e-08 | AH30: 0 | AI30: 1.2670878 | AM30: C4 | AQ30: no_evaluable | AR30: no_evaluable | AS30: si | AT30: (b) mejor de la familia dols/fmols/ardl: especificacion C1 de menor RMSE (ECM); el OOS se hace con beta OLS estatico y es comun a los tres estimadores; NO CUMPLE LA REGLA (§8 y multiverso) en ninguna variable; RMSE 1.407 vs AR(4) 1.283 (peor que AR(4)) | AU30: src/v8/m4_largo_plazo.py | AV30: (b) mejor de la familia dols/fmols/ardl: especificacion C1 de menor RMSE (ECM); el OOS se hace con beta OLS estatico y es comun a los tres estimadores | AW30: M4:C1_sin_rupturas_ECM | AX30: si | AY30: output/v8/M4/coeficientes.csv | AZ30: =Fuera_muestra!F22 | BA30: =Fuera_muestra!G22 | BB30: =AZ30/BA30
A31: M4_compra_C1_sin_rupturas_fmols | B31: M4 | C31: fmols | D31: compra | E31: nacional | F31: completo | G31: ln_p_tasado_real | H31: ln niveles; tipo en pp | I31: valor tasado MIVAU, real (IPC general) | J31: renta | K31: 0.61837276 | L31: 0.3257678 | M31: FMOLS Omega_u.e (Bartlett) | N31: 1.898201 | O31: 0.057669612 | P31: 0.13782796 | Q31: BH | R31: -0.020132131 | S31: 1.2568777 | T31: 0.4012189 | U31: 0.61837276 | V31: 112 | W31: 0.1572982 | X31: 0.14183578 | Y31: -392.50463 | Z31: -384.34913 | AA31: -0.016724123 | AB31: 41.098403 | AC31: 0.62515886 | AD31: 6.6502279e-81 | AE31: 0.37435497 | AF31: 0.00053782407 | AG31: 0.019327627 | AH31: 0 | AI31: 1.2670878 | AM31: C4 | AQ31: no_evaluable | AR31: no_evaluable | AS31: si | AT31: (b) mejor de la familia dols/fmols/ardl: especificacion C1 de menor RMSE (ECM); el OOS se hace con beta OLS estatico y es comun a los tres estimadores; NO CUMPLE LA REGLA (§8 y multiverso) en ninguna variable; RMSE 1.407 vs AR(4) 1.283 (peor que AR(4)) | AU31: src/v8/m4_largo_plazo.py | AV31: (b) mejor de la familia dols/fmols/ardl: especificacion C1 de menor RMSE (ECM); el OOS se hace con beta OLS estatico y es comun a los tres estimadores | AW31: M4:C1_sin_rupturas_ECM | AX31: si | AY31: output/v8/M4/coeficientes.csv | AZ31: =Fuera_muestra!F22 | BA31: =Fuera_muestra!G22 | BB31: =AZ31/BA31
A32: M4_compra_C1_sin_rupturas_fmols | B32: M4 | C32: fmols | D32: compra | E32: nacional | F32: completo | G32: ln_p_tasado_real | H32: ln niveles; tipo en pp | I32: valor tasado MIVAU, real (IPC general) | J32: tipo | K32: 0.0040101428 | L32: 0.019564575 | M32: FMOLS Omega_u.e (Bartlett) | N32: 0.20496959 | O32: 0.83759589 | P32: 0.90479941 | Q32: BH | R32: -0.034336424 | S32: 0.04235671 | T32: 0.042573789 | V32: 112 | W32: 0.1572982 | X32: 0.14183578 | Y32: -392.50463 | Z32: -384.34913 | AA32: -0.016724123 | AB32: 41.098403 | AC32: 0.62515886 | AD32: 6.6502279e-81 | AE32: 0.37435497 | AF32: 0.00053782407 | AG32: 0.019327627 | AH32: 0 | AI32: 1.2670878 | AM32: C4 | AQ32: no_evaluable | AR32: no_evaluable | AS32: si | AT32: (b) mejor de la familia dols/fmols/ardl: especificacion C1 de menor RMSE (ECM); el OOS se hace con beta OLS estatico y es comun a los tres estimadores; NO CUMPLE LA REGLA (§8 y multiverso) en ninguna variable; RMSE 1.407 vs AR(4) 1.283 (peor que AR(4)) | AU32: src/v8/m4_largo_plazo.py | AV32: (b) mejor de la familia dols/fmols/ardl: especificacion C1 de menor RMSE (ECM); el OOS se hace con beta OLS estatico y es comun a los tres estimadores | AW32: M4:C1_sin_rupturas_ECM | AX32: si | AY32: output/v8/M4/coeficientes.csv | AZ32: =Fuera_muestra!F22 | BA32: =Fuera_muestra!G22 | BB32: =AZ32/BA32
A33: M6_ols_compra_trimestral_completo | B33: M6 | C33: ols_familias | D33: compra | E33: nacional | F33: completo | G33: d_ln_tasado_real | H33: trimestral | I33: tasado | J33: const | K33: -0.70338909 | L33: 0.47222358 | M33: EWC | N33: -1.4895256 | O33: 0.17467738 | P33: 0.29360667 | Q33: BH | R33: -1.7923386 | S33: 0.38556043 | V33: 96 | W33: 0.46568303 | X33: 0.42318055 | Y33: 361.168 | Z33: 381.68278 | AD33: 1.1624361e-09 | AE33: 0.027089553 | AF33: 0.0063835048 | AG33: 0.17232653 | AH33: 0 | AI33: 1.1057624 | AM33: C4 | AQ33: no_evaluable | AR33: no_evaluable | AS33: si | AT33: (b) mejor de la familia ols_familias: ols_factores trimestral, periodo completo; NO CUMPLE LA REGLA (§8 y multiverso) en ninguna variable; RMSE 2.830 vs AR(4) 1.038 (peor que AR(4)) | AU33: src/v8/m6_colinealidad.py | AV33: (b) mejor de la familia ols_familias: ols_factores trimestral, periodo completo | AW33: M6:ols_factores | AX33: si | AY33: output/v8/M6/coeficientes.csv | AZ33: =Fuera_muestra!F49 | BA33: =Fuera_muestra!G49 | BB33: =AZ33/BA33
A34: M6_ols_compra_trimestral_completo | B34: M6 | C34: ols_familias | D34: compra | E34: nacional | F34: completo | G34: d_ln_tasado_real | H34: trimestral | I34: tasado | J34: hogares_epa | K34: 1.9795045 | L34: 1.0987707 | M34: EWC | N34: 1.8015628 | O34: 0.10929162 | P34: 0.20557234 | Q34: BH | R34: -0.55426535 | S34: 4.5132744 | T34: 0.27764163 | U34: 1.9795045 | V34: 96 | W34: 0.46568303 | X34: 0.42318055 | Y34: 361.168 | Z34: 381.68278 | AD34: 1.1624361e-09 | AE34: 0.027089553 | AF34: 0.0063835048 | AG34: 0.17232653 | AH34: 0 | AI34: 1.1057624 | AM34: C4 | AN34: 1152 | AO34: 0.72222222 | AP34: 0.2109375 | AQ34: no_evaluable | AR34: no | AS34: si | AT34: (b) mejor de la familia ols_familias: ols_factores trimestral, periodo completo; NO CUMPLE LA REGLA (§8 y multiverso) en ninguna variable; RMSE 2.830 vs AR(4) 1.038 (peor que AR(4)) | AU34: src/v8/m6_colinealidad.py | AV34: (b) mejor de la familia ols_familias: ols_factores trimestral, periodo completo | AW34: M6:ols_factores | AX34: si | AY34: output/v8/M6/coeficientes.csv | AZ34: =Fuera_muestra!F49 | BA34: =Fuera_muestra!G49 | BB34: =AZ34/BA34
A35: M6_ols_compra_trimestral_completo | B35: M6 | C35: ols_familias | D35: compra | E35: nacional | F35: completo | G35: d_ln_tasado_real | H35: trimestral | I35: tasado | J35: pib_vol | K35: 0.080293891 | L35: 0.030005919 | M35: EWC | N35: 2.6759351 | O35: 0.028102498 | P35: 0.076295772 | Q35: BH | R35: 0.011100118 | S35: 0.14948766 | T35: 0.10718294 | U35: 0.080293891 | V35: 96 | W35: 0.46568303 | X35: 0.42318055 | Y35: 361.168 | Z35: 381.68278 | AD35: 1.1624361e-09 | AE35: 0.027089553 | AF35: 0.0063835048 | AG35: 0.17232653 | AH35: 0 | AI35: 1.1057624 | AM35: C4 | AN35: 1152 | AO35: 0.88715278 | AP35: 0.22395833 | AQ35: no_evaluable | AR35: no | AS35: si | AT35: (b) mejor de la familia ols_familias: ols_factores trimestral, periodo completo; NO CUMPLE LA REGLA (§8 y multiverso) en ninguna variable; RMSE 2.830 vs AR(4) 1.038 (peor que AR(4)) | AU35: src/v8/m6_colinealidad.py | AV35: (b) mejor de la familia ols_familias: ols_factores trimestral, periodo completo | AW35: M6:ols_factores | AX35: si | AY35: output/v8/M6/coeficientes.csv | AZ35: =Fuera_muestra!F49 | BA35: =Fuera_muestra!G49 | BB35: =AZ35/BA35
A36: M6_ols_compra_trimestral_completo | B36: M6 | C36: ols_familias | D36: compra | E36: nacional | F36: completo | G36: d_ln_tasado_real | H36: trimestral | I36: tasado | J36: tipo_hip_real | K36: -0.032704484 | L36: 0.093515867 | M36: EWC | N36: -0.34972123 | O36: 0.73557599 | P36: 0.7960343 | Q36: BH | R36: -0.24835246 | S36: 0.18294349 | T36: -0.032546979 | V36: 96 | W36: 0.46568303 | X36: 0.42318055 | Y36: 361.168 | Z36: 381.68278 | AD36: 1.1624361e-09 | AE36: 0.027089553 | AF36: 0.0063835048 | AG36: 0.17232653 | AH36: 0 | AI36: 1.1057624 | AM36: C4 | AN36: 1152 | AO36: 0.75520833 | AP36: 0.36371528 | AQ36: no_evaluable | AR36: no | AS36: si | AT36: (b) mejor de la familia ols_familias: ols_factores trimestral, periodo completo; NO CUMPLE LA REGLA (§8 y multiverso) en ninguna variable; RMSE 2.830 vs AR(4) 1.038 (peor que AR(4)) | AU36: src/v8/m6_colinealidad.py | AV36: (b) mejor de la familia ols_familias: ols_factores trimestral, periodo completo | AW36: M6:ols_factores | AX36: si | AY36: output/v8/M6/coeficientes.csv | AZ36: =Fuera_muestra!F49 | BA36: =Fuera_muestra!G49 | BB36: =AZ36/BA36
A37: M6_ols_compra_trimestral_completo | B37: M6 | C37: ols_familias | D37: compra | E37: nacional | F37: completo | G37: d_ln_tasado_real | H37: trimestral | I37: tasado | J37: terminadas | K37: 0.0048216501 | L37: 0.0086248354 | M37: EWC | N37: 0.55904256 | O37: 0.5914339 | P37: 0.69736236 | Q37: BH | R37: -0.015067256 | S37: 0.024710556 | T37: 0.04191819 | U37: 0.0048216501 | V37: 96 | W37: 0.46568303 | X37: 0.42318055 | Y37: 361.168 | Z37: 381.68278 | AD37: 1.1624361e-09 | AE37: 0.027089553 | AF37: 0.0063835048 | AG37: 0.17232653 | AH37: 0 | AI37: 1.1057624 | AM37: C4 | AN37: 1152 | AO37: 0.76736111 | AP37: 0.43142361 | AQ37: no_evaluable | AR37: no | AS37: si | AT37: (b) mejor de la familia ols_familias: ols_factores trimestral, periodo completo; NO CUMPLE LA REGLA (§8 y multiverso) en ninguna variable; RMSE 2.830 vs AR(4) 1.038 (peor que AR(4)) | AU37: src/v8/m6_colinealidad.py | AV37: (b) mejor de la familia ols_familias: ols_factores trimestral, periodo completo | AW37: M6:ols_factores | AX37: si | AY37: output/v8/M6/coeficientes.csv | AZ37: =Fuera_muestra!F49 | BA37: =Fuera_muestra!G49 | BB37: =AZ37/BA37
A38: M6_ols_compra_trimestral_completo | B38: M6 | C38: ols_familias | D38: compra | E38: nacional | F38: completo | G38: d_ln_tasado_real | H38: trimestral | I38: tasado | J38: bis_hpi_xm_real | K38: 1.0851875 | L38: 0.35207371 | M38: EWC | N38: 3.0822737 | O38: 0.015064902 | P38: 0.050231711 | Q38: BH | R38: 0.27330411 | S38: 1.897071 | T38: 0.59808777 | U38: 1.0851875 | V38: 96 | W38: 0.46568303 | X38: 0.42318055 | Y38: 361.168 | Z38: 381.68278 | AD38: 1.1624361e-09 | AE38: 0.027089553 | AF38: 0.0063835048 | AG38: 0.17232653 | AH38: 0 | AI38: 1.1057624 | AM38: C4 | AN38: 960 | AO38: 0.71458333 | AP38: 0.346875 | AQ38: no_evaluable | AR38: no | AS38: si | AT38: (b) mejor de la familia ols_familias: ols_factores trimestral, periodo completo; NO CUMPLE LA REGLA (§8 y multiverso) en ninguna variable; RMSE 2.830 vs AR(4) 1.038 (peor que AR(4)) | AU38: src/v8/m6_colinealidad.py | AV38: (b) mejor de la familia ols_familias: ols_factores trimestral, periodo completo | AW38: M6:ols_factores | AX38: si | AY38: output/v8/M6/coeficientes.csv | AZ38: =Fuera_muestra!F49 | BA38: =Fuera_muestra!G49 | BB38: =AZ38/BA38
A39: M6_ols_compra_trimestral_completo | B39: M6 | C39: ols_familias | D39: compra | E39: nacional | F39: completo | G39: d_ln_tasado_real | H39: trimestral | I39: tasado | J39: covid | K39: -1.3751379 | L39: 0.37665158 | M39: EWC | N39: -3.6509549 | O39: 0.0064854075 | P39: 0.03543864 | Q39: BH | R39: -2.243698 | S39: -0.50657784 | T39: -0.11974596 | V39: 96 | W39: 0.46568303 | X39: 0.42318055 | Y39: 361.168 | Z39: 381.68278 | AD39: 1.1624361e-09 | AE39: 0.027089553 | AF39: 0.0063835048 | AG39: 0.17232653 | AH39: 0 | AI39: 1.1057624 | AM39: C4 | AQ39: no_evaluable | AR39: no_evaluable | AS39: si | AT39: (b) mejor de la familia ols_familias: ols_factores trimestral, periodo completo; NO CUMPLE LA REGLA (§8 y multiverso) en ninguna variable; RMSE 2.830 vs AR(4) 1.038 (peor que AR(4)) | AU39: src/v8/m6_colinealidad.py | AV39: (b) mejor de la familia ols_familias: ols_factores trimestral, periodo completo | AW39: M6:ols_factores | AX39: si | AY39: output/v8/M6/coeficientes.csv | AZ39: =Fuera_muestra!F49 | BA39: =Fuera_muestra!G49 | BB39: =AZ39/BA39
A40: M6_ols_compra_trimestral_completo | B40: M6 | C40: ols_familias | D40: compra | E40: nacional | F40: completo | G40: d_ln_tasado_real | H40: trimestral | I40: tasado | J40: epa2021_q | K40: 2.2482144 | L40: 1.5551236 | M40: EWC | N40: 1.4456822 | O40: 0.18627618 | P40: 0.30867695 | Q40: BH | R40: -1.337907 | S40: 5.8343357 | T40: 0.11423838 | V40: 96 | W40: 0.46568303 | X40: 0.42318055 | Y40: 361.168 | Z40: 381.68278 | AD40: 1.1624361e-09 | AE40: 0.027089553 | AF40: 0.0063835048 | AG40: 0.17232653 | AH40: 0 | AI40: 1.1057624 | AM40: C4 | AQ40: no_evaluable | AR40: no_evaluable | AS40: si | AT40: (b) mejor de la familia ols_familias: ols_factores trimestral, periodo completo; NO CUMPLE LA REGLA (§8 y multiverso) en ninguna variable; RMSE 2.830 vs AR(4) 1.038 (peor que AR(4)) | AU40: src/v8/m6_colinealidad.py | AV40: (b) mejor de la familia ols_familias: ols_factores trimestral, periodo completo | AW40: M6:ols_factores | AX40: si | AY40: output/v8/M6/coeficientes.csv | AZ40: =Fuera_muestra!F49 | BA40: =Fuera_muestra!G49 | BB40: =AZ40/BA40
A41: M0_alquiler_base_P1 | B41: M0 | C41: ols_tramos_hac | D41: alquiler | E41: nacional | F41: P1 | G41: d4_ln_ipc_alquiler_real | H41: d4_ln*100 | I41: IPC alquiler, real (IPC general) | J41: d4_pob_total | K41: -2.9584199 | L41: 1.1565262 | M41: HAC-NW(4), t(14) | N41: -2.5580223 | O41: 0.022760405 | P41: 0.048279648 | Q41: BH | R41: -5.4389219 | S41: -0.47791782 | T41: -0.63303495 | V41: 20 | W41: 0.84384788 | X41: 0.78807926 | Y41: 8.6243442 | Z41: 14.598738 | AM41: C4 | AN41: 96 | AO41: 0.60416667 | AP41: 0.041666667 | AQ41: no_evaluable | AR41: no | AS41: si | AT41: (b) mejor de la familia ols_tramos_hac: ecuacion AR1+X por periodo; unico candidato con OOS en la familia; NO CUMPLE LA REGLA (§8 y multiverso) en ninguna variable; RMSE 1.815 vs AR(4) 0.800 (peor que AR(4)) | AU41: src/v8/m0_periodos.py | AV41: (b) mejor de la familia ols_tramos_hac: ecuacion AR1+X por periodo; unico candidato con OOS en la familia | AW41: M0:AR1+X_por_periodo | AX41: si | AY41: output/v8/M0/coeficientes.csv | AZ41: =Fuera_muestra!F19 | BA41: =Fuera_muestra!G19 | BB41: =AZ41/BA41
A42: M0_alquiler_base_P1 | B42: M0 | C42: ols_tramos_hac | D42: alquiler | E42: nacional | F42: P1 | G42: d4_ln_ipc_alquiler_real | H42: d4_ln*100 | I42: IPC alquiler, real (IPC general) | J42: d4_pib_vol | K42: -0.96054979 | L42: 0.14182911 | M42: HAC-NW(4), t(14) | N42: -6.7725856 | O42: 8.9854917e-06 | P42: 6.9887158e-05 | Q42: BH | R42: -1.264743 | S42: -0.6563566 | T42: -0.71583018 | V42: 20 | W42: 0.84384788 | X42: 0.78807926 | Y42: 8.6243442 | Z42: 14.598738 | AM42: C4 | AN42: 96 | AO42: 0.5 | AP42: 0.052083333 | AQ42: no_evaluable | AR42: no | AS42: si | AT42: (b) mejor de la familia ols_tramos_hac: ecuacion AR1+X por periodo; unico candidato con OOS en la familia; NO CUMPLE LA REGLA (§8 y multiverso) en ninguna variable; RMSE 1.815 vs AR(4) 0.800 (peor que AR(4)) | AU42: src/v8/m0_periodos.py | AV42: (b) mejor de la familia ols_tramos_hac: ecuacion AR1+X por periodo; unico candidato con OOS en la familia | AW42: M0:AR1+X_por_periodo | AX42: si | AY42: output/v8/M0/coeficientes.csv | AZ42: =Fuera_muestra!F19 | BA42: =Fuera_muestra!G19 | BB42: =AZ42/BA42
A43: M0_alquiler_base_P1 | B43: M0 | C43: ols_tramos_hac | D43: alquiler | E43: nacional | F43: P1 | G43: d4_ln_ipc_alquiler_real | H43: d4_ln*100 | I43: IPC alquiler, real (IPC general) | J43: tipo_hip_real | K43: 0.6246276 | L43: 0.070271292 | M43: HAC-NW(4), t(14) | N43: 8.888802 | O43: 3.9356327e-07 | P43: 3.9356327e-06 | Q43: BH | R43: 0.47391066 | S43: 0.77534453 | T43: 1.1277245 | V43: 20 | W43: 0.84384788 | X43: 0.78807926 | Y43: 8.6243442 | Z43: 14.598738 | AM43: C4 | AN43: 96 | AO43: 0.60416667 | AP43: 0.26041667 | AQ43: no_evaluable | AR43: no | AS43: si | AT43: (b) mejor de la familia ols_tramos_hac: ecuacion AR1+X por periodo; unico candidato con OOS en la familia; NO CUMPLE LA REGLA (§8 y multiverso) en ninguna variable; RMSE 1.815 vs AR(4) 0.800 (peor que AR(4)) | AU43: src/v8/m0_periodos.py | AV43: (b) mejor de la familia ols_tramos_hac: ecuacion AR1+X por periodo; unico candidato con OOS en la familia | AW43: M0:AR1+X_por_periodo | AX43: si | AY43: output/v8/M0/coeficientes.csv | AZ43: =Fuera_muestra!F19 | BA43: =Fuera_muestra!G19 | BB43: =AZ43/BA43
A44: M0_alquiler_base_P1 | B44: M0 | C44: ols_tramos_hac | D44: alquiler | E44: nacional | F44: P1 | G44: d4_ln_ipc_alquiler_real | H44: d4_ln*100 | I44: IPC alquiler, real (IPC general) | J44: d4_credito_vivienda_real | K44: 0.06539416 | L44: 0.018063791 | M44: HAC-NW(4), t(14) | N44: 3.6201791 | O44: 0.0027847436 | P44: 0.0081221688 | Q44: BH | R44: 0.026651181 | S44: 0.10413714 | T44: 0.62812287 | V44: 20 | W44: 0.84384788 | X44: 0.78807926 | Y44: 8.6243442 | Z44: 14.598738 | AM44: C4 | AQ44: no_evaluable | AR44: no_evaluable | AS44: si | AT44: (b) mejor de la familia ols_tramos_hac: ecuacion AR1+X por periodo; unico candidato con OOS en la familia; NO CUMPLE LA REGLA (§8 y multiverso) en ninguna variable; RMSE 1.815 vs AR(4) 0.800 (peor que AR(4)) | AU44: src/v8/m0_periodos.py | AV44: (b) mejor de la familia ols_tramos_hac: ecuacion AR1+X por periodo; unico candidato con OOS en la familia | AW44: M0:AR1+X_por_periodo | AX44: si | AY44: output/v8/M0/coeficientes.csv | AZ44: =Fuera_muestra!F19 | BA44: =Fuera_muestra!G19 | BB44: =AZ44/BA44
A45: M0_alquiler_base_P1 | B45: M0 | C45: ols_tramos_hac | D45: alquiler | E45: nacional | F45: P1 | G45: d4_ln_ipc_alquiler_real | H45: d4_ln*100 | I45: IPC alquiler, real (IPC general) | J45: d4_terminadas | K45: -0.036619769 | L45: 0.019714341 | M45: HAC-NW(4), t(14) | N45: -1.8575193 | O45: 0.084395575 | P45: 0.14409001 | Q45: BH | R45: -0.078902825 | S45: 0.0056632867 | T45: -0.42146555 | V45: 20 | W45: 0.84384788 | X45: 0.78807926 | Y45: 8.6243442 | Z45: 14.598738 | AM45: C4 | AN45: 96 | AO45: 0.70833333 | AP45: 0.083333333 | AQ45: no_evaluable | AR45: no | AS45: si | AT45: (b) mejor de la familia ols_tramos_hac: ecuacion AR1+X por periodo; unico candidato con OOS en la familia; NO CUMPLE LA REGLA (§8 y multiverso) en ninguna variable; RMSE 1.815 vs AR(4) 0.800 (peor que AR(4)) | AU45: src/v8/m0_periodos.py | AV45: (b) mejor de la familia ols_tramos_hac: ecuacion AR1+X por periodo; unico candidato con OOS en la familia | AW45: M0:AR1+X_por_periodo | AX45: si | AY45: output/v8/M0/coeficientes.csv | AZ45: =Fuera_muestra!F19 | BA45: =Fuera_muestra!G19 | BB45: =AZ45/BA45
A46: M0_alquiler_base_P2 | B46: M0 | C46: ols_tramos_hac | D46: alquiler | E46: nacional | F46: P2 | G46: d4_ln_ipc_alquiler_real | H46: d4_ln*100 | I46: IPC alquiler, real (IPC general) | J46: d4_pob_total | K46: -1.452668 | L46: 0.69518343 | M46: HAC-NW(4), t(16) | N46: -2.0896183 | O46: 0.052979836 | P46: 0.10301635 | Q46: BH | R46: -2.9263911 | S46: 0.021055005 | T46: -0.38331367 | V46: 22 | W46: 0.97528633 | X46: 0.96756331 | Y46: 25.030347 | Z46: 31.576601 | AM46: C4 | AN46: 96 | AO46: 1 | AP46: 0.82291667 | AQ46: no_evaluable | AR46: sí | AS46: si | AT46: (b) mejor de la familia ols_tramos_hac: ecuacion AR1+X por periodo; unico candidato con OOS en la familia; NO CUMPLE LA REGLA (§8 y multiverso) en ninguna variable; RMSE 1.815 vs AR(4) 0.800 (peor que AR(4)) | AU46: src/v8/m0_periodos.py | AV46: (b) mejor de la familia ols_tramos_hac: ecuacion AR1+X por periodo; unico candidato con OOS en la familia | AW46: M0:AR1+X_por_periodo | AX46: si | AY46: output/v8/M0/coeficientes.csv | AZ46: =Fuera_muestra!F19 | BA46: =Fuera_muestra!G19 | BB46: =AZ46/BA46
A47: M0_alquiler_base_P2 | B47: M0 | C47: ols_tramos_hac | D47: alquiler | E47: nacional | F47: P2 | G47: d4_ln_ipc_alquiler_real | H47: d4_ln*100 | I47: IPC alquiler, real (IPC general) | J47: d4_pib_vol | K47: -0.4127992 | L47: 0.069479297 | M47: HAC-NW(4), t(16) | N47: -5.9413267 | O47: 2.0699109e-05 | P47: 0.0001207448 | Q47: BH | R47: -0.56008873 | S47: -0.26550967 | T47: -0.31322051 | V47: 22 | W47: 0.97528633 | X47: 0.96756331 | Y47: 25.030347 | Z47: 31.576601 | AM47: C4 | AN47: 96 | AO47: 0.5625 | AP47: 0.1875 | AQ47: no_evaluable | AR47: no | AS47: si | AT47: (b) mejor de la familia ols_tramos_hac: ecuacion AR1+X por periodo; unico candidato con OOS en la familia; NO CUMPLE LA REGLA (§8 y multiverso) en ninguna variable; RMSE 1.815 vs AR(4) 0.800 (peor que AR(4)) | AU47: src/v8/m0_periodos.py | AV47: (b) mejor de la familia ols_tramos_hac: ecuacion AR1+X por periodo; unico candidato con OOS en la familia | AW47: M0:AR1+X_por_periodo | AX47: si | AY47: output/v8/M0/coeficientes.csv | AZ47: =Fuera_muestra!F19 | BA47: =Fuera_muestra!G19 | BB47: =AZ47/BA47
A48: M0_alquiler_base_P2 | B48: M0 | C48: ols_tramos_hac | D48: alquiler | E48: nacional | F48: P2 | G48: d4_ln_ipc_alquiler_real | H48: d4_ln*100 | I48: IPC alquiler, real (IPC general) | J48: tipo_hip_real | K48: 0.52182825 | L48: 0.086523723 | M48: HAC-NW(4), t(16) | N48: 6.0310425 | O48: 1.7467844e-05 | P48: 0.00011115901 | Q48: BH | R48: 0.33840615 | S48: 0.70525035 | T48: 0.3489817 | V48: 22 | W48: 0.97528633 | X48: 0.96756331 | Y48: 25.030347 | Z48: 31.576601 | AM48: C4 | AN48: 96 | AO48: 0.75 | AP48: 0.3125 | AQ48: no_evaluable | AR48: no | AS48: si | AT48: (b) mejor de la familia ols_tramos_hac: ecuacion AR1+X por periodo; unico candidato con OOS en la familia; NO CUMPLE LA REGLA (§8 y multiverso) en ninguna variable; RMSE 1.815 vs AR(4) 0.800 (peor que AR(4)) | AU48: src/v8/m0_periodos.py | AV48: (b) mejor de la familia ols_tramos_hac: ecuacion AR1+X por periodo; unico candidato con OOS en la familia | AW48: M0:AR1+X_por_periodo | AX48: si | AY48: output/v8/M0/coeficientes.csv | AZ48: =Fuera_muestra!F19 | BA48: =Fuera_muestra!G19 | BB48: =AZ48/BA48
A49: M0_alquiler_base_P2 | B49: M0 | C49: ols_tramos_hac | D49: alquiler | E49: nacional | F49: P2 | G49: d4_ln_ipc_alquiler_real | H49: d4_ln*100 | I49: IPC alquiler, real (IPC general) | J49: d4_credito_vivienda_real | K49: 0.67808281 | L49: 0.13248464 | M49: HAC-NW(4), t(16) | N49: 5.1181995 | O49: 0.0001031923 | P49: 0.00051596148 | Q49: BH | R49: 0.39722792 | S49: 0.9589377 | T49: 0.95750078 | V49: 22 | W49: 0.97528633 | X49: 0.96756331 | Y49: 25.030347 | Z49: 31.576601 | AM49: C4 | AQ49: no_evaluable | AR49: no_evaluable | AS49: si | AT49: (b) mejor de la familia ols_tramos_hac: ecuacion AR1+X por periodo; unico candidato con OOS en la familia; NO CUMPLE LA REGLA (§8 y multiverso) en ninguna variable; RMSE 1.815 vs AR(4) 0.800 (peor que AR(4)) | AU49: src/v8/m0_periodos.py | AV49: (b) mejor de la familia ols_tramos_hac: ecuacion AR1+X por periodo; unico candidato con OOS en la familia | AW49: M0:AR1+X_por_periodo | AX49: si | AY49: output/v8/M0/coeficientes.csv | AZ49: =Fuera_muestra!F19 | BA49: =Fuera_muestra!G19 | BB49: =AZ49/BA49
A50: M0_alquiler_base_P2 | B50: M0 | C50: ols_tramos_hac | D50: alquiler | E50: nacional | F50: P2 | G50: d4_ln_ipc_alquiler_real | H50: d4_ln*100 | I50: IPC alquiler, real (IPC general) | J50: d4_terminadas | K50: -0.0039423586 | L50: 0.0072638507 | M50: HAC-NW(4), t(16) | N50: -0.54273674 | O50: 0.59479127 | P50: 0.66087919 | Q50: BH | R50: -0.019341034 | S50: 0.011456317 | T50: -0.031974329 | V50: 22 | W50: 0.97528633 | X50: 0.96756331 | Y50: 25.030347 | Z50: 31.576601 | AM50: C4 | AN50: 96 | AO50: 0.58333333 | AP50: 0.125 | AQ50: no_evaluable | AR50: no | AS50: si | AT50: (b) mejor de la familia ols_tramos_hac: ecuacion AR1+X por periodo; unico candidato con OOS en la familia; NO CUMPLE LA REGLA (§8 y multiverso) en ninguna variable; RMSE 1.815 vs AR(4) 0.800 (peor que AR(4)) | AU50: src/v8/m0_periodos.py | AV50: (b) mejor de la familia ols_tramos_hac: ecuacion AR1+X por periodo; unico candidato con OOS en la familia | AW50: M0:AR1+X_por_periodo | AX50: si | AY50: output/v8/M0/coeficientes.csv | AZ50: =Fuera_muestra!F19 | BA50: =Fuera_muestra!G19 | BB50: =AZ50/BA50
A51: M0_alquiler_base_P3 | B51: M0 | C51: ols_tramos_hac | D51: alquiler | E51: nacional | F51: P3 | G51: d4_ln_ipc_alquiler_real | H51: d4_ln*100 | I51: IPC alquiler, real (IPC general) | J51: d4_pob_total | K51: 1.8343955 | L51: 0.19306097 | M51: HAC-NW(4), t(18) | N51: 9.5016387 | O51: 1.949814e-08 | P51: 2.8580378e-07 | Q51: BH | R51: 1.4287895 | S51: 2.2400016 | T51: 0.75761446 | V51: 24 | W51: 0.96694959 | X51: 0.95776892 | Y51: -9.0918435 | Z51: -2.0235205 | AM51: C4 | AN51: 96 | AO51: 0.89583333 | AP51: 0.20833333 | AQ51: no_evaluable | AR51: no | AS51: si | AT51: (b) mejor de la familia ols_tramos_hac: ecuacion AR1+X por periodo; unico candidato con OOS en la familia; NO CUMPLE LA REGLA (§8 y multiverso) en ninguna variable; RMSE 1.815 vs AR(4) 0.800 (peor que AR(4)) | AU51: src/v8/m0_periodos.py | AV51: (b) mejor de la familia ols_tramos_hac: ecuacion AR1+X por periodo; unico candidato con OOS en la familia | AW51: M0:AR1+X_por_periodo | AX51: si | AY51: output/v8/M0/coeficientes.csv | AZ51: =Fuera_muestra!F19 | BA51: =Fuera_muestra!G19 | BB51: =AZ51/BA51
A52: M0_alquiler_base_P3 | B52: M0 | C52: ols_tramos_hac | D52: alquiler | E52: nacional | F52: P3 | G52: d4_ln_ipc_alquiler_real | H52: d4_ln*100 | I52: IPC alquiler, real (IPC general) | J52: d4_pib_vol | K52: 0.11664641 | L52: 0.059762104 | M52: HAC-NW(4), t(18) | N52: 1.9518457 | O52: 0.066692451 | P52: 0.12285452 | Q52: BH | R52: -0.0089091139 | S52: 0.24220193 | T52: 0.12351905 | V52: 24 | W52: 0.96694959 | X52: 0.95776892 | Y52: -9.0918435 | Z52: -2.0235205 | AM52: C4 | AN52: 96 | AO52: 0.54166667 | AP52: 0.020833333 | AQ52: no_evaluable | AR52: no | AS52: si | AT52: (b) mejor de la familia ols_tramos_hac: ecuacion AR1+X por periodo; unico candidato con OOS en la familia; NO CUMPLE LA REGLA (§8 y multiverso) en ninguna variable; RMSE 1.815 vs AR(4) 0.800 (peor que AR(4)) | AU52: src/v8/m0_periodos.py | AV52: (b) mejor de la familia ols_tramos_hac: ecuacion AR1+X por periodo; unico candidato con OOS en la familia | AW52: M0:AR1+X_por_periodo | AX52: si | AY52: output/v8/M0/coeficientes.csv | AZ52: =Fuera_muestra!F19 | BA52: =Fuera_muestra!G19 | BB52: =AZ52/BA52
A53: M0_alquiler_base_P3 | B53: M0 | C53: ols_tramos_hac | D53: alquiler | E53: nacional | F53: P3 | G53: d4_ln_ipc_alquiler_real | H53: d4_ln*100 | I53: IPC alquiler, real (IPC general) | J53: tipo_hip_real | K53: 0.69019172 | L53: 0.042057199 | M53: HAC-NW(4), t(18) | N53: 16.410787 | O53: 2.8387419e-12 | P53: 9.9355966e-11 | Q53: BH | R53: 0.60183282 | S53: 0.77855062 | T53: 1.0299216 | V53: 24 | W53: 0.96694959 | X53: 0.95776892 | Y53: -9.0918435 | Z53: -2.0235205 | AM53: C4 | AN53: 96 | AO53: 0.5625 | AP53: 0.125 | AQ53: no_evaluable | AR53: no | AS53: si | AT53: (b) mejor de la familia ols_tramos_hac: ecuacion AR1+X por periodo; unico candidato con OOS en la familia; NO CUMPLE LA REGLA (§8 y multiverso) en ninguna variable; RMSE 1.815 vs AR(4) 0.800 (peor que AR(4)) | AU53: src/v8/m0_periodos.py | AV53: (b) mejor de la familia ols_tramos_hac: ecuacion AR1+X por periodo; unico candidato con OOS en la familia | AW53: M0:AR1+X_por_periodo | AX53: si | AY53: output/v8/M0/coeficientes.csv | AZ53: =Fuera_muestra!F19 | BA53: =Fuera_muestra!G19 | BB53: =AZ53/BA53
A54: M0_alquiler_base_P3 | B54: M0 | C54: ols_tramos_hac | D54: alquiler | E54: nacional | F54: P3 | G54: d4_ln_ipc_alquiler_real | H54: d4_ln*100 | I54: IPC alquiler, real (IPC general) | J54: d4_credito_vivienda_real | K54: 0.2613978 | L54: 0.056635517 | M54: HAC-NW(4), t(18) | N54: 4.6154395 | O54: 0.00021483295 | P54: 0.00093989415 | Q54: BH | R54: 0.142411 | S54: 0.38038461 | T54: 0.32198511 | V54: 24 | W54: 0.96694959 | X54: 0.95776892 | Y54: -9.0918435 | Z54: -2.0235205 | AM54: C4 | AQ54: no_evaluable | AR54: no_evaluable | AS54: si | AT54: (b) mejor de la familia ols_tramos_hac: ecuacion AR1+X por periodo; unico candidato con OOS en la familia; NO CUMPLE LA REGLA (§8 y multiverso) en ninguna variable; RMSE 1.815 vs AR(4) 0.800 (peor que AR(4)) | AU54: src/v8/m0_periodos.py | AV54: (b) mejor de la familia ols_tramos_hac: ecuacion AR1+X por periodo; unico candidato con OOS en la familia | AW54: M0:AR1+X_por_periodo | AX54: si | AY54: output/v8/M0/coeficientes.csv | AZ54: =Fuera_muestra!F19 | BA54: =Fuera_muestra!G19 | BB54: =AZ54/BA54
A55: M0_alquiler_base_P3 | B55: M0 | C55: ols_tramos_hac | D55: alquiler | E55: nacional | F55: P3 | G55: d4_ln_ipc_alquiler_real | H55: d4_ln*100 | I55: IPC alquiler, real (IPC general) | J55: d4_terminadas | K55: 0.0026972862 | L55: 0.0026806323 | M55: HAC-NW(4), t(18) | N55: 1.0062126 | O55: 0.32764907 | P55: 0.43274406 | Q55: BH | R55: -0.0029345134 | S55: 0.0083290857 | T55: 0.073763079 | V55: 24 | W55: 0.96694959 | X55: 0.95776892 | Y55: -9.0918435 | Z55: -2.0235205 | AM55: C4 | AN55: 96 | AO55: 0.52083333 | AP55: 0.083333333 | AQ55: no_evaluable | AR55: no | AS55: si | AT55: (b) mejor de la familia ols_tramos_hac: ecuacion AR1+X por periodo; unico candidato con OOS en la familia; NO CUMPLE LA REGLA (§8 y multiverso) en ninguna variable; RMSE 1.815 vs AR(4) 0.800 (peor que AR(4)) | AU55: src/v8/m0_periodos.py | AV55: (b) mejor de la familia ols_tramos_hac: ecuacion AR1+X por periodo; unico candidato con OOS en la familia | AW55: M0:AR1+X_por_periodo | AX55: si | AY55: output/v8/M0/coeficientes.csv | AZ55: =Fuera_muestra!F19 | BA55: =Fuera_muestra!G19 | BB55: =AZ55/BA55
A56: M0_alquiler_base_P4 | B56: M0 | C56: ols_tramos_hac | D56: alquiler | E56: nacional | F56: P4 | G56: d4_ln_ipc_alquiler_real | H56: d4_ln*100 | I56: IPC alquiler, real (IPC general) | J56: d4_pob_total | K56: 0.10491992 | L56: 0.65488351 | M56: HAC-NW(4), t(3) | N56: 0.16021158 | O56: 0.88289427 | P56: 0.89568984 | Q56: BH | R56: -1.9792117 | S56: 2.1890515 | T56: 0.0070355364 | V56: 9 | W56: 0.99992138 | X56: 0.99979036 | Y56: -25.0902 | Z56: -23.906853 | AM56: C4 | AN56: 120 | AO56: 0.63333333 | AP56: 0.45833333 | AQ56: no_evaluable | AR56: no | AS56: si | AT56: (b) mejor de la familia ols_tramos_hac: ecuacion AR1+X por periodo; unico candidato con OOS en la familia; NO CUMPLE LA REGLA (§8 y multiverso) en ninguna variable; RMSE 1.815 vs AR(4) 0.800 (peor que AR(4)) | AU56: src/v8/m0_periodos.py | AV56: (b) mejor de la familia ols_tramos_hac: ecuacion AR1+X por periodo; unico candidato con OOS en la familia | AW56: M0:AR1+X_por_periodo | AX56: si | AY56: output/v8/M0/coeficientes.csv | AZ56: =Fuera_muestra!F19 | BA56: =Fuera_muestra!G19 | BB56: =AZ56/BA56
A57: M0_alquiler_base_P4 | B57: M0 | C57: ols_tramos_hac | D57: alquiler | E57: nacional | F57: P4 | G57: d4_ln_ipc_alquiler_real | H57: d4_ln*100 | I57: IPC alquiler, real (IPC general) | J57: d4_pib_vol | K57: 0.016176939 | L57: 0.0021545193 | M57: HAC-NW(4), t(3) | N57: 7.5083754 | O57: 0.0048952242 | P57: 0.01317945 | Q57: BH | R57: 0.0093202975 | S57: 0.023033581 | T57: 0.055195019 | V57: 9 | W57: 0.99992138 | X57: 0.99979036 | Y57: -25.0902 | Z57: -23.906853 | AM57: C4 | AN57: 120 | AO57: 0.75 | AP57: 0.475 | AQ57: no_evaluable | AR57: no | AS57: si | AT57: (b) mejor de la familia ols_tramos_hac: ecuacion AR1+X por periodo; unico candidato con OOS en la familia; NO CUMPLE LA REGLA (§8 y multiverso) en ninguna variable; RMSE 1.815 vs AR(4) 0.800 (peor que AR(4)) | AU57: src/v8/m0_periodos.py | AV57: (b) mejor de la familia ols_tramos_hac: ecuacion AR1+X por periodo; unico candidato con OOS en la familia | AW57: M0:AR1+X_por_periodo | AX57: si | AY57: output/v8/M0/coeficientes.csv | AZ57: =Fuera_muestra!F19 | BA57: =Fuera_muestra!G19 | BB57: =AZ57/BA57
A58: M0_alquiler_base_P4 | B58: M0 | C58: ols_tramos_hac | D58: alquiler | E58: nacional | F58: P4 | G58: d4_ln_ipc_alquiler_real | H58: d4_ln*100 | I58: IPC alquiler, real (IPC general) | J58: tipo_hip_real | K58: 1.293498 | L58: 0.18548602 | M58: HAC-NW(4), t(3) | N58: 6.9735604 | O58: 0.0060514093 | P58: 0.015688839 | Q58: BH | R58: 0.70319866 | S58: 1.8837973 | T58: 1.2973348 | V58: 9 | W58: 0.99992138 | X58: 0.99979036 | Y58: -25.0902 | Z58: -23.906853 | AM58: C4 | AN58: 120 | AO58: 0.83333333 | AP58: 0.54166667 | AQ58: no_evaluable | AR58: sí | AS58: si | AT58: (b) mejor de la familia ols_tramos_hac: ecuacion AR1+X por periodo; unico candidato con OOS en la familia; NO CUMPLE LA REGLA (§8 y multiverso) en ninguna variable; RMSE 1.815 vs AR(4) 0.800 (peor que AR(4)) | AU58: src/v8/m0_periodos.py | AV58: (b) mejor de la familia ols_tramos_hac: ecuacion AR1+X por periodo; unico candidato con OOS en la familia | AW58: M0:AR1+X_por_periodo | AX58: si | AY58: output/v8/M0/coeficientes.csv | AZ58: =Fuera_muestra!F19 | BA58: =Fuera_muestra!G19 | BB58: =AZ58/BA58
A59: M0_alquiler_base_P4 | B59: M0 | C59: ols_tramos_hac | D59: alquiler | E59: nacional | F59: P4 | G59: d4_ln_ipc_alquiler_real | H59: d4_ln*100 | I59: IPC alquiler, real (IPC general) | J59: d4_credito_vivienda_real | K59: -0.40267144 | L59: 0.27597875 | M59: HAC-NW(4), t(3) | N59: -1.4590668 | O59: 0.24064235 | P59: 0.32394163 | Q59: BH | R59: -1.280959 | S59: 0.47561611 | T59: -0.26732003 | V59: 9 | W59: 0.99992138 | X59: 0.99979036 | Y59: -25.0902 | Z59: -23.906853 | AM59: C4 | AQ59: no_evaluable | AR59: no_evaluable | AS59: si | AT59: (b) mejor de la familia ols_tramos_hac: ecuacion AR1+X por periodo; unico candidato con OOS en la familia; NO CUMPLE LA REGLA (§8 y multiverso) en ninguna variable; RMSE 1.815 vs AR(4) 0.800 (peor que AR(4)) | AU59: src/v8/m0_periodos.py | AV59: (b) mejor de la familia ols_tramos_hac: ecuacion AR1+X por periodo; unico candidato con OOS en la familia | AW59: M0:AR1+X_por_periodo | AX59: si | AY59: output/v8/M0/coeficientes.csv | AZ59: =Fuera_muestra!F19 | BA59: =Fuera_muestra!G19 | BB59: =AZ59/BA59
A60: M0_alquiler_base_P4 | B60: M0 | C60: ols_tramos_hac | D60: alquiler | E60: nacional | F60: P4 | G60: d4_ln_ipc_alquiler_real | H60: d4_ln*100 | I60: IPC alquiler, real (IPC general) | J60: d4_terminadas | K60: -0.002999107 | L60: 0.0011369494 | M60: HAC-NW(4), t(3) | N60: -2.6378543 | O60: 0.07779894 | P60: 0.13614815 | Q60: BH | R60: -0.0066173875 | S60: 0.00061917354 | T60: -0.014348536 | V60: 9 | W60: 0.99992138 | X60: 0.99979036 | Y60: -25.0902 | Z60: -23.906853 | AM60: C4 | AN60: 120 | AO60: 0.63333333 | AP60: 0.091666667 | AQ60: no_evaluable | AR60: no | AS60: si | AT60: (b) mejor de la familia ols_tramos_hac: ecuacion AR1+X por periodo; unico candidato con OOS en la familia; NO CUMPLE LA REGLA (§8 y multiverso) en ninguna variable; RMSE 1.815 vs AR(4) 0.800 (peor que AR(4)) | AU60: src/v8/m0_periodos.py | AV60: (b) mejor de la familia ols_tramos_hac: ecuacion AR1+X por periodo; unico candidato con OOS en la familia | AW60: M0:AR1+X_por_periodo | AX60: si | AY60: output/v8/M0/coeficientes.csv | AZ60: =Fuera_muestra!F19 | BA60: =Fuera_muestra!G19 | BB60: =AZ60/BA60
A61: M0_alquiler_base_P5 | B61: M0 | C61: ols_tramos_hac | D61: alquiler | E61: nacional | F61: P5 | G61: d4_ln_ipc_alquiler_real | H61: d4_ln*100 | I61: IPC alquiler, real (IPC general) | J61: d4_pob_total | K61: 1.1779269 | L61: 0.59012526 | M61: HAC-NW(4), t(10) | N61: 1.9960624 | O61: 0.073871058 | P61: 0.13258908 | Q61: BH | R61: -0.13695416 | S61: 2.4928079 | T61: 0.051979521 | V61: 16 | W61: 0.99811543 | X61: 0.99717315 | Y61: -19.524713 | Z61: -14.889181 | AM61: C4 | AN61: 96 | AO61: 0.58333333 | AP61: 0.125 | AQ61: no_evaluable | AR61: no | AS61: si | AT61: (b) mejor de la familia ols_tramos_hac: ecuacion AR1+X por periodo; unico candidato con OOS en la familia; NO CUMPLE LA REGLA (§8 y multiverso) en ninguna variable; RMSE 1.815 vs AR(4) 0.800 (peor que AR(4)) | AU61: src/v8/m0_periodos.py | AV61: (b) mejor de la familia ols_tramos_hac: ecuacion AR1+X por periodo; unico candidato con OOS en la familia | AW61: M0:AR1+X_por_periodo | AX61: si | AY61: output/v8/M0/coeficientes.csv | AZ61: =Fuera_muestra!F19 | BA61: =Fuera_muestra!G19 | BB61: =AZ61/BA61
A62: M0_alquiler_base_P5 | B62: M0 | C62: ols_tramos_hac | D62: alquiler | E62: nacional | F62: P5 | G62: d4_ln_ipc_alquiler_real | H62: d4_ln*100 | I62: IPC alquiler, real (IPC general) | J62: d4_pib_vol | K62: 0.087205816 | L62: 0.057340833 | M62: HAC-NW(4), t(10) | N62: 1.5208327 | O62: 0.1592713 | P62: 0.24236937 | Q62: BH | R62: -0.040557521 | S62: 0.21496915 | T62: 0.044759808 | V62: 16 | W62: 0.99811543 | X62: 0.99717315 | Y62: -19.524713 | Z62: -14.889181 | AM62: C4 | AN62: 96 | AO62: 0.6875 | AP62: 0.17708333 | AQ62: no_evaluable | AR62: no | AS62: si | AT62: (b) mejor de la familia ols_tramos_hac: ecuacion AR1+X por periodo; unico candidato con OOS en la familia; NO CUMPLE LA REGLA (§8 y multiverso) en ninguna variable; RMSE 1.815 vs AR(4) 0.800 (peor que AR(4)) | AU62: src/v8/m0_periodos.py | AV62: (b) mejor de la familia ols_tramos_hac: ecuacion AR1+X por periodo; unico candidato con OOS en la familia | AW62: M0:AR1+X_por_periodo | AX62: si | AY62: output/v8/M0/coeficientes.csv | AZ62: =Fuera_muestra!F19 | BA62: =Fuera_muestra!G19 | BB62: =AZ62/BA62
A63: M0_alquiler_base_P5 | B63: M0 | C63: ols_tramos_hac | D63: alquiler | E63: nacional | F63: P5 | G63: d4_ln_ipc_alquiler_real | H63: d4_ln*100 | I63: IPC alquiler, real (IPC general) | J63: tipo_hip_real | K63: 0.77182937 | L63: 0.017035008 | M63: HAC-NW(4), t(10) | N63: 45.308424 | O63: 6.6014282e-13 | P63: 4.6209998e-11 | Q63: BH | R63: 0.73387301 | S63: 0.80978574 | T63: 0.80956916 | V63: 16 | W63: 0.99811543 | X63: 0.99717315 | Y63: -19.524713 | Z63: -14.889181 | AM63: C4 | AN63: 96 | AO63: 0.85416667 | AP63: 0.45833333 | AQ63: no_evaluable | AR63: no | AS63: si | AT63: (b) mejor de la familia ols_tramos_hac: ecuacion AR1+X por periodo; unico candidato con OOS en la familia; NO CUMPLE LA REGLA (§8 y multiverso) en ninguna variable; RMSE 1.815 vs AR(4) 0.800 (peor que AR(4)) | AU63: src/v8/m0_periodos.py | AV63: (b) mejor de la familia ols_tramos_hac: ecuacion AR1+X por periodo; unico candidato con OOS en la familia | AW63: M0:AR1+X_por_periodo | AX63: si | AY63: output/v8/M0/coeficientes.csv | AZ63: =Fuera_muestra!F19 | BA63: =Fuera_muestra!G19 | BB63: =AZ63/BA63
A64: M0_alquiler_base_P5 | B64: M0 | C64: ols_tramos_hac | D64: alquiler | E64: nacional | F64: P5 | G64: d4_ln_ipc_alquiler_real | H64: d4_ln*100 | I64: IPC alquiler, real (IPC general) | J64: d4_credito_vivienda_real | K64: 0.24804343 | L64: 0.013612916 | M64: HAC-NW(4), t(10) | N64: 18.221182 | O64: 5.3242257e-09 | P64: 1.2423193e-07 | Q64: BH | R64: 0.21771196 | S64: 0.2783749 | T64: 0.37599717 | V64: 16 | W64: 0.99811543 | X64: 0.99717315 | Y64: -19.524713 | Z64: -14.889181 | AM64: C4 | AQ64: no_evaluable | AR64: no_evaluable | AS64: si | AT64: (b) mejor de la familia ols_tramos_hac: ecuacion AR1+X por periodo; unico candidato con OOS en la familia; NO CUMPLE LA REGLA (§8 y multiverso) en ninguna variable; RMSE 1.815 vs AR(4) 0.800 (peor que AR(4)) | AU64: src/v8/m0_periodos.py | AV64: (b) mejor de la familia ols_tramos_hac: ecuacion AR1+X por periodo; unico candidato con OOS en la familia | AW64: M0:AR1+X_por_periodo | AX64: si | AY64: output/v8/M0/coeficientes.csv | AZ64: =Fuera_muestra!F19 | BA64: =Fuera_muestra!G19 | BB64: =AZ64/BA64
A65: M0_alquiler_base_P5 | B65: M0 | C65: ols_tramos_hac | D65: alquiler | E65: nacional | F65: P5 | G65: d4_ln_ipc_alquiler_real | H65: d4_ln*100 | I65: IPC alquiler, real (IPC general) | J65: d4_terminadas | K65: 0.0018129361 | L65: 0.0028706981 | M65: HAC-NW(4), t(10) | N65: 0.63153143 | O65: 0.54185931 | P65: 0.63216919 | Q65: BH | R65: -0.0045833779 | S65: 0.00820925 | T65: 0.0068125486 | V65: 16 | W65: 0.99811543 | X65: 0.99717315 | Y65: -19.524713 | Z65: -14.889181 | AM65: C4 | AN65: 96 | AO65: 0.5 | AP65: 0.052083333 | AQ65: no_evaluable | AR65: no | AS65: si | AT65: (b) mejor de la familia ols_tramos_hac: ecuacion AR1+X por periodo; unico candidato con OOS en la familia; NO CUMPLE LA REGLA (§8 y multiverso) en ninguna variable; RMSE 1.815 vs AR(4) 0.800 (peor que AR(4)) | AU65: src/v8/m0_periodos.py | AV65: (b) mejor de la familia ols_tramos_hac: ecuacion AR1+X por periodo; unico candidato con OOS en la familia | AW65: M0:AR1+X_por_periodo | AX65: si | AY65: output/v8/M0/coeficientes.csv | AZ65: =Fuera_muestra!F19 | BA65: =Fuera_muestra!G19 | BB65: =AZ65/BA65
A66: M4_alquiler_A2_sin_rupturas_ardl | B66: M4 | C66: ardl_bounds_uecm | D66: alquiler | E66: nacional | F66: completo | G66: ln_ipc_alquiler_real | H66: ln niveles; tipo en pp | I66: IPC alquiler, real (IPC general) | J66: renta | K66: 1.4284393 | L66: 0.98090704 | M66: delta (OLS clasico) | N66: 1.4562433 | O66: 0.14532536 | P66: 0.28889982 | Q66: BH | R66: -0.49413846 | S66: 3.3510172 | T66: 2.4329949 | U66: 1.4284393 | V66: 95 | W66: 0.71149068 | X66: 0.68094264 | Y66: -690.24064 | Z66: -664.70188 | AA66: -0.043379778 | AB66: 15.629443 | AC66: 0.001 | AD66: 0.00020201641 | AE66: 0.51139752 | AF66: 1.641996e-09 | AG66: 0.077310237 | AH66: 1 | AI66: 2.6558142 | AM66: C4 | AQ66: no_evaluable | AR66: no_evaluable | AS66: si | AT66: (b) mejor de la familia dols/fmols/ardl: especificacion A2 de menor RMSE (SR); el OOS se hace con beta OLS estatico y es comun a los tres estimadores; NO CUMPLE LA REGLA (§8 y multiverso) en ninguna variable; RMSE 0.705 vs AR(4) 0.726 (no peor que AR(4)) | AU66: src/v8/m4_largo_plazo.py | AV66: (b) mejor de la familia dols/fmols/ardl: especificacion A2 de menor RMSE (SR); el OOS se hace con beta OLS estatico y es comun a los tres estimadores | AW66: M4:A2_sin_rupturas_SR | AX66: si | AY66: output/v8/M4/coeficientes.csv | AZ66: =Fuera_muestra!F36 | BA66: =Fuera_muestra!G36 | BB66: =AZ66/BA66
A67: M4_alquiler_A2_sin_rupturas_ardl | B67: M4 | C67: ardl_bounds_uecm | D67: alquiler | E67: nacional | F67: completo | G67: ln_ipc_alquiler_real | H67: ln niveles; tipo en pp | I67: IPC alquiler, real (IPC general) | J67: tipo | K67: 0.071405273 | L67: 0.04039542 | M67: delta (OLS clasico) | N67: 1.7676576 | O67: 0.077118154 | P67: 0.17551028 | Q67: BH | R67: -0.0077697501 | S67: 0.1505803 | T67: 2.8884115 | V67: 95 | W67: 0.71149068 | X67: 0.68094264 | Y67: -690.24064 | Z67: -664.70188 | AA67: -0.043379778 | AB67: 15.629443 | AC67: 0.001 | AD67: 0.00020201641 | AE67: 0.51139752 | AF67: 1.641996e-09 | AG67: 0.077310237 | AH67: 1 | AI67: 2.6558142 | AM67: C4 | AQ67: no_evaluable | AR67: no_evaluable | AS67: si | AT67: (b) mejor de la familia dols/fmols/ardl: especificacion A2 de menor RMSE (SR); el OOS se hace con beta OLS estatico y es comun a los tres estimadores; NO CUMPLE LA REGLA (§8 y multiverso) en ninguna variable; RMSE 0.705 vs AR(4) 0.726 (no peor que AR(4)) | AU67: src/v8/m4_largo_plazo.py | AV67: (b) mejor de la familia dols/fmols/ardl: especificacion A2 de menor RMSE (SR); el OOS se hace con beta OLS estatico y es comun a los tres estimadores | AW67: M4:A2_sin_rupturas_SR | AX67: si | AY67: output/v8/M4/coeficientes.csv | AZ67: =Fuera_muestra!F36 | BA67: =Fuera_muestra!G36 | BB67: =AZ67/BA67
A68: M4_alquiler_A2_sin_rupturas_ardl | B68: M4 | C68: ardl_bounds_uecm | D68: alquiler | E68: nacional | F68: completo | G68: ln_ipc_alquiler_real | H68: ln niveles; tipo en pp | I68: IPC alquiler, real (IPC general) | J68: hogares | K68: -2.3271837 | L68: 1.4616476 | M68: delta (OLS clasico) | N68: -1.5921647 | O68: 0.11134771 | P68: 0.23128789 | Q68: BH | R68: -5.1920129 | S68: 0.5376456 | T68: -3.7976949 | U68: -2.3271837 | V68: 95 | W68: 0.71149068 | X68: 0.68094264 | Y68: -690.24064 | Z68: -664.70188 | AA68: -0.043379778 | AB68: 15.629443 | AC68: 0.001 | AD68: 0.00020201641 | AE68: 0.51139752 | AF68: 1.641996e-09 | AG68: 0.077310237 | AH68: 1 | AI68: 2.6558142 | AM68: C4 | AQ68: no_evaluable | AR68: no_evaluable | AS68: si | AT68: (b) mejor de la familia dols/fmols/ardl: especificacion A2 de menor RMSE (SR); el OOS se hace con beta OLS estatico y es comun a los tres estimadores; NO CUMPLE LA REGLA (§8 y multiverso) en ninguna variable; RMSE 0.705 vs AR(4) 0.726 (no peor que AR(4)) | AU68: src/v8/m4_largo_plazo.py | AV68: (b) mejor de la familia dols/fmols/ardl: especificacion A2 de menor RMSE (SR); el OOS se hace con beta OLS estatico y es comun a los tres estimadores | AW68: M4:A2_sin_rupturas_SR | AX68: si | AY68: output/v8/M4/coeficientes.csv | AZ68: =Fuera_muestra!F36 | BA68: =Fuera_muestra!G36 | BB68: =AZ68/BA68
A69: M4_alquiler_A2_sin_rupturas_ardl | B69: M4 | C69: ardl_bounds_uecm | D69: alquiler | E69: nacional | F69: completo | G69: ln_ipc_alquiler_real | H69: ln niveles; tipo en pp | I69: IPC alquiler, real (IPC general) | J69: ruptura:epa2021 | K69: -0.1017719 | L69: 0.058403788 | M69: delta (OLS clasico) | N69: -1.7425566 | O69: 0.081411102 | P69: 0.18275962 | Q69: BH | R69: -0.21624333 | S69: 0.01269952 | T69: -0.85495298 | V69: 95 | W69: 0.71149068 | X69: 0.68094264 | Y69: -690.24064 | Z69: -664.70188 | AA69: -0.043379778 | AB69: 15.629443 | AC69: 0.001 | AD69: 0.00020201641 | AE69: 0.51139752 | AF69: 1.641996e-09 | AG69: 0.077310237 | AH69: 1 | AI69: 2.6558142 | AM69: C4 | AQ69: no_evaluable | AR69: no_evaluable | AS69: si | AT69: (b) mejor de la familia dols/fmols/ardl: especificacion A2 de menor RMSE (SR); el OOS se hace con beta OLS estatico y es comun a los tres estimadores; NO CUMPLE LA REGLA (§8 y multiverso) en ninguna variable; RMSE 0.705 vs AR(4) 0.726 (no peor que AR(4)) | AU69: src/v8/m4_largo_plazo.py | AV69: (b) mejor de la familia dols/fmols/ardl: especificacion A2 de menor RMSE (SR); el OOS se hace con beta OLS estatico y es comun a los tres estimadores | AW69: M4:A2_sin_rupturas_SR | AX69: si | AY69: output/v8/M4/coeficientes.csv | AZ69: =Fuera_muestra!F36 | BA69: =Fuera_muestra!G36 | BB69: =AZ69/BA69
A70: M4_alquiler_A2_sin_rupturas_dols | B70: M4 | C70: dols | D70: alquiler | E70: nacional | F70: completo | G70: ln_ipc_alquiler_real | H70: ln niveles; tipo en pp | I70: IPC alquiler, real (IPC general) | J70: renta | K70: -0.307229 | L70: 0.11721339 | M70: HAC-NW(4) | N70: -2.6211084 | O70: 0.008764438 | P70: 0.028080238 | Q70: BH | R70: -0.53696302 | S70: -0.077494982 | T70: -0.52328901 | U70: -0.307229 | V70: 95 | W70: 0.80172038 | X70: 0.76989772 | Y70: -427.61914 | Z70: -391.86487 | AA70: -0.055395284 | AB70: 12.162882 | AC70: 0.63515124 | AD70: 3.448066e-27 | AE70: 0.0085108967 | AF70: 0.022497379 | AG70: 0.38980925 | AH70: 0 | AI70: 2.6558142 | AM70: C4 | AQ70: no_evaluable | AR70: no_evaluable | AS70: si | AT70: (b) mejor de la familia dols/fmols/ardl: especificacion A2 de menor RMSE (SR); el OOS se hace con beta OLS estatico y es comun a los tres estimadores; NO CUMPLE LA REGLA (§8 y multiverso) en ninguna variable; RMSE 0.705 vs AR(4) 0.726 (no peor que AR(4)) | AU70: src/v8/m4_largo_plazo.py | AV70: (b) mejor de la familia dols/fmols/ardl: especificacion A2 de menor RMSE (SR); el OOS se hace con beta OLS estatico y es comun a los tres estimadores | AW70: M4:A2_sin_rupturas_SR | AX70: si | AY70: output/v8/M4/coeficientes.csv | AZ70: =Fuera_muestra!F36 | BA70: =Fuera_muestra!G36 | BB70: =AZ70/BA70
A71: M4_alquiler_A2_sin_rupturas_dols | B71: M4 | C71: dols | D71: alquiler | E71: nacional | F71: completo | G71: ln_ipc_alquiler_real | H71: ln niveles; tipo en pp | I71: IPC alquiler, real (IPC general) | J71: tipo | K71: 0.0029103471 | L71: 0.0028987493 | M71: HAC-NW(4) | N71: 1.0040009 | O71: 0.31537816 | P71: 0.52298891 | Q71: BH | R71: -0.0027710972 | S71: 0.0085917914 | T71: 0.11772632 | V71: 95 | W71: 0.80172038 | X71: 0.76989772 | Y71: -427.61914 | Z71: -391.86487 | AA71: -0.055395284 | AB71: 12.162882 | AC71: 0.63515124 | AD71: 3.448066e-27 | AE71: 0.0085108967 | AF71: 0.022497379 | AG71: 0.38980925 | AH71: 0 | AI71: 2.6558142 | AM71: C4 | AQ71: no_evaluable | AR71: no_evaluable | AS71: si | AT71: (b) mejor de la familia dols/fmols/ardl: especificacion A2 de menor RMSE (SR); el OOS se hace con beta OLS estatico y es comun a los tres estimadores; NO CUMPLE LA REGLA (§8 y multiverso) en ninguna variable; RMSE 0.705 vs AR(4) 0.726 (no peor que AR(4)) | AU71: src/v8/m4_largo_plazo.py | AV71: (b) mejor de la familia dols/fmols/ardl: especificacion A2 de menor RMSE (SR); el OOS se hace con beta OLS estatico y es comun a los tres estimadores | AW71: M4:A2_sin_rupturas_SR | AX71: si | AY71: output/v8/M4/coeficientes.csv | AZ71: =Fuera_muestra!F36 | BA71: =Fuera_muestra!G36 | BB71: =AZ71/BA71
A72: M4_alquiler_A2_sin_rupturas_dols | B72: M4 | C72: dols | D72: alquiler | E72: nacional | F72: completo | G72: ln_ipc_alquiler_real | H72: ln niveles; tipo en pp | I72: IPC alquiler, real (IPC general) | J72: hogares | K72: 0.51305206 | L72: 0.20368432 | M72: HAC-NW(4) | N72: 2.5188588 | O72: 0.011773584 | P72: 0.037002694 | Q72: BH | R72: 0.11383812 | S72: 0.91226599 | T72: 0.83724168 | U72: 0.51305206 | V72: 95 | W72: 0.80172038 | X72: 0.76989772 | Y72: -427.61914 | Z72: -391.86487 | AA72: -0.055395284 | AB72: 12.162882 | AC72: 0.63515124 | AD72: 3.448066e-27 | AE72: 0.0085108967 | AF72: 0.022497379 | AG72: 0.38980925 | AH72: 0 | AI72: 2.6558142 | AM72: C4 | AQ72: no_evaluable | AR72: no_evaluable | AS72: si | AT72: (b) mejor de la familia dols/fmols/ardl: especificacion A2 de menor RMSE (SR); el OOS se hace con beta OLS estatico y es comun a los tres estimadores; NO CUMPLE LA REGLA (§8 y multiverso) en ninguna variable; RMSE 0.705 vs AR(4) 0.726 (no peor que AR(4)) | AU72: src/v8/m4_largo_plazo.py | AV72: (b) mejor de la familia dols/fmols/ardl: especificacion A2 de menor RMSE (SR); el OOS se hace con beta OLS estatico y es comun a los tres estimadores | AW72: M4:A2_sin_rupturas_SR | AX72: si | AY72: output/v8/M4/coeficientes.csv | AZ72: =Fuera_muestra!F36 | BA72: =Fuera_muestra!G36 | BB72: =AZ72/BA72
A73: M4_alquiler_A2_sin_rupturas_dols | B73: M4 | C73: dols | D73: alquiler | E73: nacional | F73: completo | G73: ln_ipc_alquiler_real | H73: ln niveles; tipo en pp | I73: IPC alquiler, real (IPC general) | J73: ruptura:epa2021 | K73: -0.10274172 | L73: 0.017647349 | M73: HAC-NW(4) | N73: -5.821935 | O73: 5.8170162e-09 | P73: 6.855769e-08 | Q73: BH | R73: -0.13732989 | S73: -0.068153551 | T73: -0.86310009 | V73: 95 | W73: 0.80172038 | X73: 0.76989772 | Y73: -427.61914 | Z73: -391.86487 | AA73: -0.055395284 | AB73: 12.162882 | AC73: 0.63515124 | AD73: 3.448066e-27 | AE73: 0.0085108967 | AF73: 0.022497379 | AG73: 0.38980925 | AH73: 0 | AI73: 2.6558142 | AM73: C4 | AQ73: no_evaluable | AR73: no_evaluable | AS73: si | AT73: (b) mejor de la familia dols/fmols/ardl: especificacion A2 de menor RMSE (SR); el OOS se hace con beta OLS estatico y es comun a los tres estimadores; NO CUMPLE LA REGLA (§8 y multiverso) en ninguna variable; RMSE 0.705 vs AR(4) 0.726 (no peor que AR(4)) | AU73: src/v8/m4_largo_plazo.py | AV73: (b) mejor de la familia dols/fmols/ardl: especificacion A2 de menor RMSE (SR); el OOS se hace con beta OLS estatico y es comun a los tres estimadores | AW73: M4:A2_sin_rupturas_SR | AX73: si | AY73: output/v8/M4/coeficientes.csv | AZ73: =Fuera_muestra!F36 | BA73: =Fuera_muestra!G36 | BB73: =AZ73/BA73
A74: M4_alquiler_A2_sin_rupturas_fmols | B74: M4 | C74: fmols | D74: alquiler | E74: nacional | F74: completo | G74: ln_ipc_alquiler_real | H74: ln niveles; tipo en pp | I74: IPC alquiler, real (IPC general) | J74: renta | K74: -0.14846863 | L74: 0.10093933 | M74: FMOLS Omega_u.e (Bartlett) | N74: -1.47087 | O74: 0.14132628 | P74: 0.28437605 | Q74: BH | R74: -0.34630971 | S74: 0.049372453 | T74: -0.25287977 | U74: -0.14846863 | V74: 94 | W74: 0.70304071 | X74: 0.68969423 | Y74: -668.64364 | Z74: -655.92716 | AA74: -0.077283343 | AB74: 8.6176887 | AC74: 0.63515124 | AD74: 1.1471361e-32 | AE74: 0.0010236509 | AF74: 0.0033858269 | AG74: 2.8516004e-12 | AH74: 0 | AI74: 2.6558142 | AM74: C4 | AQ74: no_evaluable | AR74: no_evaluable | AS74: si | AT74: (b) mejor de la familia dols/fmols/ardl: especificacion A2 de menor RMSE (SR); el OOS se hace con beta OLS estatico y es comun a los tres estimadores; NO CUMPLE LA REGLA (§8 y multiverso) en ninguna variable; RMSE 0.705 vs AR(4) 0.726 (no peor que AR(4)) | AU74: src/v8/m4_largo_plazo.py | AV74: (b) mejor de la familia dols/fmols/ardl: especificacion A2 de menor RMSE (SR); el OOS se hace con beta OLS estatico y es comun a los tres estimadores | AW74: M4:A2_sin_rupturas_SR | AX74: si | AY74: output/v8/M4/coeficientes.csv | AZ74: =Fuera_muestra!F36 | BA74: =Fuera_muestra!G36 | BB74: =AZ74/BA74
A75: M4_alquiler_A2_sin_rupturas_fmols | B75: M4 | C75: fmols | D75: alquiler | E75: nacional | F75: completo | G75: ln_ipc_alquiler_real | H75: ln niveles; tipo en pp | I75: IPC alquiler, real (IPC general) | J75: tipo | K75: 0.0039071829 | L75: 0.002743984 | M75: FMOLS Omega_u.e (Bartlett) | N75: 1.4239088 | O75: 0.15447288 | P75: 0.2981906 | Q75: BH | R75: -0.0014710257 | S75: 0.0092853916 | T75: 0.15804928 | V75: 94 | W75: 0.70304071 | X75: 0.68969423 | Y75: -668.64364 | Z75: -655.92716 | AA75: -0.077283343 | AB75: 8.6176887 | AC75: 0.63515124 | AD75: 1.1471361e-32 | AE75: 0.0010236509 | AF75: 0.0033858269 | AG75: 2.8516004e-12 | AH75: 0 | AI75: 2.6558142 | AM75: C4 | AQ75: no_evaluable | AR75: no_evaluable | AS75: si | AT75: (b) mejor de la familia dols/fmols/ardl: especificacion A2 de menor RMSE (SR); el OOS se hace con beta OLS estatico y es comun a los tres estimadores; NO CUMPLE LA REGLA (§8 y multiverso) en ninguna variable; RMSE 0.705 vs AR(4) 0.726 (no peor que AR(4)) | AU75: src/v8/m4_largo_plazo.py | AV75: (b) mejor de la familia dols/fmols/ardl: especificacion A2 de menor RMSE (SR); el OOS se hace con beta OLS estatico y es comun a los tres estimadores | AW75: M4:A2_sin_rupturas_SR | AX75: si | AY75: output/v8/M4/coeficientes.csv | AZ75: =Fuera_muestra!F36 | BA75: =Fuera_muestra!G36 | BB75: =AZ75/BA75
A76: M4_alquiler_A2_sin_rupturas_fmols | B76: M4 | C76: fmols | D76: alquiler | E76: nacional | F76: completo | G76: ln_ipc_alquiler_real | H76: ln niveles; tipo en pp | I76: IPC alquiler, real (IPC general) | J76: hogares | K76: 0.078812825 | L76: 0.090201407 | M76: FMOLS Omega_u.e (Bartlett) | N76: 0.87374274 | O76: 0.38225837 | P76: 0.58672215 | Q76: BH | R76: -0.097981933 | S76: 0.25560758 | T76: 0.12861342 | U76: 0.078812825 | V76: 94 | W76: 0.70304071 | X76: 0.68969423 | Y76: -668.64364 | Z76: -655.92716 | AA76: -0.077283343 | AB76: 8.6176887 | AC76: 0.63515124 | AD76: 1.1471361e-32 | AE76: 0.0010236509 | AF76: 0.0033858269 | AG76: 2.8516004e-12 | AH76: 0 | AI76: 2.6558142 | AM76: C4 | AQ76: no_evaluable | AR76: no_evaluable | AS76: si | AT76: (b) mejor de la familia dols/fmols/ardl: especificacion A2 de menor RMSE (SR); el OOS se hace con beta OLS estatico y es comun a los tres estimadores; NO CUMPLE LA REGLA (§8 y multiverso) en ninguna variable; RMSE 0.705 vs AR(4) 0.726 (no peor que AR(4)) | AU76: src/v8/m4_largo_plazo.py | AV76: (b) mejor de la familia dols/fmols/ardl: especificacion A2 de menor RMSE (SR); el OOS se hace con beta OLS estatico y es comun a los tres estimadores | AW76: M4:A2_sin_rupturas_SR | AX76: si | AY76: output/v8/M4/coeficientes.csv | AZ76: =Fuera_muestra!F36 | BA76: =Fuera_muestra!G36 | BB76: =AZ76/BA76
A77: M4_alquiler_A2_sin_rupturas_fmols | B77: M4 | C77: fmols | D77: alquiler | E77: nacional | F77: completo | G77: ln_ipc_alquiler_real | H77: ln niveles; tipo en pp | I77: IPC alquiler, real (IPC general) | J77: ruptura:epa2021 | K77: -0.072791255 | L77: 0.018077064 | M77: FMOLS Omega_u.e (Bartlett) | N77: -4.026719 | O77: 5.6560556e-05 | P77: 0.00031108306 | Q77: BH | R77: -0.1082223 | S77: -0.037360211 | T77: -0.61149589 | V77: 94 | W77: 0.70304071 | X77: 0.68969423 | Y77: -668.64364 | Z77: -655.92716 | AA77: -0.077283343 | AB77: 8.6176887 | AC77: 0.63515124 | AD77: 1.1471361e-32 | AE77: 0.0010236509 | AF77: 0.0033858269 | AG77: 2.8516004e-12 | AH77: 0 | AI77: 2.6558142 | AM77: C4 | AQ77: no_evaluable | AR77: no_evaluable | AS77: si | AT77: (b) mejor de la familia dols/fmols/ardl: especificacion A2 de menor RMSE (SR); el OOS se hace con beta OLS estatico y es comun a los tres estimadores; NO CUMPLE LA REGLA (§8 y multiverso) en ninguna variable; RMSE 0.705 vs AR(4) 0.726 (no peor que AR(4)) | AU77: src/v8/m4_largo_plazo.py | AV77: (b) mejor de la familia dols/fmols/ardl: especificacion A2 de menor RMSE (SR); el OOS se hace con beta OLS estatico y es comun a los tres estimadores | AW77: M4:A2_sin_rupturas_SR | AX77: si | AY77: output/v8/M4/coeficientes.csv | AZ77: =Fuera_muestra!F36 | BA77: =Fuera_muestra!G36 | BB77: =AZ77/BA77
A78: M6_ols_alquiler_trimestral_completo | B78: M6 | C78: ols_familias | D78: alquiler | E78: nacional | F78: completo | G78: d_ln_ipc_alquiler_real | H78: trimestral | I78: ipc_alquiler | J78: const | K78: -0.27787475 | L78: 0.16224486 | M78: EWC | N78: -1.7126876 | O78: 0.13049848 | P78: 0.24001401 | Q78: BH | R78: -0.66152287 | S78: 0.10577337 | V78: 76 | W78: 0.43795508 | X78: 0.37084524 | Y78: 202.41652 | Z78: 223.39312 | AD78: 0.0051572934 | AE78: 0.5475726 | AF78: 0.00044732986 | AG78: 0.6931786 | AH78: 1 | AI78: 1.9622605 | AM78: C4 | AQ78: no_evaluable | AR78: no_evaluable | AS78: si | AT78: (b) mejor de la familia ols_familias: ols_factores trimestral, periodo completo; NO CUMPLE LA REGLA (§8 y multiverso) en ninguna variable; RMSE 3.839 vs AR(4) 0.804 (peor que AR(4)) | AU78: src/v8/m6_colinealidad.py | AV78: (b) mejor de la familia ols_familias: ols_factores trimestral, periodo completo | AW78: M6:ols_factores | AX78: si | AY78: output/v8/M6/coeficientes.csv | AZ78: =Fuera_muestra!F54 | BA78: =Fuera_muestra!G54 | BB78: =AZ78/BA78
A79: M6_ols_alquiler_trimestral_completo | B79: M6 | C79: ols_familias | D79: alquiler | E79: nacional | F79: completo | G79: d_ln_ipc_alquiler_real | H79: trimestral | I79: ipc_alquiler | J79: hogares_epa | K79: -0.44143827 | L79: 0.49682696 | M79: EWC | N79: -0.88851513 | O79: 0.40376057 | P79: 0.53777169 | Q79: BH | R79: -1.6162473 | S79: 0.73337081 | T79: -0.097465416 | U79: -0.44143827 | V79: 76 | W79: 0.43795508 | X79: 0.37084524 | Y79: 202.41652 | Z79: 223.39312 | AD79: 0.0051572934 | AE79: 0.5475726 | AF79: 0.00044732986 | AG79: 0.6931786 | AH79: 1 | AI79: 1.9622605 | AM79: C4 | AN79: 576 | AO79: 0.98263889 | AP79: 0.60416667 | AQ79: no_evaluable | AR79: sí | AS79: si | AT79: (b) mejor de la familia ols_familias: ols_factores trimestral, periodo completo; NO CUMPLE LA REGLA (§8 y multiverso) en ninguna variable; RMSE 3.839 vs AR(4) 0.804 (peor que AR(4)) | AU79: src/v8/m6_colinealidad.py | AV79: (b) mejor de la familia ols_familias: ols_factores trimestral, periodo completo | AW79: M6:ols_factores | AX79: si | AY79: output/v8/M6/coeficientes.csv | AZ79: =Fuera_muestra!F54 | BA79: =Fuera_muestra!G54 | BB79: =AZ79/BA79
A80: M6_ols_alquiler_trimestral_completo | B80: M6 | C80: ols_familias | D80: alquiler | E80: nacional | F80: completo | G80: d_ln_ipc_alquiler_real | H80: trimestral | I80: ipc_alquiler | J80: pib_vol | K80: 0.055220944 | L80: 0.041382918 | M80: EWC | N80: 1.3343898 | O80: 0.22384664 | P80: 0.35725019 | Q80: BH | R80: -0.042634107 | S80: 0.15307599 | T80: 0.1517799 | U80: 0.055220944 | V80: 76 | W80: 0.43795508 | X80: 0.37084524 | Y80: 202.41652 | Z80: 223.39312 | AD80: 0.0051572934 | AE80: 0.5475726 | AF80: 0.00044732986 | AG80: 0.6931786 | AH80: 1 | AI80: 1.9622605 | AM80: C4 | AN80: 576 | AO80: 0.66666667 | AP80: 0.25694444 | AQ80: no_evaluable | AR80: no | AS80: si | AT80: (b) mejor de la familia ols_familias: ols_factores trimestral, periodo completo; NO CUMPLE LA REGLA (§8 y multiverso) en ninguna variable; RMSE 3.839 vs AR(4) 0.804 (peor que AR(4)) | AU80: src/v8/m6_colinealidad.py | AV80: (b) mejor de la familia ols_familias: ols_factores trimestral, periodo completo | AW80: M6:ols_factores | AX80: si | AY80: output/v8/M6/coeficientes.csv | AZ80: =Fuera_muestra!F54 | BA80: =Fuera_muestra!G54 | BB80: =AZ80/BA80
A81: M6_ols_alquiler_trimestral_completo | B81: M6 | C81: ols_familias | D81: alquiler | E81: nacional | F81: completo | G81: d_ln_ipc_alquiler_real | H81: trimestral | I81: ipc_alquiler | J81: tipo_hip_real | K81: 0.18450392 | L81: 0.042062587 | M81: EWC | N81: 4.3864141 | O81: 0.0032093493 | P81: 0.025995325 | Q81: BH | R81: 0.08504171 | S81: 0.28396614 | T81: 0.37346091 | V81: 76 | W81: 0.43795508 | X81: 0.37084524 | Y81: 202.41652 | Z81: 223.39312 | AD81: 0.0051572934 | AE81: 0.5475726 | AF81: 0.00044732986 | AG81: 0.6931786 | AH81: 1 | AI81: 1.9622605 | AM81: C4 | AN81: 576 | AO81: 0.58333333 | AP81: 0.30555556 | AQ81: no_evaluable | AR81: no | AS81: si | AT81: (b) mejor de la familia ols_familias: ols_factores trimestral, periodo completo; NO CUMPLE LA REGLA (§8 y multiverso) en ninguna variable; RMSE 3.839 vs AR(4) 0.804 (peor que AR(4)) | AU81: src/v8/m6_colinealidad.py | AV81: (b) mejor de la familia ols_familias: ols_factores trimestral, periodo completo | AW81: M6:ols_factores | AX81: si | AY81: output/v8/M6/coeficientes.csv | AZ81: =Fuera_muestra!F54 | BA81: =Fuera_muestra!G54 | BB81: =AZ81/BA81
A82: M6_ols_alquiler_trimestral_completo | B82: M6 | C82: ols_familias | D82: alquiler | E82: nacional | F82: completo | G82: d_ln_ipc_alquiler_real | H82: trimestral | I82: ipc_alquiler | J82: terminadas | K82: -0.010170364 | L82: 0.0054322627 | M82: EWC | N82: -1.872215 | O82: 0.10334107 | P82: 0.19672156 | Q82: BH | R82: -0.023015624 | S82: 0.0026748966 | T82: -0.18139832 | U82: -0.010170364 | V82: 76 | W82: 0.43795508 | X82: 0.37084524 | Y82: 202.41652 | Z82: 223.39312 | AD82: 0.0051572934 | AE82: 0.5475726 | AF82: 0.00044732986 | AG82: 0.6931786 | AH82: 1 | AI82: 1.9622605 | AM82: C4 | AN82: 576 | AO82: 0.62847222 | AP82: 0.17534722 | AQ82: no_evaluable | AR82: no | AS82: si | AT82: (b) mejor de la familia ols_familias: ols_factores trimestral, periodo completo; NO CUMPLE LA REGLA (§8 y multiverso) en ninguna variable; RMSE 3.839 vs AR(4) 0.804 (peor que AR(4)) | AU82: src/v8/m6_colinealidad.py | AV82: (b) mejor de la familia ols_familias: ols_factores trimestral, periodo completo | AW82: M6:ols_factores | AX82: si | AY82: output/v8/M6/coeficientes.csv | AZ82: =Fuera_muestra!F54 | BA82: =Fuera_muestra!G54 | BB82: =AZ82/BA82
A83: M6_ols_alquiler_trimestral_completo | B83: M6 | C83: ols_familias | D83: alquiler | E83: nacional | F83: completo | G83: d_ln_ipc_alquiler_real | H83: trimestral | I83: ipc_alquiler | J83: tx_extranj | K83: -0.018072955 | L83: 0.0075406803 | M83: EWC | N83: -2.3967274 | O83: 0.047694944 | P83: 0.11033779 | Q83: BH | R83: -0.03590383 | S83: -0.00024207922 | T83: -0.38551938 | U83: -0.018072955 | V83: 76 | W83: 0.43795508 | X83: 0.37084524 | Y83: 202.41652 | Z83: 223.39312 | AD83: 0.0051572934 | AE83: 0.5475726 | AF83: 0.00044732986 | AG83: 0.6931786 | AH83: 1 | AI83: 1.9622605 | AM83: C4 | AN83: 384 | AO83: 0.56770833 | AP83: 0.23697917 | AQ83: no_evaluable | AR83: no | AS83: si | AT83: (b) mejor de la familia ols_familias: ols_factores trimestral, periodo completo; NO CUMPLE LA REGLA (§8 y multiverso) en ninguna variable; RMSE 3.839 vs AR(4) 0.804 (peor que AR(4)) | AU83: src/v8/m6_colinealidad.py | AV83: (b) mejor de la familia ols_familias: ols_factores trimestral, periodo completo | AW83: M6:ols_factores | AX83: si | AY83: output/v8/M6/coeficientes.csv | AZ83: =Fuera_muestra!F54 | BA83: =Fuera_muestra!G54 | BB83: =AZ83/BA83
A84: M6_ols_alquiler_trimestral_completo | B84: M6 | C84: ols_familias | D84: alquiler | E84: nacional | F84: completo | G84: d_ln_ipc_alquiler_real | H84: trimestral | I84: ipc_alquiler | J84: bis_hpi_xm_real | K84: 0.12994077 | L84: 0.19681031 | M84: EWC | N84: 0.66023356 | O84: 0.53022185 | P84: 0.65389714 | Q84: BH | R84: -0.33544166 | S84: 0.5953232 | T84: 0.13439007 | U84: 0.12994077 | V84: 76 | W84: 0.43795508 | X84: 0.37084524 | Y84: 202.41652 | Z84: 223.39312 | AD84: 0.0051572934 | AE84: 0.5475726 | AF84: 0.00044732986 | AG84: 0.6931786 | AH84: 1 | AI84: 1.9622605 | AM84: C4 | AN84: 576 | AO84: 0.51388889 | AP84: 0.038194444 | AQ84: no_evaluable | AR84: no | AS84: si | AT84: (b) mejor de la familia ols_familias: ols_factores trimestral, periodo completo; NO CUMPLE LA REGLA (§8 y multiverso) en ninguna variable; RMSE 3.839 vs AR(4) 0.804 (peor que AR(4)) | AU84: src/v8/m6_colinealidad.py | AV84: (b) mejor de la familia ols_familias: ols_factores trimestral, periodo completo | AW84: M6:ols_factores | AX84: si | AY84: output/v8/M6/coeficientes.csv | AZ84: =Fuera_muestra!F54 | BA84: =Fuera_muestra!G54 | BB84: =AZ84/BA84
A85: M6_ols_alquiler_trimestral_completo | B85: M6 | C85: ols_familias | D85: alquiler | E85: nacional | F85: completo | G85: d_ln_ipc_alquiler_real | H85: trimestral | I85: ipc_alquiler | J85: covid | K85: -0.048584589 | L85: 0.25591021 | M85: EWC | N85: -0.18985014 | O85: 0.85481453 | P85: 0.90040464 | Q85: BH | R85: -0.65371608 | S85: 0.5565469 | T85: -0.0087119367 | V85: 76 | W85: 0.43795508 | X85: 0.37084524 | Y85: 202.41652 | Z85: 223.39312 | AD85: 0.0051572934 | AE85: 0.5475726 | AF85: 0.00044732986 | AG85: 0.6931786 | AH85: 1 | AI85: 1.9622605 | AM85: C4 | AQ85: no_evaluable | AR85: no_evaluable | AS85: si | AT85: (b) mejor de la familia ols_familias: ols_factores trimestral, periodo completo; NO CUMPLE LA REGLA (§8 y multiverso) en ninguna variable; RMSE 3.839 vs AR(4) 0.804 (peor que AR(4)) | AU85: src/v8/m6_colinealidad.py | AV85: (b) mejor de la familia ols_familias: ols_factores trimestral, periodo completo | AW85: M6:ols_factores | AX85: si | AY85: output/v8/M6/coeficientes.csv | AZ85: =Fuera_muestra!F54 | BA85: =Fuera_muestra!G54 | BB85: =AZ85/BA85
A86: M6_ols_alquiler_trimestral_completo | B86: M6 | C86: ols_familias | D86: alquiler | E86: nacional | F86: completo | G86: d_ln_ipc_alquiler_real | H86: trimestral | I86: ipc_alquiler | J86: epa2021_q | K86: -0.85984009 | L86: 0.69851019 | M86: EWC | N86: -1.2309629 | O86: 0.25808844 | P86: 0.38469787 | Q86: BH | R86: -2.5115542 | S86: 0.79187403 | T86: -0.090228231 | V86: 76 | W86: 0.43795508 | X86: 0.37084524 | Y86: 202.41652 | Z86: 223.39312 | AD86: 0.0051572934 | AE86: 0.5475726 | AF86: 0.00044732986 | AG86: 0.6931786 | AH86: 1 | AI86: 1.9622605 | AM86: C4 | AQ86: no_evaluable | AR86: no_evaluable | AS86: si | AT86: (b) mejor de la familia ols_familias: ols_factores trimestral, periodo completo; NO CUMPLE LA REGLA (§8 y multiverso) en ninguna variable; RMSE 3.839 vs AR(4) 0.804 (peor que AR(4)) | AU86: src/v8/m6_colinealidad.py | AV86: (b) mejor de la familia ols_familias: ols_factores trimestral, periodo completo | AW86: M6:ols_factores | AX86: si | AY86: output/v8/M6/coeficientes.csv | AZ86: =Fuera_muestra!F54 | BA86: =Fuera_muestra!G54 | BB86: =AZ86/BA86

Sheet Hipotesis
A1: id | B1: hipotesis | C1: estimacion | D1: p | E1: p_holm | F1: metodo_ajuste | G1: capa | H1: decision | I1: fuente | J1: rechaza_H0_calc (p_holm < 0,05)
A2: H8-1 | B2: En P5, la contribucion del shock demografico a la subida del alquiler real es positiva | C2: contribucion acumulada 0.07 pp (mediana 0.04; banda 68 % [-1.92; 2.13]); P(signo esperado) = 0.506 | D2: 0.49374973 | E2: 0.98749946 | F2: Holm | G2: C3s | H2: no respaldada tras Holm (C3s: condicionada a las restricciones de signo) | I2: output/v8/M2/hipotesis_m2.csv | J2: =IF(E2<0.05,"sí","no")
A3: H8-2 | B3: En P5, la contribucion de credito y tipos al precio real de compra es negativa | C3: contribucion acumulada -0.47 pp (mediana 3.37; banda 68 % [-2.82; 12.77]); P(signo esperado) = 0.293 | D3: 0.70664204 | E3: 0.98749946 | F3: Holm | G3: C3s | H3: no respaldada tras Holm (C3s: condicionada a las restricciones de signo) | I3: output/v8/M2/hipotesis_m2.csv | J3: =IF(E3<0.05,"sí","no")
A4: H8-3 | B4: En P3, la contribucion de actividad y renta al precio real de compra es positiva | C4: contribucion acumulada 7.72 pp (mediana 5.22; banda 68 % [-3.47; 18.23]); P(signo esperado) = 0.721 | D4: 0.27926802 | E4: 0.83780405 | F4: Holm | G4: C3s | H4: no respaldada tras Holm (C3s: condicionada a las restricciones de signo) | I4: output/v8/M2/hipotesis_m2.csv | J4: =IF(E4<0.05,"sí","no")
A5: H8-4 | B5: En P2, la contribucion conjunta de credito y tipos y de actividad y renta al precio real de compra es negativa | C5: contribucion acumulada -19.23 pp (mediana -16.71; banda 68 % [-34.59; -4.15]); P(signo esperado) = 0.914 | D5: 0.085658416 | E5: 0.34263366 | F5: Holm | G5: C3s | H5: no respaldada tras Holm (C3s: condicionada a las restricciones de signo) | I5: output/v8/M2/hipotesis_m2.csv | J5: =IF(E5<0.05,"sí","no")
A6: H8-5 | B6: Un shock monetario contractivo del BCE reduce el precio real de compra a h = 4-8 | C6: beta descriptivo (cociente) -8.78 (no es evidencia); F efectivo 1.83; IC AR95 [-inf; inf]; signo forma reducida 1 (esperado -1) | D6: 0.72438721 | E6: 1 | F6: Holm | G6: C4 | H6: no respaldada tras Holm; no respaldada tras Holm (instrumento no supera C3) | I6: output/v8/M5/hipotesis_m5.csv | J6: =IF(E6<0.05,"sí","no")
A7: H8-6 | B7: Un shock monetario contractivo del BCE reduce el alquiler real a h = 4-8 | C7: beta descriptivo (cociente) -2.91 (no es evidencia); F efectivo 0.77; IC AR95 [-inf; inf]; signo forma reducida 1 (esperado -1) | D7: 0.63493905 | E7: 1 | F7: Holm | G7: C4 | H7: no respaldada tras Holm; no respaldada tras Holm (instrumento no supera C3) | I7: output/v8/M5/hipotesis_m5.csv | J7: =IF(E7<0.05,"sí","no")
A8: H8-7 | B8: El empuje migratorio aumenta el alquiler real | C8: beta descriptivo (cociente) -0.51 (no es evidencia); F efectivo 0.05; IC AR95 [-inf; inf]; signo forma reducida -1 (esperado 1) | D8: 0.53637094 | E8: 1 | F8: Holm | G8: C4 | H8: no respaldada tras Holm; no respaldada tras Holm (instrumento no supera C3) | I8: output/v8/M5/hipotesis_m5.csv | J8: =IF(E8<0.05,"sí","no")
A9: H8-8 | B9: El componente comun de las 17 CCAA explica mas del 50 % de la varianza del crecimiento interanual del precio real de compra en cada periodo | C9: {"P1": 0.6474, "P2": 0.4527, "P3": 0.5958, "P4": 0.455, "P5": 0.9279} | D9: 0.669 | E9: 0.669 | F9: Holm | G9: C4 | H9: no respaldada tras Holm (C4: asociacion, sin lectura causal) | I9: output/v8/M1/hipotesis_m1.csv | J9: =IF(E9<0.05,"sí","no")
A10: H8-9 | B10: El factor comun espanol covaria positivamente con el crecimiento del HPI de la zona euro | C10: 0.5976 | D10: 0.01 | E10: 0.02 | F10: Holm | G10: C4 | H10: respaldada tras Holm (C4: asociacion, sin lectura causal) | I10: output/v8/M1/hipotesis_m1.csv | J10: =IF(E10<0.05,"sí","no")

Sheet Votos_s9
A1: mercado | B1: periodo | C1: voto_svar_hd | D1: voto_dominancia | E1: voto_lpiv | F1: voto_contabilidad | G1: factor_evaluado | H1: n_votos | I1: cond1 | J1: cond2 | K1: cond3 | L1: resultado | M1: capa | N1: fuente | O1: votos_factor_calc (COUNTIF) | P1: cond1_calc (>=3)
A2: compra | B2: P1 | C2: empleo_renta | D2: abstiene | E2: abstiene | F2: abstiene | G2: empleo_renta | H2: 1 | I2: no | J2: sí | K2: sí | L2: no designado | M2: C4 (ranking; sin designacion) | N2: output/v8/F5/regla_s9.csv | O2: =COUNTIF(C2:F2,G2) | P2: =IF(O2>=3,"sí","no")
A3: compra | B3: P2 | C3: empleo_renta | D3: factor_europeo | E3: abstiene | F3: abstiene | G3: empleo_renta | H3: 1 | I3: no | J3: no | K3: no | L3: no designado | M3: C4 (ranking; sin designacion) | N3: output/v8/F5/regla_s9.csv | O3: =COUNTIF(C3:F3,G3) | P3: =IF(O3>=3,"sí","no")
A4: compra | B4: P3 | C4: empleo_renta | D4: empleo_renta | E4: abstiene | F4: demografia | G4: empleo_renta | H4: 2 | I4: no | J4: sí | K4: no | L4: no designado | M4: C4 (ranking; sin designacion) | N4: output/v8/F5/regla_s9.csv | O4: =COUNTIF(C4:F4,G4) | P4: =IF(O4>=3,"sí","no")
A5: compra | B5: P4 | C5: empleo_renta | D5: credito_tipos | E5: credito_tipos | F5: abstiene | G5: credito_tipos | H5: 2 | I5: no | J5: no | K5: no | L5: no designado | M5: C4 (ranking; sin designacion) | N5: output/v8/F5/regla_s9.csv | O5: =COUNTIF(C5:F5,G5) | P5: =IF(O5>=3,"sí","no")
A6: compra | B6: P5 | C6: credito_tipos | D6: credito_tipos | E6: abstiene | F6: demografia | G6: credito_tipos | H6: 2 | I6: no | J6: no | K6: no | L6: no designado | M6: C4 (ranking; sin designacion) | N6: output/v8/F5/regla_s9.csv | O6: =COUNTIF(C6:F6,G6) | P6: =IF(O6>=3,"sí","no")
A7: alquiler | B7: P1 | C7: abstiene | D7: factor_europeo | E7: abstiene | F7: abstiene | G7: factor_europeo | H7: 1 | I7: no | J7: no | K7: no | L7: no designado | M7: C4 (ranking; sin designacion) | N7: output/v8/F5/regla_s9.csv | O7: =COUNTIF(C7:F7,G7) | P7: =IF(O7>=3,"sí","no")
A8: alquiler | B8: P2 | C8: empleo_renta | D8: empleo_renta | E8: abstiene | F8: abstiene | G8: empleo_renta | H8: 2 | I8: no | J8: no | K8: no | L8: no designado | M8: C4 (ranking; sin designacion) | N8: output/v8/F5/regla_s9.csv | O8: =COUNTIF(C8:F8,G8) | P8: =IF(O8>=3,"sí","no")
A9: alquiler | B9: P3 | C9: demografia | D9: demanda_externa | E9: abstiene | F9: abstiene | G9: demografia | H9: 1 | I9: no | J9: no | K9: no | L9: no designado | M9: C4 (ranking; sin designacion) | N9: output/v8/F5/regla_s9.csv | O9: =COUNTIF(C9:F9,G9) | P9: =IF(O9>=3,"sí","no")
A10: alquiler | B10: P4 | C10: demanda_vivienda | D10: credito_tipos | E10: abstiene | F10: abstiene | G10: demanda_vivienda | H10: 1 | I10: no | J10: no | K10: no | L10: no designado | M10: C4 (ranking; sin designacion) | N10: output/v8/F5/regla_s9.csv | O10: =COUNTIF(C10:F10,G10) | P10: =IF(O10>=3,"sí","no")
A11: alquiler | B11: P5 | C11: credito_tipos | D11: credito_tipos | E11: abstiene | F11: abstiene | G11: credito_tipos | H11: 2 | I11: no | J11: no | K11: no | L11: no designado | M11: C4 (ranking; sin designacion) | N11: output/v8/F5/regla_s9.csv | O11: =COUNTIF(C11:F11,G11) | P11: =IF(O11>=3,"sí","no")
A13: Celdas designadas (calc.) | B13: =COUNTIF(L2:L11,"designado")
A14: Celdas con condición 1 (calc.) | B14: =COUNTIF(P2:P11,"sí")

Sheet Atribucion
A1: mercado | B1: ambito | C1: periodo | D1: factor | E1: metodo | F1: contribucion_pp | G1: media | H1: mediana | I1: pct_signo | J1: b68_lo | K1: b68_hi | L1: b90_lo | M1: b90_hi | N1: capa | O1: compite | P1: vota | Q1: variante | R1: delta_y_metodo_pp | S1: notas | T1: fuente | U1: pct_total_calc (contribución / ΔY) | V1: suma_contribuciones_celda_calc (SUMIFS)
A2: compra | B2: nacional | C2: P2 | D2: empleo_renta | E2: svar_hd | F2: -10.6353 | G2: -10.6353 | H2: -7.57201 | I2: 0.241701 | J2: -23.5243 | K2: 0.660395 | L2: -38.8394 | M2: 7.26832 | N2: C3s | O2: si | P2: si | Q2: V3 | R2: -44.0018 | S2: media posterior (aditiva); R0; C3s condicionada a los supuestos | T2: output/v8/F5/atribucion_combinada.csv | U2: =IF(R2=0,"",F2/R2) | V2: =SUMIFS(F$2:F$1589,A$2:A$1589,A2,C$2:C$1589,C2,E$2:E$1589,E2,Q$2:Q$1589,Q2)
A3: compra | B3: nacional | C3: P2 | D3: demografia | E3: svar_hd | F3: -2.93343 | G3: -2.93343 | H3: -1.59917 | I3: 0.0666662 | J3: -10.7148 | K3: 4.04962 | L3: -20.6099 | M3: 11.0989 | N3: C3s | O3: si | P3: no | Q3: V3 | R3: -44.0018 | S3: media posterior (aditiva); R0; C3s condicionada a los supuestos | T3: output/v8/F5/atribucion_combinada.csv | U3: =IF(R3=0,"",F3/R3) | V3: =SUMIFS(F$2:F$1589,A$2:A$1589,A3,C$2:C$1589,C3,E$2:E$1589,E3,Q$2:Q$1589,Q3)
A4: compra | B4: nacional | C4: P2 | D4: demanda_vivienda | E4: svar_hd | F4: -7.40779 | G4: -7.40779 | H4: -3.54416 | I4: 0.168352 | J4: -17.8842 | K4: 1.99552 | L4: -34.0416 | M4: 6.11398 | N4: C3s | O4: si | P4: no | Q4: V3 | R4: -44.0018 | S4: media posterior (aditiva); R0; C3s condicionada a los supuestos | T4: output/v8/F5/atribucion_combinada.csv | U4: =IF(R4=0,"",F4/R4) | V4: =SUMIFS(F$2:F$1589,A$2:A$1589,A4,C$2:C$1589,C4,E$2:E$1589,E4,Q$2:Q$1589,Q4)
A5: compra | B5: nacional | C5: P2 | D5: oferta | E5: svar_hd | F5: -4.81136 | G5: -4.81136 | H5: -2.0535 | I5: 0.109345 | J5: -13.2992 | K5: 2.48894 | L5: -25.0249 | M5: 7.58723 | N5: C3s | O5: si | P5: no | Q5: V3 | R5: -44.0018 | S5: media posterior (aditiva); R0; C3s condicionada a los supuestos | T5: output/v8/F5/atribucion_combinada.csv | U5: =IF(R5=0,"",F5/R5) | V5: =SUMIFS(F$2:F$1589,A$2:A$1589,A5,C$2:C$1589,C5,E$2:E$1589,E5,Q$2:Q$1589,Q5)
A6: compra | B6: nacional | C6: P2 | D6: credito_tipos | E6: svar_hd | F6: -8.59653 | G6: -8.59653 | H6: -5.88471 | I6: 0.195368 | J6: -18.8749 | K6: 0.542165 | L6: -32.8942 | M6: 5.23205 | N6: C3s | O6: si | P6: no | Q6: V3 | R6: -44.0018 | S6: media posterior (aditiva); R0; C3s condicionada a los supuestos | T6: output/v8/F5/atribucion_combinada.csv | U6: =IF(R6=0,"",F6/R6) | V6: =SUMIFS(F$2:F$1589,A$2:A$1589,A6,C$2:C$1589,C6,E$2:E$1589,E6,Q$2:Q$1589,Q6)
A7: compra | B7: nacional | C7: P2 | D7: no_identificados | E7: svar_hd | F7: -7.86463 | G7: -7.86463 | H7: -6.49137 | I7: 0.178734 | J7: -18.8391 | K7: 2.34579 | L7: -29.573 | M7: 12.0855 | N7: C3s | O7: no | P7: no_compite | Q7: V3 | R7: -44.0018 | S7: media posterior (aditiva); R0; C3s condicionada a los supuestos | T7: output/v8/F5/atribucion_combinada.csv | U7: =IF(R7=0,"",F7/R7) | V7: =SUMIFS(F$2:F$1589,A$2:A$1589,A7,C$2:C$1589,C7,E$2:E$1589,E7,Q$2:Q$1589,Q7)
A8: compra | B8: nacional | C8: P2 | D8: determinista | E8: svar_hd | F8: -1.75281 | G8: -1.75281 | H8: -3.18546 | I8: 0.0398349 | J8: -16.3721 | K8: 13.1959 | L8: -26.7554 | M8: 25.8187 | N8: C3s | O8: no | P8: no_compite | Q8: V3 | R8: -44.0018 | S8: media posterior (aditiva); R0; C3s condicionada a los supuestos | T8: output/v8/F5/atribucion_combinada.csv | U8: =IF(R8=0,"",F8/R8) | V8: =SUMIFS(F$2:F$1589,A$2:A$1589,A8,C$2:C$1589,C8,E$2:E$1589,E8,Q$2:Q$1589,Q8)
A9: compra | B9: nacional | C9: P3 | D9: empleo_renta | E9: svar_hd | F9: 7.72218 | G9: 7.72218 | H9: 5.22264 | I9: 0.939816 | J9: -3.46639 | K9: 18.2318 | L9: -15.2388 | M9: 31.2052 | N9: C3s | O9: si | P9: si | Q9: V3 | R9: 8.2167 | S9: media posterior (aditiva); R0; C3s condicionada a los supuestos | T9: output/v8/F5/atribucion_combinada.csv | U9: =IF(R9=0,"",F9/R9) | V9: =SUMIFS(F$2:F$1589,A$2:A$1589,A9,C$2:C$1589,C9,E$2:E$1589,E9,Q$2:Q$1589,Q9)
A10: compra | B10: nacional | C10: P3 | D10: demografia | E10: svar_hd | F10: 0.141604 | G10: 0.141604 | H10: -0.177369 | I10: 0.0172337 | J10: -6.57831 | K10: 6.81486 | L10: -13.9672 | M10: 17.345 | N10: C3s | O10: si | P10: no | Q10: V3 | R10: 8.2167 | S10: media posterior (aditiva); R0; C3s condicionada a los supuestos | T10: output/v8/F5/atribucion_combinada.csv | U10: =IF(R10=0,"",F10/R10) | V10: =SUMIFS(F$2:F$1589,A$2:A$1589,A10,C$2:C$1589,C10,E$2:E$1589,E10,Q$2:Q$1589,Q10)
A11: compra | B11: nacional | C11: P3 | D11: demanda_vivienda | E11: svar_hd | F11: -0.411954 | G11: -0.411954 | H11: 0.532209 | I11: -0.0501362 | J11: -7.20665 | K11: 8.99381 | L11: -18.366 | M11: 17.6965 | N11: C3s | O11: si | P11: no | Q11: V3 | R11: 8.2167 | S11: media posterior (aditiva); R0; C3s condicionada a los supuestos | T11: output/v8/F5/atribucion_combinada.csv | U11: =IF(R11=0,"",F11/R11) | V11: =SUMIFS(F$2:F$1589,A$2:A$1589,A11,C$2:C$1589,C11,E$2:E$1589,E11,Q$2:Q$1589,Q11)
A12: compra | B12: nacional | C12: P3 | D12: oferta | E12: svar_hd | F12: 0.380583 | G12: 0.380583 | H12: 0.18425 | I12: 0.0463182 | J12: -7.29269 | K12: 8.02427 | L12: -16.8044 | M12: 18.9594 | N12: C3s | O12: si | P12: no | Q12: V3 | R12: 8.2167 | S12: media posterior (aditiva); R0; C3s condicionada a los supuestos | T12: output/v8/F5/atribucion_combinada.csv | U12: =IF(R12=0,"",F12/R12) | V12: =SUMIFS(F$2:F$1589,A$2:A$1589,A12,C$2:C$1589,C12,E$2:E$1589,E12,Q$2:Q$1589,Q12)
A13: compra | B13: nacional | C13: P3 | D13: credito_tipos | E13: svar_hd | F13: -1.55002 | G13: -1.55002 | H13: -0.684626 | I13: -0.188642 | J13: -9.78341 | K13: 7.07096 | L13: -17.7135 | M13: 18.4172 | N13: C3s | O13: si | P13: no | Q13: V3 | R13: 8.2167 | S13: media posterior (aditiva); R0; C3s condicionada a los supuestos | T13: output/v8/F5/atribucion_combinada.csv | U13: =IF(R13=0,"",F13/R13) | V13: =SUMIFS(F$2:F$1589,A$2:A$1589,A13,C$2:C$1589,C13,E$2:E$1589,E13,Q$2:Q$1589,Q13)
... A62: compra | B62: nacional | C62: P1 | D62: determinista | E62: svar_hd | F62: 23.0593 | G62: 23.0593 | H62: 22.5386 | I62: 0.306022 | J62: -1.04812 | K62: 50.2903 | L62: -23.2178 | M62: 76.3301 | N62: C3s | O62: no | P62: no_compite | Q62: larga | R62: 75.3518 | S62: media posterior (aditiva); R0; C3s condicionada a los supuestos | T62: output/v8/F5/atribucion_combinada.csv | U62: =IF(R62=0,"",F62/R62) | V62: =SUMIFS(F$2:F$1589,A$2:A$1589,A62,C$2:C$1589,C62,E$2:E$1589,E62,Q$2:Q$1589,Q62)
A63: compra | B63: nacional | C63: P1 | D63: demografia | E63: dominancia | F63: 15.3085 | I63: 0.2047 | J63: 6.97915 | K63: 20.2422 | L63: 3.22483 | M63: 23.2585 | N63: C4 | O63: si | P63: abstiene | Q63: interanual_ipc_tasado | R63: 74.7849 | S63: cuota LMG x R2 x dY (asociacion; no causal) | T63: output/v8/F5/atribucion_combinada.csv | U63: =IF(R63=0,"",F63/R63) | V63: =SUMIFS(F$2:F$1589,A$2:A$1589,A63,C$2:C$1589,C63,E$2:E$1589,E63,Q$2:Q$1589,Q63)
A64: compra | B64: nacional | C64: P1 | D64: empleo_renta | E64: dominancia | F64: 2.82591 | I64: 0.0377872 | J64: 0 | K64: 3.70053 | L64: 0 | M64: 4.31351 | N64: C4 | O64: si | P64: abstiene | Q64: interanual_ipc_tasado | R64: 74.7849 | S64: cuota LMG x R2 x dY (asociacion; no causal) | T64: output/v8/F5/atribucion_combinada.csv | U64: =IF(R64=0,"",F64/R64) | V64: =SUMIFS(F$2:F$1589,A$2:A$1589,A64,C$2:C$1589,C64,E$2:E$1589,E64,Q$2:Q$1589,Q64)
A65: compra | B65: nacional | C65: P1 | D65: credito_tipos | E65: dominancia | F65: 35.1516 | I65: 0.470036 | J65: 34.9004 | K65: 49.4521 | L65: 31.3662 | M65: 56.2306 | N65: C4 | O65: si | P65: abstiene | Q65: interanual_ipc_tasado | R65: 74.7849 | S65: cuota LMG x R2 x dY (asociacion; no causal) | T65: output/v8/F5/atribucion_combinada.csv | U65: =IF(R65=0,"",F65/R65) | V65: =SUMIFS(F$2:F$1589,A$2:A$1589,A65,C$2:C$1589,C65,E$2:E$1589,E65,Q$2:Q$1589,Q65)
A66: compra | B66: nacional | C66: P1 | D66: oferta | E66: dominancia | F66: 1.52909 | I66: 0.0204465 | J66: 0 | K66: 1.70152 | L66: 0 | M66: 2.22823 | N66: C4 | O66: si | P66: abstiene | Q66: interanual_ipc_tasado | R66: 74.7849 | S66: cuota LMG x R2 x dY (asociacion; no causal) | T66: output/v8/F5/atribucion_combinada.csv | U66: =IF(R66=0,"",F66/R66) | V66: =SUMIFS(F$2:F$1589,A$2:A$1589,A66,C$2:C$1589,C66,E$2:E$1589,E66,Q$2:Q$1589,Q66)
A67: compra | B67: nacional | C67: P1 | D67: residuo | E67: dominancia | F67: 19.9699 | I67: 0.267031 | J67: 17.3614 | K67: 28.6794 | L67: 12.5399 | M67: 31.1334 | N67: C4 | O67: no | P67: no_compite | Q67: interanual_ipc_tasado | R67: 74.7849 | S67: cuota LMG x R2 x dY (asociacion; no causal) | T67: output/v8/F5/atribucion_combinada.csv | U67: =IF(R67=0,"",F67/R67) | V67: =SUMIFS(F$2:F$1589,A$2:A$1589,A67,C$2:C$1589,C67,E$2:E$1589,E67,Q$2:Q$1589,Q67)
A68: compra | B68: nacional | C68: P1 | D68: demanda_externa | E68: dominancia | N68: C4 | O68: si | P68: abstiene | Q68: interanual_ipc_tasado | S68: cuota LMG x R2 x dY (asociacion; no causal) | T68: output/v8/F5/atribucion_combinada.csv | U68: =IF(R68=0,"",F68/R68) | V68: =SUMIFS(F$2:F$1589,A$2:A$1589,A68,C$2:C$1589,C68,E$2:E$1589,E68,Q$2:Q$1589,Q68)
A69: compra | B69: nacional | C69: P1 | D69: turismo | E69: dominancia | N69: C4 | O69: si | P69: abstiene | Q69: interanual_ipc_tasado | S69: cuota LMG x R2 x dY (asociacion; no causal) | T69: output/v8/F5/atribucion_combinada.csv | U69: =IF(R69=0,"",F69/R69) | V69: =SUMIFS(F$2:F$1589,A$2:A$1589,A69,C$2:C$1589,C69,E$2:E$1589,E69,Q$2:Q$1589,Q69)
A70: compra | B70: nacional | C70: P1 | D70: factor_europeo | E70: dominancia | N70: C4 | O70: si | P70: abstiene | Q70: interanual_ipc_tasado | S70: cuota LMG x R2 x dY (asociacion; no causal) | T70: output/v8/F5/atribucion_combinada.csv | U70: =IF(R70=0,"",F70/R70) | V70: =SUMIFS(F$2:F$1589,A$2:A$1589,A70,C$2:C$1589,C70,E$2:E$1589,E70,Q$2:Q$1589,Q70)
A71: compra | B71: nacional | C71: P2 | D71: demografia | E71: dominancia | F71: -3.06021 | I71: 0.0695474 | J71: -3.9061 | K71: 0 | L71: -5.15279 | M71: 0 | N71: C4 | O71: si | P71: no | Q71: interanual_ipc_tasado | R71: -44.0018 | S71: cuota LMG x R2 x dY (asociacion; no causal) | T71: output/v8/F5/atribucion_combinada.csv | U71: =IF(R71=0,"",F71/R71) | V71: =SUMIFS(F$2:F$1589,A$2:A$1589,A71,C$2:C$1589,C71,E$2:E$1589,E71,Q$2:Q$1589,Q71)
A72: compra | B72: nacional | C72: P2 | D72: empleo_renta | E72: dominancia | F72: -9.05181 | I72: 0.205714 | J72: -11.3565 | K72: -6.69725 | L72: -12.6017 | M72: -4.76672 | N72: C4 | O72: si | P72: no | Q72: interanual_ipc_tasado | R72: -44.0018 | S72: cuota LMG x R2 x dY (asociacion; no causal) | T72: output/v8/F5/atribucion_combinada.csv | U72: =IF(R72=0,"",F72/R72) | V72: =SUMIFS(F$2:F$1589,A$2:A$1589,A72,C$2:C$1589,C72,E$2:E$1589,E72,Q$2:Q$1589,Q72)
A73: compra | B73: nacional | C73: P2 | D73: credito_tipos | E73: dominancia | F73: -15.8711 | I73: 0.360691 | J73: -24.67 | K73: -15.768 | L73: -26.9376 | M73: -12.4889 | N73: C4 | O73: si | P73: no | Q73: interanual_ipc_tasado | R73: -44.0018 | S73: cuota LMG x R2 x dY (asociacion; no causal) | T73: output/v8/F5/atribucion_combinada.csv | U73: =IF(R73=0,"",F73/R73) | V73: =SUMIFS(F$2:F$1589,A$2:A$1589,A73,C$2:C$1589,C73,E$2:E$1589,E73,Q$2:Q$1589,Q73)
A74: compra | B74: nacional | C74: P2 | D74: oferta | E74: dominancia | F74: -0.38256 | I74: 0.00869417 | J74: -0.415233 | K74: 0 | L74: -0.560654 | M74: 0 | N74: C4 | O74: si | P74: no | Q74: interanual_ipc_tasado | R74: -44.0018 | S74: cuota LMG x R2 x dY (asociacion; no causal) | T74: output/v8/F5/atribucion_combinada.csv | U74: =IF(R74=0,"",F74/R74) | V74: =SUMIFS(F$2:F$1589,A$2:A$1589,A74,C$2:C$1589,C74,E$2:E$1589,E74,Q$2:Q$1589,Q74)
A75: compra | B75: nacional | C75: P2 | D75: demanda_externa | E75: dominancia | F75: -3.05562 | I75: 0.069443 | J75: -4.34185 | K75: -2.48807 | L75: -4.6889 | M75: -1.64336 | N75: C4 | O75: si | P75: no | Q75: interanual_ipc_tasado | R75: -44.0018 | S75: cuota LMG x R2 x dY (asociacion; no causal) | T75: output/v8/F5/atribucion_combinada.csv | U75: =IF(R75=0,"",F75/R75) | V75: =SUMIFS(F$2:F$1589,A$2:A$1589,A75,C$2:C$1589,C75,E$2:E$1589,E75,Q$2:Q$1589,Q75)
A76: compra | B76: nacional | C76: P2 | D76: factor_europeo | E76: dominancia | F76: -10.6612 | I76: 0.242289 | J76: -12.0121 | K76: -7.92906 | L76: -13.6646 | M76: -6.97924 | N76: C4 | O76: si | P76: si | Q76: interanual_ipc_tasado | R76: -44.0018 | S76: cuota LMG x R2 x dY (asociacion; no causal) | T76: output/v8/F5/atribucion_combinada.csv | U76: =IF(R76=0,"",F76/R76) | V76: =SUMIFS(F$2:F$1589,A$2:A$1589,A76,C$2:C$1589,C76,E$2:E$1589,E76,Q$2:Q$1589,Q76)
A77: compra | B77: nacional | C77: P2 | D77: residuo | E77: dominancia | F77: -1.91941 | I77: 0.0436211 | J77: -3.32054 | K77: -1.88124 | L77: -3.55929 | M77: -0.861842 | N77: C4 | O77: no | P77: no_compite | Q77: interanual_ipc_tasado | R77: -44.0018 | S77: cuota LMG x R2 x dY (asociacion; no causal) | T77: output/v8/F5/atribucion_combinada.csv | U77: =IF(R77=0,"",F77/R77) | V77: =SUMIFS(F$2:F$1589,A$2:A$1589,A77,C$2:C$1589,C77,E$2:E$1589,E77,Q$2:Q$1589,Q77)
A78: compra | B78: nacional | C78: P2 | D78: turismo | E78: dominancia | N78: C4 | O78: si | P78: no | Q78: interanual_ipc_tasado | S78: cuota LMG x R2 x dY (asociacion; no causal) | T78: output/v8/F5/atribucion_combinada.csv | U78: =IF(R78=0,"",F78/R78) | V78: =SUMIFS(F$2:F$1589,A$2:A$1589,A78,C$2:C$1589,C78,E$2:E$1589,E78,Q$2:Q$1589,Q78)
A79: compra | B79: nacional | C79: P3 | D79: demografia | E79: dominancia | F79: 1.83553 | I79: 0.22339 | J79: 1.21055 | K79: 2.38341 | L79: 0.742851 | M79: 2.58738 | N79: C4 | O79: si | P79: no | Q79: interanual_ipc_tasado | R79: 8.2167 | S79: cuota LMG x R2 x dY (asociacion; no causal) | T79: output/v8/F5/atribucion_combinada.csv | U79: =IF(R79=0,"",F79/R79) | V79: =SUMIFS(F$2:F$1589,A$2:A$1589,A79,C$2:C$1589,C79,E$2:E$1589,E79,Q$2:Q$1589,Q79)
A80: compra | B80: nacional | C80: P3 | D80: empleo_renta | E80: dominancia | F80: 2.1377 | I80: 0.260165 | J80: 1.97152 | K80: 3.4024 | L80: 1.45221 | M80: 3.63231 | N80: C4 | O80: si | P80: si | Q80: interanual_ipc_tasado | R80: 8.2167 | S80: cuota LMG x R2 x dY (asociacion; no causal) | T80: output/v8/F5/atribucion_combinada.csv | U80: =IF(R80=0,"",F80/R80) | V80: =SUMIFS(F$2:F$1589,A$2:A$1589,A80,C$2:C$1589,C80,E$2:E$1589,E80,Q$2:Q$1589,Q80)
A81: compra | B81: nacional | C81: P3 | D81: credito_tipos | E81: dominancia | F81: 0.435345 | I81: 0.0529829 | J81: 0 | K81: 0.300797 | L81: 0 | M81: 0.468445 | N81: C4 | O81: si | P81: no | Q81: interanual_ipc_tasado | R81: 8.2167 | S81: cuota LMG x R2 x dY (asociacion; no causal) | T81: output/v8/F5/atribucion_combinada.csv | U81: =IF(R81=0,"",F81/R81) | V81: =SUMIFS(F$2:F$1589,A$2:A$1589,A81,C$2:C$1589,C81,E$2:E$1589,E81,Q$2:Q$1589,Q81)
A82: compra | B82: nacional | C82: P3 | D82: oferta | E82: dominancia | F82: 0.29778 | I82: 0.0362408 | J82: 0 | K82: 0.243319 | L82: 0 | M82: 0.308558 | N82: C4 | O82: si | P82: no | Q82: interanual_ipc_tasado | R82: 8.2167 | S82: cuota LMG x R2 x dY (asociacion; no causal) | T82: output/v8/F5/atribucion_combinada.csv | U82: =IF(R82=0,"",F82/R82) | V82: =SUMIFS(F$2:F$1589,A$2:A$1589,A82,C$2:C$1589,C82,E$2:E$1589,E82,Q$2:Q$1589,Q82)
A83: compra | B83: nacional | C83: P3 | D83: demanda_externa | E83: dominancia | F83: 0.708923 | I83: 0.0862783 | J83: 0.599327 | K83: 1.14953 | L83: 0.330632 | M83: 1.21407 | N83: C4 | O83: si | P83: no | Q83: interanual_ipc_tasado | R83: 8.2167 | S83: cuota LMG x R2 x dY (asociacion; no causal) | T83: output/v8/F5/atribucion_combinada.csv | U83: =IF(R83=0,"",F83/R83) | V83: =SUMIFS(F$2:F$1589,A$2:A$1589,A83,C$2:C$1589,C83,E$2:E$1589,E83,Q$2:Q$1589,Q83)
A84: compra | B84: nacional | C84: P3 | D84: factor_europeo | E84: dominancia | F84: 2.08513 | I84: 0.253767 | J84: 1.99585 | K84: 3.71765 | L84: 1.73703 | M84: 3.92152 | N84: C4 | O84: si | P84: no | Q84: interanual_ipc_tasado | R84: 8.2167 | S84: cuota LMG x R2 x dY (asociacion; no causal) | T84: output/v8/F5/atribucion_combinada.csv | U84: =IF(R84=0,"",F84/R84) | V84: =SUMIFS(F$2:F$1589,A$2:A$1589,A84,C$2:C$1589,C84,E$2:E$1589,E84,Q$2:Q$1589,Q84)
A85: compra | B85: nacional | C85: P3 | D85: residuo | E85: dominancia | F85: 0.716293 | I85: 0.0871753 | J85: 0.0596246 | K85: 1.10471 | L85: 0 | M85: 1.21589 | N85: C4 | O85: no | P85: no_compite | Q85: interanual_ipc_tasado | R85: 8.2167 | S85: cuota LMG x R2 x dY (asociacion; no causal) | T85: output/v8/F5/atribucion_combinada.csv | U85: =IF(R85=0,"",F85/R85) | V85: =SUMIFS(F$2:F$1589,A$2:A$1589,A85,C$2:C$1589,C85,E$2:E$1589,E85,Q$2:Q$1589,Q85)
A86: compra | B86: nacional | C86: P3 | D86: turismo | E86: dominancia | N86: C4 | O86: si | P86: no | Q86: interanual_ipc_tasado | S86: cuota LMG x R2 x dY (asociacion; no causal) | T86: output/v8/F5/atribucion_combinada.csv | U86: =IF(R86=0,"",F86/R86) | V86: =SUMIFS(F$2:F$1589,A$2:A$1589,A86,C$2:C$1589,C86,E$2:E$1589,E86,Q$2:Q$1589,Q86)
A87: compra | B87: nacional | C87: P4 | D87: demografia | E87: dominancia | F87: -0.933381 | I87: 0.171048 | J87: -1.09504 | K87: 0 | L87: -1.22149 | M87: 0 | N87: C4 | O87: si | P87: no | Q87: interanual_ipc_tasado | R87: -5.45682 | S87: cuota LMG x R2 x dY (asociacion; no causal) | T87: output/v8/F5/atribucion_combinada.csv | U87: =IF(R87=0,"",F87/R87) | V87: =SUMIFS(F$2:F$1589,A$2:A$1589,A87,C$2:C$1589,C87,E$2:E$1589,E87,Q$2:Q$1589,Q87)
A88: compra | B88: nacional | C88: P4 | D88: empleo_renta | E88: dominancia | F88: -0.39198 | I88: 0.071833 | J88: -0.26741 | K88: 0 | L88: -0.395672 | M88: 0 | N88: C4 | O88: si | P88: no | Q88: interanual_ipc_tasado | R88: -5.45682 | S88: cuota LMG x R2 x dY (asociacion; no causal) | T88: output/v8/F5/atribucion_combinada.csv | U88: =IF(R88=0,"",F88/R88) | V88: =SUMIFS(F$2:F$1589,A$2:A$1589,A88,C$2:C$1589,C88,E$2:E$1589,E88,Q$2:Q$1589,Q88)
A89: compra | B89: nacional | C89: P4 | D89: credito_tipos | E89: dominancia | F89: -1.89632 | I89: 0.347513 | J89: -3.44514 | K89: -2.17428 | L89: -3.59509 | M89: -1.72277 | N89: C4 | O89: si | P89: si | Q89: interanual_ipc_tasado | R89: -5.45682 | S89: cuota LMG x R2 x dY (asociacion; no causal) | T89: output/v8/F5/atribucion_combinada.csv | U89: =IF(R89=0,"",F89/R89) | V89: =SUMIFS(F$2:F$1589,A$2:A$1589,A89,C$2:C$1589,C89,E$2:E$1589,E89,Q$2:Q$1589,Q89)
A90: compra | B90: nacional | C90: P4 | D90: residuo | E90: dominancia | F90: -2.23514 | I90: 0.409606 | J90: -4.20643 | K90: -2.60973 | L90: -4.47029 | M90: -2.23514 | N90: C4 | O90: no | P90: no_compite | Q90: interanual_ipc_tasado | R90: -5.45682 | S90: cuota LMG x R2 x dY (asociacion; no causal) | T90: output/v8/F5/atribucion_combinada.csv | U90: =IF(R90=0,"",F90/R90) | V90: =SUMIFS(F$2:F$1589,A$2:A$1589,A90,C$2:C$1589,C90,E$2:E$1589,E90,Q$2:Q$1589,Q90)
A91: compra | B91: nacional | C91: P4 | D91: factor_europeo | E91: dominancia | N91: C4 | O91: si | P91: no | Q91: interanual_ipc_tasado | S91: cuota LMG x R2 x dY (asociacion; no causal) | T91: output/v8/F5/atribucion_combinada.csv | U91: =IF(R91=0,"",F91/R91) | V91: =SUMIFS(F$2:F$1589,A$2:A$1589,A91,C$2:C$1589,C91,E$2:E$1589,E91,Q$2:Q$1589,Q91)
A92: compra | B92: nacional | C92: P4 | D92: turismo | E92: dominancia | N92: C4 | O92: si | P92: no | Q92: interanual_ipc_tasado | S92: cuota LMG x R2 x dY (asociacion; no causal) | T92: output/v8/F5/atribucion_combinada.csv | U92: =IF(R92=0,"",F92/R92) | V92: =SUMIFS(F$2:F$1589,A$2:A$1589,A92,C$2:C$1589,C92,E$2:E$1589,E92,Q$2:Q$1589,Q92)
A93: compra | B93: nacional | C93: P4 | D93: demanda_externa | E93: dominancia | N93: C4 | O93: si | P93: no | Q93: interanual_ipc_tasado | S93: cuota LMG x R2 x dY (asociacion; no causal) | T93: output/v8/F5/atribucion_combinada.csv | U93: =IF(R93=0,"",F93/R93) | V93: =SUMIFS(F$2:F$1589,A$2:A$1589,A93,C$2:C$1589,C93,E$2:E$1589,E93,Q$2:Q$1589,Q93)
A94: compra | B94: nacional | C94: P4 | D94: oferta | E94: dominancia | N94: C4 | O94: si | P94: no | Q94: interanual_ipc_tasado | S94: cuota LMG x R2 x dY (asociacion; no causal) | T94: output/v8/F5/atribucion_combinada.csv | U94: =IF(R94=0,"",F94/R94) | V94: =SUMIFS(F$2:F$1589,A$2:A$1589,A94,C$2:C$1589,C94,E$2:E$1589,E94,Q$2:Q$1589,Q94)
A95: compra | B95: nacional | C95: P5 | D95: demografia | E95: dominancia | F95: 1.46945 | I95: 0.0797736 | J95: 0.0666968 | K95: 2.06713 | L95: 0 | M95: 2.23748 | N95: C4 | O95: si | P95: no | Q95: interanual_ipc_tasado | R95: 18.4203 | S95: cuota LMG x R2 x dY (asociacion; no causal) | T95: output/v8/F5/atribucion_combinada.csv | U95: =IF(R95=0,"",F95/R95) | V95: =SUMIFS(F$2:F$1589,A$2:A$1589,A95,C$2:C$1589,C95,E$2:E$1589,E95,Q$2:Q$1589,Q95)
A96: compra | B96: nacional | C96: P5 | D96: empleo_renta | E96: dominancia | F96: 2.33108 | I96: 0.126549 | J96: 1.95913 | K96: 3.76003 | L96: 0.819874 | M96: 3.91692 | N96: C4 | O96: si | P96: no | Q96: interanual_ipc_tasado | R96: 18.4203 | S96: cuota LMG x R2 x dY (asociacion; no causal) | T96: output/v8/F5/atribucion_combinada.csv | U96: =IF(R96=0,"",F96/R96) | V96: =SUMIFS(F$2:F$1589,A$2:A$1589,A96,C$2:C$1589,C96,E$2:E$1589,E96,Q$2:Q$1589,Q96)
A97: compra | B97: nacional | C97: P5 | D97: credito_tipos | E97: dominancia | F97: 2.05363 | I97: 0.111488 | J97: 0.581489 | K97: 3.34812 | L97: 0 | M97: 3.57806 | N97: C4 | O97: si | P97: si | Q97: interanual_ipc_tasado | R97: 18.4203 | S97: cuota LMG x R2 x dY (asociacion; no causal) | T97: output/v8/F5/atribucion_combinada.csv | U97: =IF(R97=0,"",F97/R97) | V97: =SUMIFS(F$2:F$1589,A$2:A$1589,A97,C$2:C$1589,C97,E$2:E$1589,E97,Q$2:Q$1589,Q97)
A98: compra | B98: nacional | C98: P5 | D98: oferta | E98: dominancia | F98: 0.0890233 | I98: 0.00483289 | J98: 0 | K98: 0 | L98: 0 | M98: 0.0611163 | N98: C4 | O98: si | P98: no | Q98: interanual_ipc_tasado | R98: 18.4203 | S98: cuota LMG x R2 x dY (asociacion; no causal) | T98: output/v8/F5/atribucion_combinada.csv | U98: =IF(R98=0,"",F98/R98) | V98: =SUMIFS(F$2:F$1589,A$2:A$1589,A98,C$2:C$1589,C98,E$2:E$1589,E98,Q$2:Q$1589,Q98)
A99: compra | B99: nacional | C99: P5 | D99: demanda_externa | E99: dominancia | F99: 1.08474 | I99: 0.0588886 | J99: 0.102566 | K99: 1.40203 | L99: 0 | M99: 1.58384 | N99: C4 | O99: si | P99: no | Q99: interanual_ipc_tasado | R99: 18.4203 | S99: cuota LMG x R2 x dY (asociacion; no causal) | T99: output/v8/F5/atribucion_combinada.csv | U99: =IF(R99=0,"",F99/R99) | V99: =SUMIFS(F$2:F$1589,A$2:A$1589,A99,C$2:C$1589,C99,E$2:E$1589,E99,Q$2:Q$1589,Q99)
A100: compra | B100: nacional | C100: P5 | D100: turismo | E100: dominancia | F100: 5.32849 | I100: 0.289273 | J100: 4.99067 | K100: 6.26697 | L100: 4.46068 | M100: 7.06306 | N100: C4 | O100: si | P100: no | Q100: interanual_ipc_tasado | R100: 18.4203 | S100: cuota LMG x R2 x dY (asociacion; no causal) | T100: output/v8/F5/atribucion_combinada.csv | U100: =IF(R100=0,"",F100/R100) | V100: =SUMIFS(F$2:F$1589,A$2:A$1589,A100,C$2:C$1589,C100,E$2:E$1589,E100,Q$2:Q$1589,Q100)
A101: compra | B101: nacional | C101: P5 | D101: factor_europeo | E101: dominancia | F101: 5.84685 | I101: 0.317413 | J101: 4.98854 | K101: 7.51235 | L101: 4.65468 | M101: 9.29757 | N101: C4 | O101: si | P101: no | Q101: interanual_ipc_tasado | R101: 18.4203 | S101: cuota LMG x R2 x dY (asociacion; no causal) | T101: output/v8/F5/atribucion_combinada.csv | U101: =IF(R101=0,"",F101/R101) | V101: =SUMIFS(F$2:F$1589,A$2:A$1589,A101,C$2:C$1589,C101,E$2:E$1589,E101,Q$2:Q$1589,Q101)
A102: compra | B102: nacional | C102: P5 | D102: residuo | E102: dominancia | F102: 0.217017 | I102: 0.0117814 | J102: 0.214581 | K102: 0.434034 | L102: 0.108676 | M102: 0.434034 | N102: C4 | O102: no | P102: no_compite | Q102: interanual_ipc_tasado | R102: 18.4203 | S102: cuota LMG x R2 x dY (asociacion; no causal) | T102: output/v8/F5/atribucion_combinada.csv | U102: =IF(R102=0,"",F102/R102) | V102: =SUMIFS(F$2:F$1589,A$2:A$1589,A102,C$2:C$1589,C102,E$2:E$1589,E102,Q$2:Q$1589,Q102)
A103: compra | B103: nacional | C103: completo | D103: demografia | E103: dominancia | F103: 8.62036 | I103: 0.227243 | J103: 5.42936 | K103: 11.4235 | L103: 2.77638 | M103: 13.1307 | N103: C4 | O103: si | P103: no_vota | Q103: interanual_ipc_tasado | R103: 37.9345 | S103: cuota LMG x R2 x dY (asociacion; no causal) | T103: output/v8/F5/atribucion_combinada.csv | U103: =IF(R103=0,"",F103/R103) | V103: =SUMIFS(F$2:F$1589,A$2:A$1589,A103,C$2:C$1589,C103,E$2:E$1589,E103,Q$2:Q$1589,Q103)
A104: compra | B104: nacional | C104: completo | D104: empleo_renta | E104: dominancia | F104: 3.02521 | I104: 0.0797484 | J104: 0.562359 | K104: 4.32649 | L104: 0 | M104: 4.97109 | N104: C4 | O104: si | P104: no_vota | Q104: interanual_ipc_tasado | R104: 37.9345 | S104: cuota LMG x R2 x dY (asociacion; no causal) | T104: output/v8/F5/atribucion_combinada.csv | U104: =IF(R104=0,"",F104/R104) | V104: =SUMIFS(F$2:F$1589,A$2:A$1589,A104,C$2:C$1589,C104,E$2:E$1589,E104,Q$2:Q$1589,Q104)
A105: compra | B105: nacional | C105: completo | D105: credito_tipos | E105: dominancia | F105: 0.45024 | I105: 0.0118689 | J105: 0 | K105: 0.534806 | L105: 0 | M105: 0.683829 | N105: C4 | O105: si | P105: no_vota | Q105: interanual_ipc_tasado | R105: 37.9345 | S105: cuota LMG x R2 x dY (asociacion; no causal) | T105: output/v8/F5/atribucion_combinada.csv | U105: =IF(R105=0,"",F105/R105) | V105: =SUMIFS(F$2:F$1589,A$2:A$1589,A105,C$2:C$1589,C105,E$2:E$1589,E105,Q$2:Q$1589,Q105)
A106: compra | B106: nacional | C106: completo | D106: oferta | E106: dominancia | F106: 5.65324 | I106: 0.149026 | J106: 4.33154 | K106: 7.25924 | L106: 3.35685 | M106: 8.34036 | N106: C4 | O106: si | P106: no_vota | Q106: interanual_ipc_tasado | R106: 37.9345 | S106: cuota LMG x R2 x dY (asociacion; no causal) | T106: output/v8/F5/atribucion_combinada.csv | U106: =IF(R106=0,"",F106/R106) | V106: =SUMIFS(F$2:F$1589,A$2:A$1589,A106,C$2:C$1589,C106,E$2:E$1589,E106,Q$2:Q$1589,Q106)
... A108: compra | B108: nacional | C108: completo | D108: residuo | E108: dominancia | F108: 8.99858 | I108: 0.237213 | J108: 7.81715 | K108: 12.5398 | L108: 5.67696 | M108: 14.085 | N108: C4 | O108: no | P108: no_compite | Q108: interanual_ipc_tasado | R108: 37.9345 | S108: cuota LMG x R2 x dY (asociacion; no causal) | T108: output/v8/F5/atribucion_combinada.csv | U108: =IF(R108=0,"",F108/R108) | V108: =SUMIFS(F$2:F$1589,A$2:A$1589,A108,C$2:C$1589,C108,E$2:E$1589,E108,Q$2:Q$1589,Q108)
A109: compra | B109: nacional | C109: completo | D109: demanda_externa | E109: dominancia | N109: C4 | O109: si | P109: no_vota | Q109: interanual_ipc_tasado | S109: cuota LMG x R2 x dY (asociacion; no causal) | T109: output/v8/F5/atribucion_combinada.csv | U109: =IF(R109=0,"",F109/R109) | V109: =SUMIFS(F$2:F$1589,A$2:A$1589,A109,C$2:C$1589,C109,E$2:E$1589,E109,Q$2:Q$1589,Q109)
A110: compra | B110: nacional | C110: completo | D110: turismo | E110: dominancia | N110: C4 | O110: si | P110: no_vota | Q110: interanual_ipc_tasado | S110: cuota LMG x R2 x dY (asociacion; no causal) | T110: output/v8/F5/atribucion_combinada.csv | U110: =IF(R110=0,"",F110/R110) | V110: =SUMIFS(F$2:F$1589,A$2:A$1589,A110,C$2:C$1589,C110,E$2:E$1589,E110,Q$2:Q$1589,Q110)
A111: alquiler | B111: nacional | C111: P1 | D111: demografia | E111: dominancia | F111: 0.232032 | I111: 0.0471089 | J111: 0 | K111: 0.235066 | L111: 0 | M111: 0.311828 | N111: C4 | O111: si | P111: no | Q111: interanual_ipc_ipc_alquiler | R111: 4.92545 | S111: cuota LMG x R2 x dY (asociacion; no causal) | T111: output/v8/F5/atribucion_combinada.csv | U111: =IF(R111=0,"",F111/R111) | V111: =SUMIFS(F$2:F$1589,A$2:A$1589,A111,C$2:C$1589,C111,E$2:E$1589,E111,Q$2:Q$1589,Q111)
A112: alquiler | B112: nacional | C112: P1 | D112: empleo_renta | E112: dominancia | F112: 0.325267 | I112: 0.0660381 | J112: 0 | K112: 0.471915 | L112: 0 | M112: 0.55308 | N112: C4 | O112: si | P112: no | Q112: interanual_ipc_ipc_alquiler | R112: 4.92545 | S112: cuota LMG x R2 x dY (asociacion; no causal) | T112: output/v8/F5/atribucion_combinada.csv | U112: =IF(R112=0,"",F112/R112) | V112: =SUMIFS(F$2:F$1589,A$2:A$1589,A112,C$2:C$1589,C112,E$2:E$1589,E112,Q$2:Q$1589,Q112)
A113: alquiler | B113: nacional | C113: P1 | D113: credito_tipos | E113: dominancia | F113: 3.14703 | I113: 0.638933 | J113: 3.08064 | K113: 4.05801 | L113: 2.90886 | M113: 4.39615 | N113: C4 | O113: si | P113: no | Q113: interanual_ipc_ipc_alquiler | R113: 4.92545 | S113: cuota LMG x R2 x dY (asociacion; no causal) | T113: output/v8/F5/atribucion_combinada.csv | U113: =IF(R113=0,"",F113/R113) | V113: =SUMIFS(F$2:F$1589,A$2:A$1589,A113,C$2:C$1589,C113,E$2:E$1589,E113,Q$2:Q$1589,Q113)
A114: alquiler | B114: nacional | C114: P1 | D114: oferta | E114: dominancia | F114: 0.29709 | I114: 0.0603173 | J114: 0 | K114: 0.350936 | L114: 0 | M114: 0.403635 | N114: C4 | O114: si | P114: no | Q114: interanual_ipc_ipc_alquiler | R114: 4.92545 | S114: cuota LMG x R2 x dY (asociacion; no causal) | T114: output/v8/F5/atribucion_combinada.csv | U114: =IF(R114=0,"",F114/R114) | V114: =SUMIFS(F$2:F$1589,A$2:A$1589,A114,C$2:C$1589,C114,E$2:E$1589,E114,Q$2:Q$1589,Q114)
A115: alquiler | B115: nacional | C115: P1 | D115: factor_europeo | E115: dominancia | F115: 0.649059 | I115: 0.131777 | J115: 0.609521 | K115: 1.13215 | L115: 0.457866 | M115: 1.20005 | N115: C4 | O115: si | P115: si | Q115: interanual_ipc_ipc_alquiler | R115: 4.92545 | S115: cuota LMG x R2 x dY (asociacion; no causal) | T115: output/v8/F5/atribucion_combinada.csv | U115: =IF(R115=0,"",F115/R115) | V115: =SUMIFS(F$2:F$1589,A$2:A$1589,A115,C$2:C$1589,C115,E$2:E$1589,E115,Q$2:Q$1589,Q115)
A116: alquiler | B116: nacional | C116: P1 | D116: residuo | E116: dominancia | F116: 0.274966 | I116: 0.0558256 | J116: 0.269865 | K116: 0.456101 | L116: 0.105886 | M116: 0.506818 | N116: C4 | O116: no | P116: no_compite | Q116: interanual_ipc_ipc_alquiler | R116: 4.92545 | S116: cuota LMG x R2 x dY (asociacion; no causal) | T116: output/v8/F5/atribucion_combinada.csv | U116: =IF(R116=0,"",F116/R116) | V116: =SUMIFS(F$2:F$1589,A$2:A$1589,A116,C$2:C$1589,C116,E$2:E$1589,E116,Q$2:Q$1589,Q116)
A117: alquiler | B117: nacional | C117: P1 | D117: demanda_externa | E117: dominancia | N117: C4 | O117: si | P117: no | Q117: interanual_ipc_ipc_alquiler | S117: cuota LMG x R2 x dY (asociacion; no causal) | T117: output/v8/F5/atribucion_combinada.csv | U117: =IF(R117=0,"",F117/R117) | V117: =SUMIFS(F$2:F$1589,A$2:A$1589,A117,C$2:C$1589,C117,E$2:E$1589,E117,Q$2:Q$1589,Q117)
A118: alquiler | B118: nacional | C118: P1 | D118: turismo | E118: dominancia | N118: C4 | O118: si | P118: no | Q118: interanual_ipc_ipc_alquiler | S118: cuota LMG x R2 x dY (asociacion; no causal) | T118: output/v8/F5/atribucion_combinada.csv | U118: =IF(R118=0,"",F118/R118) | V118: =SUMIFS(F$2:F$1589,A$2:A$1589,A118,C$2:C$1589,C118,E$2:E$1589,E118,Q$2:Q$1589,Q118)
A119: alquiler | B119: nacional | C119: P2 | D119: demografia | E119: dominancia | F119: -0.703247 | I119: 0.260185 | J119: -0.885433 | K119: -0.521095 | L119: -1.06332 | M119: -0.408886 | N119: C4 | O119: si | P119: no | Q119: interanual_ipc_ipc_alquiler | R119: -2.70287 | S119: cuota LMG x R2 x dY (asociacion; no causal) | T119: output/v8/F5/atribucion_combinada.csv | U119: =IF(R119=0,"",F119/R119) | V119: =SUMIFS(F$2:F$1589,A$2:A$1589,A119,C$2:C$1589,C119,E$2:E$1589,E119,Q$2:Q$1589,Q119)
A120: alquiler | B120: nacional | C120: P2 | D120: empleo_renta | E120: dominancia | F120: -0.253536 | I120: 0.0938025 | J120: -0.387505 | K120: -0.0986985 | L120: -0.431982 | M120: -0.0036342 | N120: C4 | O120: si | P120: si | Q120: interanual_ipc_ipc_alquiler | R120: -2.70287 | S120: cuota LMG x R2 x dY (asociacion; no causal) | T120: output/v8/F5/atribucion_combinada.csv | U120: =IF(R120=0,"",F120/R120) | V120: =SUMIFS(F$2:F$1589,A$2:A$1589,A120,C$2:C$1589,C120,E$2:E$1589,E120,Q$2:Q$1589,Q120)
A121: alquiler | B121: nacional | C121: P2 | D121: credito_tipos | E121: dominancia | F121: -1.21733 | I121: 0.450384 | J121: -1.5185 | K121: -1.19683 | L121: -1.61019 | M121: -1.01083 | N121: C4 | O121: si | P121: no | Q121: interanual_ipc_ipc_alquiler | R121: -2.70287 | S121: cuota LMG x R2 x dY (asociacion; no causal) | T121: output/v8/F5/atribucion_combinada.csv | U121: =IF(R121=0,"",F121/R121) | V121: =SUMIFS(F$2:F$1589,A$2:A$1589,A121,C$2:C$1589,C121,E$2:E$1589,E121,Q$2:Q$1589,Q121)
A122: alquiler | B122: nacional | C122: P2 | D122: oferta | E122: dominancia | F122: -0.0424933 | I122: 0.0157216 | J122: -0.0584992 | K122: 0 | L122: -0.0700852 | M122: 0 | N122: C4 | O122: si | P122: no | Q122: interanual_ipc_ipc_alquiler | R122: -2.70287 | S122: cuota LMG x R2 x dY (asociacion; no causal) | T122: output/v8/F5/atribucion_combinada.csv | U122: =IF(R122=0,"",F122/R122) | V122: =SUMIFS(F$2:F$1589,A$2:A$1589,A122,C$2:C$1589,C122,E$2:E$1589,E122,Q$2:Q$1589,Q122)
A123: alquiler | B123: nacional | C123: P2 | D123: demanda_externa | E123: dominancia | F123: -0.265716 | I123: 0.098309 | J123: -0.416426 | K123: -0.107614 | L123: -0.475851 | M123: -0.0430746 | N123: C4 | O123: si | P123: no | Q123: interanual_ipc_ipc_alquiler | R123: -2.70287 | S123: cuota LMG x R2 x dY (asociacion; no causal) | T123: output/v8/F5/atribucion_combinada.csv | U123: =IF(R123=0,"",F123/R123) | V123: =SUMIFS(F$2:F$1589,A$2:A$1589,A123,C$2:C$1589,C123,E$2:E$1589,E123,Q$2:Q$1589,Q123)
A124: alquiler | B124: nacional | C124: P2 | D124: factor_europeo | E124: dominancia | F124: -0.0884862 | I124: 0.0327379 | J124: -0.0938367 | K124: 0 | L124: -0.110701 | M124: 0 | N124: C4 | O124: si | P124: no | Q124: interanual_ipc_ipc_alquiler | R124: -2.70287 | S124: cuota LMG x R2 x dY (asociacion; no causal) | T124: output/v8/F5/atribucion_combinada.csv | U124: =IF(R124=0,"",F124/R124) | V124: =SUMIFS(F$2:F$1589,A$2:A$1589,A124,C$2:C$1589,C124,E$2:E$1589,E124,Q$2:Q$1589,Q124)
A125: alquiler | B125: nacional | C125: P2 | D125: residuo | E125: dominancia | F125: -0.132062 | I125: 0.0488599 | J125: -0.225996 | K125: -0.117976 | L125: -0.244149 | M125: -0.0305394 | N125: C4 | O125: no | P125: no_compite | Q125: interanual_ipc_ipc_alquiler | R125: -2.70287 | S125: cuota LMG x R2 x dY (asociacion; no causal) | T125: output/v8/F5/atribucion_combinada.csv | U125: =IF(R125=0,"",F125/R125) | V125: =SUMIFS(F$2:F$1589,A$2:A$1589,A125,C$2:C$1589,C125,E$2:E$1589,E125,Q$2:Q$1589,Q125)
A126: alquiler | B126: nacional | C126: P2 | D126: turismo | E126: dominancia | N126: C4 | O126: si | P126: no | Q126: interanual_ipc_ipc_alquiler | S126: cuota LMG x R2 x dY (asociacion; no causal) | T126: output/v8/F5/atribucion_combinada.csv | U126: =IF(R126=0,"",F126/R126) | V126: =SUMIFS(F$2:F$1589,A$2:A$1589,A126,C$2:C$1589,C126,E$2:E$1589,E126,Q$2:Q$1589,Q126)
A127: alquiler | B127: nacional | C127: P3 | D127: demografia | E127: dominancia | F127: -0.219599 | I127: 0.207299 | J127: -0.30373 | K127: -0.171871 | L127: -0.326879 | M127: -0.0880957 | N127: C4 | O127: si | P127: no | Q127: interanual_ipc_ipc_alquiler | R127: -1.05934 | S127: cuota LMG x R2 x dY (asociacion; no causal) | T127: output/v8/F5/atribucion_combinada.csv | U127: =IF(R127=0,"",F127/R127) | V127: =SUMIFS(F$2:F$1589,A$2:A$1589,A127,C$2:C$1589,C127,E$2:E$1589,E127,Q$2:Q$1589,Q127)
A128: alquiler | B128: nacional | C128: P3 | D128: empleo_renta | E128: dominancia | F128: -0.0148626 | I128: 0.0140301 | J128: 0 | K128: 0 | L128: -0.00941002 | M128: 0 | N128: C4 | O128: si | P128: no | Q128: interanual_ipc_ipc_alquiler | R128: -1.05934 | S128: cuota LMG x R2 x dY (asociacion; no causal) | T128: output/v8/F5/atribucion_combinada.csv | U128: =IF(R128=0,"",F128/R128) | V128: =SUMIFS(F$2:F$1589,A$2:A$1589,A128,C$2:C$1589,C128,E$2:E$1589,E128,Q$2:Q$1589,Q128)
A129: alquiler | B129: nacional | C129: P3 | D129: credito_tipos | E129: dominancia | F129: -0.586196 | I129: 0.553362 | J129: -0.743983 | K129: -0.571653 | L129: -0.831474 | M129: -0.537774 | N129: C4 | O129: si | P129: no | Q129: interanual_ipc_ipc_alquiler | R129: -1.05934 | S129: cuota LMG x R2 x dY (asociacion; no causal) | T129: output/v8/F5/atribucion_combinada.csv | U129: =IF(R129=0,"",F129/R129) | V129: =SUMIFS(F$2:F$1589,A$2:A$1589,A129,C$2:C$1589,C129,E$2:E$1589,E129,Q$2:Q$1589,Q129)
A130: alquiler | B130: nacional | C130: P3 | D130: oferta | E130: dominancia | F130: -0.0468878 | I130: 0.0442615 | J130: -0.0486583 | K130: 0 | L130: -0.0628101 | M130: 0 | N130: C4 | O130: si | P130: no | Q130: interanual_ipc_ipc_alquiler | R130: -1.05934 | S130: cuota LMG x R2 x dY (asociacion; no causal) | T130: output/v8/F5/atribucion_combinada.csv | U130: =IF(R130=0,"",F130/R130) | V130: =SUMIFS(F$2:F$1589,A$2:A$1589,A130,C$2:C$1589,C130,E$2:E$1589,E130,Q$2:Q$1589,Q130)
A131: alquiler | B131: nacional | C131: P3 | D131: demanda_externa | E131: dominancia | F131: -0.0815521 | I131: 0.0769842 | J131: -0.137142 | K131: -0.0500349 | L131: -0.149793 | M131: -0.0177286 | N131: C4 | O131: si | P131: si | Q131: interanual_ipc_ipc_alquiler | R131: -1.05934 | S131: cuota LMG x R2 x dY (asociacion; no causal) | T131: output/v8/F5/atribucion_combinada.csv | U131: =IF(R131=0,"",F131/R131) | V131: =SUMIFS(F$2:F$1589,A$2:A$1589,A131,C$2:C$1589,C131,E$2:E$1589,E131,Q$2:Q$1589,Q131)
A132: alquiler | B132: nacional | C132: P3 | D132: factor_europeo | E132: dominancia | F132: -0.0619771 | I132: 0.0585056 | J132: -0.0903746 | K132: -0.0052684 | L132: -0.102308 | M132: 0 | N132: C4 | O132: si | P132: no | Q132: interanual_ipc_ipc_alquiler | R132: -1.05934 | S132: cuota LMG x R2 x dY (asociacion; no causal) | T132: output/v8/F5/atribucion_combinada.csv | U132: =IF(R132=0,"",F132/R132) | V132: =SUMIFS(F$2:F$1589,A$2:A$1589,A132,C$2:C$1589,C132,E$2:E$1589,E132,Q$2:Q$1589,Q132)
A133: alquiler | B133: nacional | C133: P3 | D133: residuo | E133: dominancia | F133: -0.0482601 | I133: 0.045557 | J133: -0.0887325 | K133: -0.0613609 | L133: -0.0936333 | M133: -0.0547281 | N133: C4 | O133: no | P133: no_compite | Q133: interanual_ipc_ipc_alquiler | R133: -1.05934 | S133: cuota LMG x R2 x dY (asociacion; no causal) | T133: output/v8/F5/atribucion_combinada.csv | U133: =IF(R133=0,"",F133/R133) | V133: =SUMIFS(F$2:F$1589,A$2:A$1589,A133,C$2:C$1589,C133,E$2:E$1589,E133,Q$2:Q$1589,Q133)
A134: alquiler | B134: nacional | C134: P3 | D134: turismo | E134: dominancia | N134: C4 | O134: si | P134: no | Q134: interanual_ipc_ipc_alquiler | S134: cuota LMG x R2 x dY (asociacion; no causal) | T134: output/v8/F5/atribucion_combinada.csv | U134: =IF(R134=0,"",F134/R134) | V134: =SUMIFS(F$2:F$1589,A$2:A$1589,A134,C$2:C$1589,C134,E$2:E$1589,E134,Q$2:Q$1589,Q134)
A135: alquiler | B135: nacional | C135: P4 | D135: demografia | E135: dominancia | F135: -0.485661 | I135: 0.0519808 | J135: -0.590157 | K135: 0 | L135: -0.78952 | M135: 0 | N135: C4 | O135: si | P135: no | Q135: interanual_ipc_ipc_alquiler | R135: -9.34309 | S135: cuota LMG x R2 x dY (asociacion; no causal) | T135: output/v8/F5/atribucion_combinada.csv | U135: =IF(R135=0,"",F135/R135) | V135: =SUMIFS(F$2:F$1589,A$2:A$1589,A135,C$2:C$1589,C135,E$2:E$1589,E135,Q$2:Q$1589,Q135)
A136: alquiler | B136: nacional | C136: P4 | D136: empleo_renta | E136: dominancia | F136: -2.29553 | I136: 0.245692 | J136: -3.67313 | K136: -2.13448 | L136: -4.3423 | M136: -1.27627 | N136: C4 | O136: si | P136: no | Q136: interanual_ipc_ipc_alquiler | R136: -9.34309 | S136: cuota LMG x R2 x dY (asociacion; no causal) | T136: output/v8/F5/atribucion_combinada.csv | U136: =IF(R136=0,"",F136/R136) | V136: =SUMIFS(F$2:F$1589,A$2:A$1589,A136,C$2:C$1589,C136,E$2:E$1589,E136,Q$2:Q$1589,Q136)
A137: alquiler | B137: nacional | C137: P4 | D137: credito_tipos | E137: dominancia | F137: -6.56052 | I137: 0.702178 | J137: -8.68543 | K137: -5.48755 | L137: -9.19323 | M137: -4.71527 | N137: C4 | O137: si | P137: si | Q137: interanual_ipc_ipc_alquiler | R137: -9.34309 | S137: cuota LMG x R2 x dY (asociacion; no causal) | T137: output/v8/F5/atribucion_combinada.csv | U137: =IF(R137=0,"",F137/R137) | V137: =SUMIFS(F$2:F$1589,A$2:A$1589,A137,C$2:C$1589,C137,E$2:E$1589,E137,Q$2:Q$1589,Q137)
A138: alquiler | B138: nacional | C138: P4 | D138: residuo | E138: dominancia | F138: -0.00138849 | I138: 0.000148611 | J138: -0.00270974 | K138: -0.000810101 | L138: -0.00277698 | M138: -0.000112742 | N138: C4 | O138: no | P138: no_compite | Q138: interanual_ipc_ipc_alquiler | R138: -9.34309 | S138: cuota LMG x R2 x dY (asociacion; no causal) | T138: output/v8/F5/atribucion_combinada.csv | U138: =IF(R138=0,"",F138/R138) | V138: =SUMIFS(F$2:F$1589,A$2:A$1589,A138,C$2:C$1589,C138,E$2:E$1589,E138,Q$2:Q$1589,Q138)
A139: alquiler | B139: nacional | C139: P4 | D139: factor_europeo | E139: dominancia | N139: C4 | O139: si | P139: no | Q139: interanual_ipc_ipc_alquiler | S139: cuota LMG x R2 x dY (asociacion; no causal) | T139: output/v8/F5/atribucion_combinada.csv | U139: =IF(R139=0,"",F139/R139) | V139: =SUMIFS(F$2:F$1589,A$2:A$1589,A139,C$2:C$1589,C139,E$2:E$1589,E139,Q$2:Q$1589,Q139)
A140: alquiler | B140: nacional | C140: P4 | D140: turismo | E140: dominancia | N140: C4 | O140: si | P140: no | Q140: interanual_ipc_ipc_alquiler | S140: cuota LMG x R2 x dY (asociacion; no causal) | T140: output/v8/F5/atribucion_combinada.csv | U140: =IF(R140=0,"",F140/R140) | V140: =SUMIFS(F$2:F$1589,A$2:A$1589,A140,C$2:C$1589,C140,E$2:E$1589,E140,Q$2:Q$1589,Q140)
A141: alquiler | B141: nacional | C141: P4 | D141: demanda_externa | E141: dominancia | N141: C4 | O141: si | P141: no | Q141: interanual_ipc_ipc_alquiler | S141: cuota LMG x R2 x dY (asociacion; no causal) | T141: output/v8/F5/atribucion_combinada.csv | U141: =IF(R141=0,"",F141/R141) | V141: =SUMIFS(F$2:F$1589,A$2:A$1589,A141,C$2:C$1589,C141,E$2:E$1589,E141,Q$2:Q$1589,Q141)
A142: alquiler | B142: nacional | C142: P4 | D142: oferta | E142: dominancia | N142: C4 | O142: si | P142: no | Q142: interanual_ipc_ipc_alquiler | S142: cuota LMG x R2 x dY (asociacion; no causal) | T142: output/v8/F5/atribucion_combinada.csv | U142: =IF(R142=0,"",F142/R142) | V142: =SUMIFS(F$2:F$1589,A$2:A$1589,A142,C$2:C$1589,C142,E$2:E$1589,E142,Q$2:Q$1589,Q142)
A143: alquiler | B143: nacional | C143: P5 | D143: demografia | E143: dominancia | F143: -0.0620122 | I143: 0.033599 | J143: -0.0552426 | K143: 0 | L143: -0.0690652 | M143: 0 | N143: C4 | O143: si | P143: no | Q143: interanual_ipc_ipc_alquiler | R143: -1.84566 | S143: cuota LMG x R2 x dY (asociacion; no causal) | T143: output/v8/F5/atribucion_combinada.csv | U143: =IF(R143=0,"",F143/R143) | V143: =SUMIFS(F$2:F$1589,A$2:A$1589,A143,C$2:C$1589,C143,E$2:E$1589,E143,Q$2:Q$1589,Q143)
A144: alquiler | B144: nacional | C144: P5 | D144: empleo_renta | E144: dominancia | F144: -0.339497 | I144: 0.183944 | J144: -0.599328 | K144: -0.336829 | L144: -0.619164 | M144: -0.281377 | N144: C4 | O144: si | P144: no | Q144: interanual_ipc_ipc_alquiler | R144: -1.84566 | S144: cuota LMG x R2 x dY (asociacion; no causal) | T144: output/v8/F5/atribucion_combinada.csv | U144: =IF(R144=0,"",F144/R144) | V144: =SUMIFS(F$2:F$1589,A$2:A$1589,A144,C$2:C$1589,C144,E$2:E$1589,E144,Q$2:Q$1589,Q144)
A145: alquiler | B145: nacional | C145: P5 | D145: credito_tipos | E145: dominancia | F145: -0.573819 | I145: 0.310902 | J145: -0.784641 | K145: -0.552636 | L145: -0.875364 | M145: -0.45788 | N145: C4 | O145: si | P145: si | Q145: interanual_ipc_ipc_alquiler | R145: -1.84566 | S145: cuota LMG x R2 x dY (asociacion; no causal) | T145: output/v8/F5/atribucion_combinada.csv | U145: =IF(R145=0,"",F145/R145) | V145: =SUMIFS(F$2:F$1589,A$2:A$1589,A145,C$2:C$1589,C145,E$2:E$1589,E145,Q$2:Q$1589,Q145)
A146: alquiler | B146: nacional | C146: P5 | D146: oferta | E146: dominancia | F146: -0.0320956 | I146: 0.0173898 | J146: -0.0379207 | K146: 0 | L146: -0.0437615 | M146: 0 | N146: C4 | O146: si | P146: no | Q146: interanual_ipc_ipc_alquiler | R146: -1.84566 | S146: cuota LMG x R2 x dY (asociacion; no causal) | T146: output/v8/F5/atribucion_combinada.csv | U146: =IF(R146=0,"",F146/R146) | V146: =SUMIFS(F$2:F$1589,A$2:A$1589,A146,C$2:C$1589,C146,E$2:E$1589,E146,Q$2:Q$1589,Q146)
A147: alquiler | B147: nacional | C147: P5 | D147: demanda_externa | E147: dominancia | F147: -0.107495 | I147: 0.0582421 | J147: -0.150311 | K147: -0.021635 | L147: -0.17067 | M147: 0 | N147: C4 | O147: si | P147: no | Q147: interanual_ipc_ipc_alquiler | R147: -1.84566 | S147: cuota LMG x R2 x dY (asociacion; no causal) | T147: output/v8/F5/atribucion_combinada.csv | U147: =IF(R147=0,"",F147/R147) | V147: =SUMIFS(F$2:F$1589,A$2:A$1589,A147,C$2:C$1589,C147,E$2:E$1589,E147,Q$2:Q$1589,Q147)
A148: alquiler | B148: nacional | C148: P5 | D148: turismo | E148: dominancia | F148: -0.558454 | I148: 0.302577 | J148: -0.656222 | K148: -0.529284 | L148: -0.780377 | M148: -0.467158 | N148: C4 | O148: si | P148: no | Q148: interanual_ipc_ipc_alquiler | R148: -1.84566 | S148: cuota LMG x R2 x dY (asociacion; no causal) | T148: output/v8/F5/atribucion_combinada.csv | U148: =IF(R148=0,"",F148/R148) | V148: =SUMIFS(F$2:F$1589,A$2:A$1589,A148,C$2:C$1589,C148,E$2:E$1589,E148,Q$2:Q$1589,Q148)
A149: alquiler | B149: nacional | C149: P5 | D149: factor_europeo | E149: dominancia | F149: -0.163964 | I149: 0.088838 | J149: -0.181743 | K149: 0 | L149: -0.247888 | M149: 0 | N149: C4 | O149: si | P149: no | Q149: interanual_ipc_ipc_alquiler | R149: -1.84566 | S149: cuota LMG x R2 x dY (asociacion; no causal) | T149: output/v8/F5/atribucion_combinada.csv | U149: =IF(R149=0,"",F149/R149) | V149: =SUMIFS(F$2:F$1589,A$2:A$1589,A149,C$2:C$1589,C149,E$2:E$1589,E149,Q$2:Q$1589,Q149)
...

Sheet Ranking
A1: mercado | B1: periodo | C1: factor | D1: delta_y_pp | E1: rank_svar_media | F1: media_c_signo_pp | G1: b68_lo | H1: b68_hi | I1: b90_lo | J1: b90_hi | K1: prob_mayor | L1: rank_svar_prob | M1: rango_dominancia | N1: cuota_lmg | O1: signo_parcial_dominancia | P1: rango_shap | Q1: prob_primero_shap | R1: impreciso | S1: nota | T1: fuente | U1: resultado_s9 (vínculo)
A2: compra | B2: P1 | C2: credito_tipos | D2: 75.3518 | E2: 3 | F2: 3.02994 | G2: -7.19032 | H2: 14.0114 | I2: -15.8623 | J2: 31.4975 | K2: 0.108908 | L2: 3 | M2: 1 | N2: 0.64 | O2: - | P2: 3 | Q2: 0.170854 | R2: no | S2: svar_hd: C3s condicionada a los supuestos; dominancia y SHAP: contraste C4, nunca causal. | T2: output/v8/F5/ranking.csv | U2: =Votos_s9!L2
A3: compra | B3: P1 | C3: demografia | D3: 75.3518 | E3: 2 | F3: 8.94019 | G3: -4.98915 | H3: 24.7777 | I3: -15.5745 | J3: 46.9727 | K3: 0.17454 | L3: 2 | M3: 2 | N3: 0.28 | O3: - | P3: 2 | Q3: 0.256281 | R3: no | S3: svar_hd: C3s condicionada a los supuestos; dominancia y SHAP: contraste C4, nunca causal. | T3: output/v8/F5/ranking.csv | U3: =Votos_s9!L2
A4: compra | B4: P1 | C4: empleo_renta | D4: 75.3518 | E4: 1 | F4: 31.8224 | G4: 8.99901 | H4: 54.649 | I4: -1.8311 | J4: 72.9259 | K4: 0.716553 | L4: 1 | M4: 3 | N4: 0.05 | O4: - | P4: 1 | Q4: 0.512563 | R4: no | S4: svar_hd: C3s condicionada a los supuestos; dominancia y SHAP: contraste C4, nunca causal. | T4: output/v8/F5/ranking.csv | U4: =Votos_s9!L2
A5: compra | B5: P1 | C5: oferta | D5: 75.3518 | M5: 4 | N5: 0.03 | O5: - | P5: 4 | Q5: 0 | R5: no | S5: svar_hd: C3s condicionada a los supuestos; dominancia y SHAP: contraste C4, nunca causal. | T5: output/v8/F5/ranking.csv | U5: =Votos_s9!L2
A6: compra | B6: P1 | C6: factor_europeo | D6: 75.3518 | P6: 4 | Q6: 0.0603015 | R6: no | S6: svar_hd: C3s condicionada a los supuestos; dominancia y SHAP: contraste C4, nunca causal. | T6: output/v8/F5/ranking.csv | U6: =Votos_s9!L2
A7: compra | B7: P2 | C7: credito_tipos | D7: -44.0018 | E7: 2 | F7: 8.59653 | G7: -0.542165 | H7: 18.8749 | I7: -5.23205 | J7: 32.8942 | K7: 0.225698 | L7: 2 | M7: 1 | N7: 0.38 | O7: + | P7: 5 | Q7: 0 | R7: no | S7: svar_hd: C3s condicionada a los supuestos; dominancia y SHAP: contraste C4, nunca causal. ranking incierto (P(f*) < 0,5) | T7: output/v8/F5/ranking.csv | U7: =Votos_s9!L3
A8: compra | B8: P2 | C8: demanda_vivienda | D8: -44.0018 | E8: 3 | F8: 7.40779 | G8: -1.99552 | H8: 17.8842 | I8: -6.11398 | J8: 34.0416 | K8: 0.21663 | L8: 3 | R8: no | S8: svar_hd: C3s condicionada a los supuestos; dominancia y SHAP: contraste C4, nunca causal. ranking incierto (P(f*) < 0,5) | T8: output/v8/F5/ranking.csv | U8: =Votos_s9!L3
A9: compra | B9: P2 | C9: demografia | D9: -44.0018 | E9: 5 | F9: 2.93343 | G9: -4.04962 | H9: 10.7148 | I9: -11.0989 | J9: 20.6099 | K9: 0.104884 | L9: 5 | M9: 4 | N9: 0.07 | O9: - | P9: 3 | Q9: 0.07 | R9: no | S9: svar_hd: C3s condicionada a los supuestos; dominancia y SHAP: contraste C4, nunca causal. ranking incierto (P(f*) < 0,5) | T9: output/v8/F5/ranking.csv | U9: =Votos_s9!L3
A10: compra | B10: P2 | C10: empleo_renta | D10: -44.0018 | E10: 1 | F10: 10.6353 | G10: -0.660395 | H10: 23.5243 | I10: -7.26832 | J10: 38.8394 | K10: 0.31773 | L10: 1 | M10: 3 | N10: 0.22 | O10: - | P10: 1 | Q10: 0.75 | R10: no | S10: svar_hd: C3s condicionada a los supuestos; dominancia y SHAP: contraste C4, nunca causal. ranking incierto (P(f*) < 0,5) | T10: output/v8/F5/ranking.csv | U10: =Votos_s9!L3
A11: compra | B11: P2 | C11: oferta | D11: -44.0018 | E11: 4 | F11: 4.81136 | G11: -2.48894 | H11: 13.2992 | I11: -7.58723 | J11: 25.0249 | K11: 0.135058 | L11: 4 | M11: 6 | N11: 0.01 | O11: - | P11: 4 | Q11: 0.075 | R11: no | S11: svar_hd: C3s condicionada a los supuestos; dominancia y SHAP: contraste C4, nunca causal. ranking incierto (P(f*) < 0,5) | T11: output/v8/F5/ranking.csv | U11: =Votos_s9!L3
A12: compra | B12: P2 | C12: factor_europeo | D12: -44.0018 | M12: 2 | N12: 0.25 | O12: - | P12: 3 | Q12: 0.105 | R12: no | S12: svar_hd: C3s condicionada a los supuestos; dominancia y SHAP: contraste C4, nunca causal. ranking incierto (P(f*) < 0,5) | T12: output/v8/F5/ranking.csv | U12: =Votos_s9!L3
A13: compra | B13: P2 | C13: demanda_externa | D13: -44.0018 | M13: 5 | N13: 0.07 | O13: - | R13: no | S13: svar_hd: C3s condicionada a los supuestos; dominancia y SHAP: contraste C4, nunca causal. ranking incierto (P(f*) < 0,5) | T13: output/v8/F5/ranking.csv | U13: =Votos_s9!L3
A14: compra | B14: P3 | C14: credito_tipos | D14: 8.2167 | E14: 5 | F14: -1.55002 | G14: -9.78341 | H14: 7.07096 | I14: -17.7135 | J14: 18.4172 | K14: 0.136418 | L14: 4 | M14: 5 | N14: 0.06 | O14: + | P14: 3 | Q14: 0.05 | R14: no | S14: svar_hd: C3s condicionada a los supuestos; dominancia y SHAP: contraste C4, nunca causal. ranking incierto (P(f*) < 0,5) | T14: output/v8/F5/ranking.csv | U14: =Votos_s9!L4
A15: compra | B15: P3 | C15: demanda_vivienda | D15: 8.2167 | E15: 4 | F15: -0.411954 | G15: -7.20665 | H15: 8.99381 | I15: -18.366 | J15: 17.6965 | K15: 0.170776 | L15: 2 | R15: no | S15: svar_hd: C3s condicionada a los supuestos; dominancia y SHAP: contraste C4, nunca causal. ranking incierto (P(f*) < 0,5) | T15: output/v8/F5/ranking.csv | U15: =Votos_s9!L4
A16: compra | B16: P3 | C16: demografia | D16: 8.2167 | E16: 3 | F16: 0.141604 | G16: -6.57831 | H16: 6.81486 | I16: -13.9672 | J16: 17.345 | K16: 0.136285 | L16: 5 | M16: 3 | N16: 0.24 | O16: + | P16: 4 | Q16: 0.13 | R16: no | S16: svar_hd: C3s condicionada a los supuestos; dominancia y SHAP: contraste C4, nunca causal. ranking incierto (P(f*) < 0,5) | T16: output/v8/F5/ranking.csv | U16: =Votos_s9!L4
A17: compra | B17: P3 | C17: empleo_renta | D17: 8.2167 | E17: 1 | F17: 7.72218 | G17: -3.46639 | H17: 18.2318 | I17: -15.2388 | J17: 31.2052 | K17: 0.407665 | L17: 1 | M17: 1 | N17: 0.29 | O17: + | P17: 1 | Q17: 0.68 | R17: no | S17: svar_hd: C3s condicionada a los supuestos; dominancia y SHAP: contraste C4, nunca causal. ranking incierto (P(f*) < 0,5) | T17: output/v8/F5/ranking.csv | U17: =Votos_s9!L4
A18: compra | B18: P3 | C18: oferta | D18: 8.2167 | E18: 2 | F18: 0.380583 | G18: -7.29269 | H18: 8.02427 | I18: -16.8044 | J18: 18.9594 | K18: 0.148856 | L18: 3 | M18: 6 | N18: 0.04 | O18: - | P18: 4 | Q18: 0.06 | R18: no | S18: svar_hd: C3s condicionada a los supuestos; dominancia y SHAP: contraste C4, nunca causal. ranking incierto (P(f*) < 0,5) | T18: output/v8/F5/ranking.csv | U18: =Votos_s9!L4
A19: compra | B19: P3 | C19: factor_europeo | D19: 8.2167 | M19: 2 | N19: 0.28 | O19: + | P19: 4 | Q19: 0.08 | R19: no | S19: svar_hd: C3s condicionada a los supuestos; dominancia y SHAP: contraste C4, nunca causal. ranking incierto (P(f*) < 0,5) | T19: output/v8/F5/ranking.csv | U19: =Votos_s9!L4
A20: compra | B20: P3 | C20: demanda_externa | D20: 8.2167 | M20: 4 | N20: 0.09 | O20: + | R20: no | S20: svar_hd: C3s condicionada a los supuestos; dominancia y SHAP: contraste C4, nunca causal. ranking incierto (P(f*) < 0,5) | T20: output/v8/F5/ranking.csv | U20: =Votos_s9!L4
A21: compra | B21: P4 | C21: credito_tipos | D21: -5.45682 | E21: 2 | F21: 1.29208 | G21: -4.43588 | H21: 4.72305 | I21: -9.20296 | J21: 10.0285 | K21: 0.169313 | L21: 4 | M21: 1 | N21: 0.59 | O21: - | P21: 4 | Q21: 0 | R21: sí | S21: svar_hd: C3s condicionada a los supuestos; dominancia y SHAP: contraste C4, nunca causal. ranking incierto (media y P(f*) discrepan); ranking incierto (P(f*) < 0,5) | T21: output/v8/F5/ranking.csv | U21: =Votos_s9!L5
A22: compra | B22: P4 | C22: demanda_vivienda | D22: -5.45682 | E22: 1 | F22: 2.61446 | G22: -2.42139 | H22: 6.00271 | I22: -6.04984 | J22: 12.3484 | K22: 0.238417 | L22: 2 | R22: sí | S22: svar_hd: C3s condicionada a los supuestos; dominancia y SHAP: contraste C4, nunca causal. ranking incierto (media y P(f*) discrepan); ranking incierto (P(f*) < 0,5) | T22: output/v8/F5/ranking.csv | U22: =Votos_s9!L5
A23: compra | B23: P4 | C23: demografia | D23: -5.45682 | E23: 4 | F23: 0.273356 | G23: -3.3891 | H23: 3.99072 | I23: -7.06439 | J23: 8.2383 | K23: 0.148217 | L23: 5 | M23: 2 | N23: 0.29 | O23: - | P23: 3 | Q23: 0.14359 | R23: sí | S23: svar_hd: C3s condicionada a los supuestos; dominancia y SHAP: contraste C4, nunca causal. ranking incierto (media y P(f*) discrepan); ranking incierto (P(f*) < 0,5) | T23: output/v8/F5/ranking.csv | U23: =Votos_s9!L5
A24: compra | B24: P4 | C24: empleo_renta | D24: -5.45682 | E24: 5 | F24: -0.27266 | G24: -4.66018 | H24: 7.08693 | I24: -10.1891 | J24: 13.2385 | K24: 0.259322 | L24: 1 | M24: 3 | N24: 0.12 | O24: - | P24: 1 | Q24: 0.728205 | R24: sí | S24: svar_hd: C3s condicionada a los supuestos; dominancia y SHAP: contraste C4, nunca causal. ranking incierto (media y P(f*) discrepan); ranking incierto (P(f*) < 0,5) | T24: output/v8/F5/ranking.csv | U24: =Votos_s9!L5
A25: compra | B25: P4 | C25: oferta | D25: -5.45682 | E25: 3 | F25: 0.797043 | G25: -3.31995 | H25: 4.7538 | I25: -7.51088 | J25: 9.99627 | K25: 0.184732 | L25: 3 | P25: 4 | Q25: 0.0102564 | R25: sí | S25: svar_hd: C3s condicionada a los supuestos; dominancia y SHAP: contraste C4, nunca causal. ranking incierto (media y P(f*) discrepan); ranking incierto (P(f*) < 0,5) | T25: output/v8/F5/ranking.csv | U25: =Votos_s9!L5
A26: compra | B26: P4 | C26: factor_europeo | D26: -5.45682 | P26: 3 | Q26: 0.117949 | R26: sí | S26: svar_hd: C3s condicionada a los supuestos; dominancia y SHAP: contraste C4, nunca causal. ranking incierto (media y P(f*) discrepan); ranking incierto (P(f*) < 0,5) | T26: output/v8/F5/ranking.csv | U26: =Votos_s9!L5
A27: compra | B27: P5 | C27: credito_tipos | D27: 18.4203 | E27: 5 | F27: -0.469355 | G27: -2.81899 | H27: 12.7731 | I27: -9.8517 | J27: 20.6693 | K27: 0.296623 | L27: 1 | M27: 4 | N27: 0.11 | O27: + | P27: 4 | Q27: 0.0358974 | R27: no | S27: svar_hd: C3s condicionada a los supuestos; dominancia y SHAP: contraste C4, nunca causal. ranking incierto (media y P(f*) discrepan); ranking incierto (P(f*) < 0,5) | T27: output/v8/F5/ranking.csv | U27: =Votos_s9!L6
A28: compra | B28: P5 | C28: demanda_vivienda | D28: 18.4203 | E28: 4 | F28: -0.30196 | G28: -2.86541 | H28: 10.9817 | I28: -10.7762 | J28: 19.5331 | K28: 0.231689 | L28: 2 | R28: no | S28: svar_hd: C3s condicionada a los supuestos; dominancia y SHAP: contraste C4, nunca causal. ranking incierto (media y P(f*) discrepan); ranking incierto (P(f*) < 0,5) | T28: output/v8/F5/ranking.csv | U28: =Votos_s9!L6
A29: compra | B29: P5 | C29: demografia | D29: 18.4203 | E29: 3 | F29: 0.647324 | G29: -4.07861 | H29: 5.79265 | I29: -9.01505 | J29: 13.4324 | K29: 0.0989587 | L29: 5 | M29: 5 | N29: 0.08 | O29: + | P29: 3 | Q29: 0.0923077 | R29: no | S29: svar_hd: C3s condicionada a los supuestos; dominancia y SHAP: contraste C4, nunca causal. ranking incierto (media y P(f*) discrepan); ranking incierto (P(f*) < 0,5) | T29: output/v8/F5/ranking.csv | U29: =Votos_s9!L6
A30: compra | B30: P5 | C30: empleo_renta | D30: 18.4203 | E30: 1 | F30: 7.15724 | G30: -4.70611 | H30: 11.1947 | I30: -10.7761 | J30: 22.7129 | K30: 0.203338 | L30: 3 | M30: 3 | N30: 0.13 | O30: - | P30: 1 | Q30: 0.805128 | R30: no | S30: svar_hd: C3s condicionada a los supuestos; dominancia y SHAP: contraste C4, nunca causal. ranking incierto (media y P(f*) discrepan); ranking incierto (P(f*) < 0,5) | T30: output/v8/F5/ranking.csv | U30: =Votos_s9!L6
A31: compra | B31: P5 | C31: oferta | D31: 18.4203 | E31: 2 | F31: 1.87093 | G31: -3.25013 | H31: 9.02896 | I31: -10.0527 | J31: 16.9023 | K31: 0.16939 | L31: 4 | M31: 7 | N31: 0 | O31: - | P31: 4 | Q31: 0.00512821 | R31: no | S31: svar_hd: C3s condicionada a los supuestos; dominancia y SHAP: contraste C4, nunca causal. ranking incierto (media y P(f*) discrepan); ranking incierto (P(f*) < 0,5) | T31: output/v8/F5/ranking.csv | U31: =Votos_s9!L6
A32: compra | B32: P5 | C32: factor_europeo | D32: 18.4203 | M32: 1 | N32: 0.32 | O32: - | P32: 3 | Q32: 0.0615385 | R32: no | S32: svar_hd: C3s condicionada a los supuestos; dominancia y SHAP: contraste C4, nunca causal. ranking incierto (media y P(f*) discrepan); ranking incierto (P(f*) < 0,5) | T32: output/v8/F5/ranking.csv | U32: =Votos_s9!L6
A33: compra | B33: P5 | C33: turismo | D33: 18.4203 | M33: 2 | N33: 0.29 | O33: - | R33: no | S33: svar_hd: C3s condicionada a los supuestos; dominancia y SHAP: contraste C4, nunca causal. ranking incierto (media y P(f*) discrepan); ranking incierto (P(f*) < 0,5) | T33: output/v8/F5/ranking.csv | U33: =Votos_s9!L6
A34: compra | B34: P5 | C34: demanda_externa | D34: 18.4203 | M34: 6 | N34: 0.06 | O34: - | R34: no | S34: svar_hd: C3s condicionada a los supuestos; dominancia y SHAP: contraste C4, nunca causal. ranking incierto (media y P(f*) discrepan); ranking incierto (P(f*) < 0,5) | T34: output/v8/F5/ranking.csv | U34: =Votos_s9!L6
A35: alquiler | B35: P1 | C35: credito_tipos | D35: 4.92545 | M35: 1 | N35: 0.68 | O35: - | P35: 2 | Q35: 0.296482 | R35: sí | S35: svar_hd: C3s condicionada a los supuestos; dominancia y SHAP: contraste C4, nunca causal. Sin svar_hd en esta celda: solo contraste. | T35: output/v8/F5/ranking.csv | U35: =Votos_s9!L7
A36: alquiler | B36: P1 | C36: factor_europeo | D36: 4.92545 | M36: 2 | N36: 0.14 | O36: + | P36: 5 | Q36: 0.0251256 | R36: sí | S36: svar_hd: C3s condicionada a los supuestos; dominancia y SHAP: contraste C4, nunca causal. Sin svar_hd en esta celda: solo contraste. | T36: output/v8/F5/ranking.csv | U36: =Votos_s9!L7
A37: alquiler | B37: P1 | C37: empleo_renta | D37: 4.92545 | M37: 3 | N37: 0.07 | O37: - | P37: 2 | Q37: 0.231156 | R37: sí | S37: svar_hd: C3s condicionada a los supuestos; dominancia y SHAP: contraste C4, nunca causal. Sin svar_hd en esta celda: solo contraste. | T37: output/v8/F5/ranking.csv | U37: =Votos_s9!L7
A38: alquiler | B38: P1 | C38: oferta | D38: 4.92545 | M38: 4 | N38: 0.06 | O38: - | P38: 4 | Q38: 0.0100503 | R38: sí | S38: svar_hd: C3s condicionada a los supuestos; dominancia y SHAP: contraste C4, nunca causal. Sin svar_hd en esta celda: solo contraste. | T38: output/v8/F5/ranking.csv | U38: =Votos_s9!L7
A39: alquiler | B39: P1 | C39: demografia | D39: 4.92545 | M39: 5 | N39: 0.05 | O39: - | P39: 2 | Q39: 0.437186 | R39: sí | S39: svar_hd: C3s condicionada a los supuestos; dominancia y SHAP: contraste C4, nunca causal. Sin svar_hd en esta celda: solo contraste. | T39: output/v8/F5/ranking.csv | U39: =Votos_s9!L7
A40: alquiler | B40: P2 | C40: credito_tipos | D40: -2.70287 | E40: 4 | F40: -0.256492 | G40: -2.13438 | H40: 1.46143 | I40: -3.60475 | J40: 3.27061 | K40: 0.111814 | L40: 5 | M40: 1 | N40: 0.47 | O40: + | P40: 3 | Q40: 0.045 | R40: no | S40: svar_hd: C3s condicionada a los supuestos; dominancia y SHAP: contraste C4, nunca causal. ranking incierto (P(f*) < 0,5) | T40: output/v8/F5/ranking.csv | U40: =Votos_s9!L8
A41: alquiler | B41: P2 | C41: demanda_vivienda | D41: -2.70287 | E41: 2 | F41: 0.322677 | G41: -1.84846 | H41: 2.31858 | I41: -3.32224 | J41: 5.04512 | K41: 0.175156 | L41: 3 | R41: no | S41: svar_hd: C3s condicionada a los supuestos; dominancia y SHAP: contraste C4, nunca causal. ranking incierto (P(f*) < 0,5) | T41: output/v8/F5/ranking.csv | U41: =Votos_s9!L8
A42: alquiler | B42: P2 | C42: demografia | D42: -2.70287 | E42: 5 | F42: -0.32773 | G42: -2.70734 | H42: 1.85844 | I42: -4.85592 | J42: 4.60495 | K42: 0.143583 | L42: 4 | M42: 2 | N42: 0.27 | O42: + | P42: 2 | Q42: 0.405 | R42: no | S42: svar_hd: C3s condicionada a los supuestos; dominancia y SHAP: contraste C4, nunca causal. ranking incierto (P(f*) < 0,5) | T42: output/v8/F5/ranking.csv | U42: =Votos_s9!L8
A43: alquiler | B43: P2 | C43: empleo_renta | D43: -2.70287 | E43: 1 | F43: 1.66423 | G43: -0.828869 | H43: 4.2967 | I43: -2.67143 | J43: 6.87178 | K43: 0.388093 | L43: 1 | M43: 4 | N43: 0.1 | O43: - | P43: 1 | Q43: 0.535 | R43: no | S43: svar_hd: C3s condicionada a los supuestos; dominancia y SHAP: contraste C4, nunca causal. ranking incierto (P(f*) < 0,5) | T43: output/v8/F5/ranking.csv | U43: =Votos_s9!L8
A44: alquiler | B44: P2 | C44: oferta | D44: -2.70287 | E44: 3 | F44: 0.0582198 | G44: -1.91331 | H44: 1.96612 | I44: -3.66702 | J44: 3.92079 | K44: 0.181355 | L44: 2 | M44: 6 | N44: 0.02 | O44: + | P44: 4 | Q44: 0 | R44: no | S44: svar_hd: C3s condicionada a los supuestos; dominancia y SHAP: contraste C4, nunca causal. ranking incierto (P(f*) < 0,5) | T44: output/v8/F5/ranking.csv | U44: =Votos_s9!L8
A45: alquiler | B45: P2 | C45: demanda_externa | D45: -2.70287 | M45: 3 | N45: 0.1 | O45: + | R45: no | S45: svar_hd: C3s condicionada a los supuestos; dominancia y SHAP: contraste C4, nunca causal. ranking incierto (P(f*) < 0,5) | T45: output/v8/F5/ranking.csv | U45: =Votos_s9!L8
A46: alquiler | B46: P2 | C46: factor_europeo | D46: -2.70287 | M46: 5 | N46: 0.03 | O46: - | P46: 5 | Q46: 0.015 | R46: no | S46: svar_hd: C3s condicionada a los supuestos; dominancia y SHAP: contraste C4, nunca causal. ranking incierto (P(f*) < 0,5) | T46: output/v8/F5/ranking.csv | U46: =Votos_s9!L8
A47: alquiler | B47: P3 | C47: credito_tipos | D47: -1.05934 | E47: 2 | F47: -0.236546 | G47: -2.67511 | H47: 1.73676 | I47: -4.76226 | J47: 3.61419 | K47: 0.220116 | L47: 2 | M47: 1 | N47: 0.58 | O47: + | P47: 4 | Q47: 0.05 | R47: no | S47: svar_hd: C3s condicionada a los supuestos; dominancia y SHAP: contraste C4, nunca causal. ranking incierto (P(f*) < 0,5) | T47: output/v8/F5/ranking.csv | U47: =Votos_s9!L9
A48: alquiler | B48: P3 | C48: demanda_vivienda | D48: -1.05934 | E48: 3 | F48: -0.664649 | G48: -2.90177 | H48: 1.35807 | I48: -5.4391 | J48: 3.28344 | K48: 0.150141 | L48: 4 | R48: no | S48: svar_hd: C3s condicionada a los supuestos; dominancia y SHAP: contraste C4, nunca causal. ranking incierto (P(f*) < 0,5) | T48: output/v8/F5/ranking.csv | U48: =Votos_s9!L9
A49: alquiler | B49: P3 | C49: demografia | D49: -1.05934 | E49: 1 | F49: 0.00369706 | G49: -2.7423 | H49: 2.94812 | I49: -5.4995 | J49: 5.51631 | K49: 0.325824 | L49: 1 | M49: 2 | N49: 0.22 | O49: + | P49: 2 | Q49: 0.27 | R49: no | S49: svar_hd: C3s condicionada a los supuestos; dominancia y SHAP: contraste C4, nunca causal. ranking incierto (P(f*) < 0,5) | T49: output/v8/F5/ranking.csv | U49: =Votos_s9!L9
A50: alquiler | B50: P3 | C50: empleo_renta | D50: -1.05934 | E50: 5 | F50: -1.73311 | G50: -4.79832 | H50: 1.12179 | I50: -8.00786 | J50: 3.59785 | K50: 0.147358 | L50: 5 | M50: 6 | N50: 0.01 | O50: + | P50: 1 | Q50: 0.65 | R50: no | S50: svar_hd: C3s condicionada a los supuestos; dominancia y SHAP: contraste C4, nunca causal. ranking incierto (P(f*) < 0,5) | T50: output/v8/F5/ranking.csv | U50: =Votos_s9!L9
A51: alquiler | B51: P3 | C51: oferta | D51: -1.05934 | E51: 4 | F51: -0.871418 | G51: -3.22046 | H51: 1.08042 | I51: -5.95354 | J51: 2.77199 | K51: 0.156562 | L51: 3 | M51: 5 | N51: 0.05 | O51: + | P51: 3 | Q51: 0.015 | R51: no | S51: svar_hd: C3s condicionada a los supuestos; dominancia y SHAP: contraste C4, nunca causal. ranking incierto (P(f*) < 0,5) | T51: output/v8/F5/ranking.csv | U51: =Votos_s9!L9
A52: alquiler | B52: P3 | C52: demanda_externa | D52: -1.05934 | M52: 3 | N52: 0.08 | O52: - | R52: no | S52: svar_hd: C3s condicionada a los supuestos; dominancia y SHAP: contraste C4, nunca causal. ranking incierto (P(f*) < 0,5) | T52: output/v8/F5/ranking.csv | U52: =Votos_s9!L9
A53: alquiler | B53: P3 | C53: factor_europeo | D53: -1.05934 | M53: 4 | N53: 0.06 | O53: + | P53: 5 | Q53: 0.015 | R53: no | S53: svar_hd: C3s condicionada a los supuestos; dominancia y SHAP: contraste C4, nunca causal. ranking incierto (P(f*) < 0,5) | T53: output/v8/F5/ranking.csv | U53: =Votos_s9!L9
A54: alquiler | B54: P4 | C54: credito_tipos | D54: -9.34309 | E54: 3 | F54: 1.45148 | G54: -0.304975 | H54: 3.18121 | I54: -1.07221 | J54: 5.16332 | K54: 0.230159 | L54: 2 | M54: 1 | N54: 0.7 | O54: - | P54: 4 | Q54: 0.0205128 | R54: sí | S54: svar_hd: C3s condicionada a los supuestos; dominancia y SHAP: contraste C4, nunca causal. ranking incierto (media y P(f*) discrepan); ranking incierto (P(f*) < 0,5) | T54: output/v8/F5/ranking.csv | U54: =Votos_s9!L10
A55: alquiler | B55: P4 | C55: demanda_vivienda | D55: -9.34309 | E55: 2 | F55: 1.57472 | G55: -0.12356 | H55: 3.24114 | I55: -0.860196 | J55: 5.10846 | K55: 0.244831 | L55: 1 | R55: sí | S55: svar_hd: C3s condicionada a los supuestos; dominancia y SHAP: contraste C4, nunca causal. ranking incierto (media y P(f*) discrepan); ranking incierto (P(f*) < 0,5) | T55: output/v8/F5/ranking.csv | U55: =Votos_s9!L10
A56: alquiler | B56: P4 | C56: demografia | D56: -9.34309 | E56: 5 | F56: 0.737454 | G56: -0.653901 | H56: 2.32453 | I56: -1.86846 | J56: 4.1289 | K56: 0.128168 | L56: 5 | M56: 3 | N56: 0.05 | O56: + | P56: 2 | Q56: 0.215385 | R56: sí | S56: svar_hd: C3s condicionada a los supuestos; dominancia y SHAP: contraste C4, nunca causal. ranking incierto (media y P(f*) discrepan); ranking incierto (P(f*) < 0,5) | T56: output/v8/F5/ranking.csv | U56: =Votos_s9!L10
A57: alquiler | B57: P4 | C57: empleo_renta | D57: -9.34309 | E57: 4 | F57: 0.810733 | G57: -0.641337 | H57: 2.83154 | I57: -1.61318 | J57: 4.24928 | K57: 0.170004 | L57: 4 | M57: 2 | N57: 0.25 | O57: - | P57: 1 | Q57: 0.702564 | R57: sí | S57: svar_hd: C3s condicionada a los supuestos; dominancia y SHAP: contraste C4, nunca causal. ranking incierto (media y P(f*) discrepan); ranking incierto (P(f*) < 0,5) | T57: output/v8/F5/ranking.csv | U57: =Votos_s9!L10
A58: alquiler | B58: P4 | C58: oferta | D58: -9.34309 | E58: 1 | F58: 1.60744 | G58: -0.103771 | H58: 3.57098 | I58: -0.798864 | J58: 5.25663 | K58: 0.226838 | L58: 3 | P58: 3 | Q58: 0.0410256 | R58: sí | S58: svar_hd: C3s condicionada a los supuestos; dominancia y SHAP: contraste C4, nunca causal. ranking incierto (media y P(f*) discrepan); ranking incierto (P(f*) < 0,5) | T58: output/v8/F5/ranking.csv | U58: =Votos_s9!L10
A59: alquiler | B59: P4 | C59: factor_europeo | D59: -9.34309 | P59: 5 | Q59: 0.0205128 | R59: sí | S59: svar_hd: C3s condicionada a los supuestos; dominancia y SHAP: contraste C4, nunca causal. ranking incierto (media y P(f*) discrepan); ranking incierto (P(f*) < 0,5) | T59: output/v8/F5/ranking.csv | U59: =Votos_s9!L10
A60: alquiler | B60: P5 | C60: credito_tipos | D60: -1.84566 | E60: 1 | F60: 0.501669 | G60: -2.34347 | H60: 2.57326 | I60: -4.27741 | J60: 4.33116 | K60: 0.257239 | L60: 1 | M60: 1 | N60: 0.31 | O60: - | P60: 2 | Q60: 0.192893 | R60: no | S60: svar_hd: C3s condicionada a los supuestos; dominancia y SHAP: contraste C4, nunca causal. ranking incierto (P(f*) < 0,5) | T60: output/v8/F5/ranking.csv | U60: =Votos_s9!L11
A61: alquiler | B61: P5 | C61: demanda_vivienda | D61: -1.84566 | E61: 2 | F61: 0.298746 | G61: -1.99287 | H61: 2.01307 | I61: -4.10841 | J61: 4.28596 | K61: 0.21712 | L61: 2 | R61: no | S61: svar_hd: C3s condicionada a los supuestos; dominancia y SHAP: contraste C4, nunca causal. ranking incierto (P(f*) < 0,5) | T61: output/v8/F5/ranking.csv | U61: =Votos_s9!L11
A62: alquiler | B62: P5 | C62: demografia | D62: -1.84566 | E62: 3 | F62: -0.0739278 | G62: -2.13245 | H62: 1.91917 | I62: -4.10015 | J62: 3.73809 | K62: 0.174054 | L62: 4 | M62: 6 | N62: 0.03 | O62: + | P62: 4 | Q62: 0.0609137 | R62: no | S62: svar_hd: C3s condicionada a los supuestos; dominancia y SHAP: contraste C4, nunca causal. ranking incierto (P(f*) < 0,5) | T62: output/v8/F5/ranking.csv | U62: =Votos_s9!L11
A63: alquiler | B63: P5 | C63: empleo_renta | D63: -1.84566 | E63: 5 | F63: -0.471616 | G63: -2.10312 | H63: 1.87245 | I63: -3.90377 | J63: 3.41242 | K63: 0.179128 | L63: 3 | M63: 3 | N63: 0.18 | O63: - | P63: 1 | Q63: 0.685279 | R63: no | S63: svar_hd: C3s condicionada a los supuestos; dominancia y SHAP: contraste C4, nunca causal. ranking incierto (P(f*) < 0,5) | T63: output/v8/F5/ranking.csv | U63: =Votos_s9!L11
A64: alquiler | B64: P5 | C64: oferta | D64: -1.84566 | E64: 4 | F64: -0.365414 | G64: -2.59775 | H64: 1.75133 | I64: -4.56606 | J64: 3.38467 | K64: 0.172459 | L64: 5 | M64: 7 | N64: 0.02 | O64: + | P64: 3 | Q64: 0.0304569 | R64: no | S64: svar_hd: C3s condicionada a los supuestos; dominancia y SHAP: contraste C4, nunca causal. ranking incierto (P(f*) < 0,5) | T64: output/v8/F5/ranking.csv | U64: =Votos_s9!L11
A65: alquiler | B65: P5 | C65: turismo | D65: -1.84566 | M65: 2 | N65: 0.3 | O65: - | R65: no | S65: svar_hd: C3s condicionada a los supuestos; dominancia y SHAP: contraste C4, nunca causal. ranking incierto (P(f*) < 0,5) | T65: output/v8/F5/ranking.csv | U65: =Votos_s9!L11
A66: alquiler | B66: P5 | C66: factor_europeo | D66: -1.84566 | M66: 4 | N66: 0.09 | O66: - | P66: 5 | Q66: 0.0304569 | R66: no | S66: svar_hd: C3s condicionada a los supuestos; dominancia y SHAP: contraste C4, nunca causal. ranking incierto (P(f*) < 0,5) | T66: output/v8/F5/ranking.csv | U66: =Votos_s9!L11
A67: alquiler | B67: P5 | C67: demanda_externa | D67: -1.84566 | M67: 5 | N67: 0.06 | O67: - | R67: no | S67: svar_hd: C3s condicionada a los supuestos; dominancia y SHAP: contraste C4, nunca causal. ranking incierto (P(f*) < 0,5) | T67: output/v8/F5/ranking.csv | U67: =Votos_s9!L11

Sheet Fuera_muestra
A1: mercado | B1: modelo | C1: tipo | D1: rmse_pp | E1: n_test | F1: evaluable | G1: mejor_que_exigente | H1: p_holm_vs_ar4 | I1: p_holm_vs_exigente | J1: fuente | K1: ratio_rmse_vs_ar4_calc
A2: compra | B2: ar4 | C2: base | D2: 1.17566 | E2: 40 | F2: si | G2: no | J2: output/v8/F5/fuera_muestra_comun.csv | K2: =D2/D2
A3: compra | B3: ecm_v1 | C3: base | D3: 2.61697 | E3: 40 | F3: si | G3: no | H3: 0.0123343 | I3: 0.0123343 | J3: output/v8/F5/fuera_muestra_comun.csv | K3: =D3/D2
A4: compra | B4: ar_fc | C4: base | D4: 1.27348 | E4: 40 | F4: si | G4: no | H4: 0.131506 | I4: 0.131506 | J4: output/v8/F5/fuera_muestra_comun.csv | K4: =D4/D2
A5: compra | B5: bvar_m2 | C5: candidato | D5: 1.37361 | E5: 40 | F5: si | G5: no | H5: 0.131506 | I5: 0.131506 | J5: output/v8/F5/fuera_muestra_comun.csv | K5: =D5/D2
A6: alquiler | B6: ar4 | C6: base | D6: 0.803395 | E6: 40 | F6: si | G6: no | J6: output/v8/F5/fuera_muestra_comun.csv | K6: =D6/D6
A7: alquiler | B7: ecm_v1 | C7: base | D7: 1.69155 | E7: 40 | F7: si | G7: no | H7: 0.000450274 | I7: 0.000450274 | J7: output/v8/F5/fuera_muestra_comun.csv | K7: =D7/D6
A8: alquiler | B8: ar_fc | C8: base | D8: 0.831795 | E8: 40 | F8: si | G8: no | H8: 0.595535 | I8: 0.595535 | J8: output/v8/F5/fuera_muestra_comun.csv | K8: =D8/D6
A9: alquiler | B9: bvar_m2 | C9: candidato | D9: 0.975851 | E9: 40 | F9: si | G9: no | H9: 0.126603 | I9: 0.126603 | J9: output/v8/F5/fuera_muestra_comun.csv | K9: =D9/D6
A12: Error fuera de muestra por módulo (bloques con embargo; muestras propias de cada módulo)
A13: modulo | B13: mercado | C13: ambito | D13: muestra | E13: modelo | F13: rmse | G13: rmse_ar4 | H13: p_dm_vs_ar4 | I13: metodo_p | J13: fuente | K13: ratio_rmse_vs_ar4_calc
A14: M0 | B14: compra | C14: nacional | D14: 1998Q3..2026Q2 | E14: AR4 | F14: 1.2164359 | G14: 1.2164359 | I14: sin ajustar (DM-HLN) | J14: output/v8/M0/resultado.json | K14: =F14/G14
A15: M0 | B15: compra | C15: nacional | D15: 1998Q3..2026Q2 | E15: AR4+X_comun | F15: 1.4864845 | G15: 1.2164359 | H15: 6.7981654e-05 | I15: sin ajustar (DM-HLN) | J15: output/v8/M0/resultado.json | K15: =F15/G15
A16: M0 | B16: compra | C16: nacional | D16: 1998Q3..2026Q2 | E16: AR1+X_por_periodo | F16: 1.8024443 | G16: 1.2164359 | H16: 8.5367848e-07 | I16: sin ajustar (DM-HLN) | J16: output/v8/M0/resultado.json | K16: =F16/G16
A17: M0 | B17: alquiler | C17: nacional | D17: 2004Q1..2026Q2 | E17: AR4 | F17: 0.80000512 | G17: 0.80000512 | I17: sin ajustar (DM-HLN) | J17: output/v8/M0/resultado.json | K17: =F17/G17
A18: M0 | B18: alquiler | C18: nacional | D18: 2004Q1..2026Q2 | E18: AR4+X_comun | F18: 1.7624595 | G18: 0.80000512 | H18: 0.00036050538 | I18: sin ajustar (DM-HLN) | J18: output/v8/M0/resultado.json | K18: =F18/G18
A19: M0 | B19: alquiler | C19: nacional | D19: 2004Q1..2026Q2 | E19: AR1+X_por_periodo | F19: 1.8146096 | G19: 0.80000512 | H19: 7.2984545e-05 | I19: sin ajustar (DM-HLN) | J19: output/v8/M0/resultado.json | K19: =F19/G19
A20: M4 | B20: compra | C20: nacional | D20: 1998Q1..2026Q2 (n=113) | E20: C1_sin_rupturas_AR4 | F20: 1.2826573 | G20: 1.2826573 | I20: BH (DM-HLN) | J20: output/v8/M4/fuera_muestra.csv | K20: =F20/G20
A21: M4 | B21: compra | C21: nacional | D21: 1998Q1..2026Q2 (n=113) | E21: C1_sin_rupturas_SR | F21: 1.6941077 | G21: 1.2826573 | H21: 0.26361275 | I21: BH (DM-HLN) | J21: output/v8/M4/fuera_muestra.csv | K21: =F21/G21
A22: M4 | B22: compra | C22: nacional | D22: 1998Q1..2026Q2 (n=113) | E22: C1_sin_rupturas_ECM | F22: 1.4069017 | G22: 1.2826573 | H22: 0.31298708 | I22: BH (DM-HLN) | J22: output/v8/M4/fuera_muestra.csv | K22: =F22/G22
A23: M4 | B23: compra | C23: nacional | D23: 1998Q1..2026Q2 (n=113) | E23: C2_sin_rupturas_AR4 | F23: 1.2826573 | G23: 1.2826573 | I23: BH (DM-HLN) | J23: output/v8/M4/fuera_muestra.csv | K23: =F23/G23
A24: M4 | B24: compra | C24: nacional | D24: 1998Q1..2026Q2 (n=113) | E24: C2_sin_rupturas_SR | F24: 1.4558706 | G24: 1.2826573 | H24: 0.087080613 | I24: BH (DM-HLN) | J24: output/v8/M4/fuera_muestra.csv | K24: =F24/G24
A25: M4 | B25: compra | C25: nacional | D25: 1998Q1..2026Q2 (n=113) | E25: C2_sin_rupturas_ECM | F25: 1.4086766 | G25: 1.2826573 | H25: 0.31298708 | I25: BH (DM-HLN) | J25: output/v8/M4/fuera_muestra.csv | K25: =F25/G25
A26: M4 | B26: compra | C26: nacional | D26: 1998Q1..2026Q2 (n=113) | E26: C3_sin_rupturas_AR4 | F26: 1.2826573 | G26: 1.2826573 | I26: BH (DM-HLN) | J26: output/v8/M4/fuera_muestra.csv | K26: =F26/G26
A27: M4 | B27: compra | C27: nacional | D27: 1998Q1..2026Q2 (n=113) | E27: C3_sin_rupturas_SR | F27: 1.5366549 | G27: 1.2826573 | H27: 0.0016708244 | I27: BH (DM-HLN) | J27: output/v8/M4/fuera_muestra.csv | K27: =F27/G27
A28: M4 | B28: compra | C28: nacional | D28: 1998Q1..2026Q2 (n=113) | E28: C3_sin_rupturas_ECM | F28: 1.5361928 | G28: 1.2826573 | H28: 0.0039178249 | I28: BH (DM-HLN) | J28: output/v8/M4/fuera_muestra.csv | K28: =F28/G28
A29: M4 | B29: compra | C29: nacional | D29: 1998Q1..2026Q2 (n=113) | E29: C4_sin_rupturas_AR4 | F29: 1.2826573 | G29: 1.2826573 | I29: BH (DM-HLN) | J29: output/v8/M4/fuera_muestra.csv | K29: =F29/G29
A30: M4 | B30: compra | C30: nacional | D30: 1998Q1..2026Q2 (n=113) | E30: C4_sin_rupturas_SR | F30: 1.5272327 | G30: 1.2826573 | H30: 0.0015131711 | I30: BH (DM-HLN) | J30: output/v8/M4/fuera_muestra.csv | K30: =F30/G30
A31: M4 | B31: compra | C31: nacional | D31: 1998Q1..2026Q2 (n=113) | E31: C4_sin_rupturas_ECM | F31: 2.6524368 | G31: 1.2826573 | H31: 0.0022417888 | I31: BH (DM-HLN) | J31: output/v8/M4/fuera_muestra.csv | K31: =F31/G31
A32: M4 | B32: alquiler | C32: nacional | D32: 2003Q2..2026Q2 (n=92) | E32: A1_sin_rupturas_AR4 | F32: 0.72552349 | G32: 0.72552349 | I32: BH (DM-HLN) | J32: output/v8/M4/fuera_muestra.csv | K32: =F32/G32
A33: M4 | B33: alquiler | C33: nacional | D33: 2003Q2..2026Q2 (n=92) | E33: A1_sin_rupturas_SR | F33: 0.72226349 | G33: 0.72552349 | H33: 0.99059547 | I33: BH (DM-HLN) | J33: output/v8/M4/fuera_muestra.csv | K33: =F33/G33
A34: M4 | B34: alquiler | C34: nacional | D34: 2003Q2..2026Q2 (n=92) | E34: A1_sin_rupturas_ECM | F34: 0.74958367 | G34: 0.72552349 | H34: 0.33482272 | I34: BH (DM-HLN) | J34: output/v8/M4/fuera_muestra.csv | K34: =F34/G34
A35: M4 | B35: alquiler | C35: nacional | D35: 2003Q2..2026Q2 (n=92) | E35: A2_sin_rupturas_AR4 | F35: 0.72552349 | G35: 0.72552349 | I35: BH (DM-HLN) | J35: output/v8/M4/fuera_muestra.csv | K35: =F35/G35
A36: M4 | B36: alquiler | C36: nacional | D36: 2003Q2..2026Q2 (n=92) | E36: A2_sin_rupturas_SR | F36: 0.70504173 | G36: 0.72552349 | H36: 0.77499326 | I36: BH (DM-HLN) | J36: output/v8/M4/fuera_muestra.csv | K36: =F36/G36
A37: M4 | B37: alquiler | C37: nacional | D37: 2003Q2..2026Q2 (n=92) | E37: A2_sin_rupturas_ECM | F37: 2.4625244 | G37: 0.72552349 | H37: 0.00037780397 | I37: BH (DM-HLN) | J37: output/v8/M4/fuera_muestra.csv | K37: =F37/G37
A38: M4 | B38: alquiler | C38: nacional | D38: 2003Q2..2026Q2 (n=92) | E38: A2b_sin_rupturas_AR4 | F38: 0.72552349 | G38: 0.72552349 | I38: BH (DM-HLN) | J38: output/v8/M4/fuera_muestra.csv | K38: =F38/G38
A39: M4 | B39: alquiler | C39: nacional | D39: 2003Q2..2026Q2 (n=92) | E39: A2b_sin_rupturas_SR | F39: 0.74419645 | G39: 0.72552349 | H39: 0.85347878 | I39: BH (DM-HLN) | J39: output/v8/M4/fuera_muestra.csv | K39: =F39/G39
A40: M4 | B40: alquiler | C40: nacional | D40: 2003Q2..2026Q2 (n=92) | E40: A2b_sin_rupturas_ECM | F40: 1.0670674 | G40: 0.72552349 | H40: 0.000442443 | I40: BH (DM-HLN) | J40: output/v8/M4/fuera_muestra.csv | K40: =F40/G40
A41: M4 | B41: alquiler | C41: nacional | D41: 2003Q2..2026Q2 (n=92) | E41: A3_sin_rupturas_AR4 | F41: 0.72552349 | G41: 0.72552349 | I41: BH (DM-HLN) | J41: output/v8/M4/fuera_muestra.csv | K41: =F41/G41
A42: M4 | B42: alquiler | C42: nacional | D42: 2003Q2..2026Q2 (n=92) | E42: A3_sin_rupturas_SR | F42: 0.8130352 | G42: 0.72552349 | H42: 0.087080613 | I42: BH (DM-HLN) | J42: output/v8/M4/fuera_muestra.csv | K42: =F42/G42
A43: M4 | B43: alquiler | C43: nacional | D43: 2003Q2..2026Q2 (n=92) | E43: A3_sin_rupturas_ECM | F43: 2.6688654 | G43: 0.72552349 | H43: 0.00037780397 | I43: BH (DM-HLN) | J43: output/v8/M4/fuera_muestra.csv | K43: =F43/G43
A44: M4 | B44: alquiler | C44: nacional | D44: 2003Q2..2026Q2 (n=92) | E44: A4_sin_rupturas_AR4 | F44: 0.72552349 | G44: 0.72552349 | I44: BH (DM-HLN) | J44: output/v8/M4/fuera_muestra.csv | K44: =F44/G44
A45: M4 | B45: alquiler | C45: nacional | D45: 2003Q2..2026Q2 (n=92) | E45: A4_sin_rupturas_SR | F45: 0.72532163 | G45: 0.72552349 | H45: 0.99539392 | I45: BH (DM-HLN) | J45: output/v8/M4/fuera_muestra.csv | K45: =F45/G45
A46: M4 | B46: alquiler | C46: nacional | D46: 2003Q2..2026Q2 (n=92) | E46: A4_sin_rupturas_ECM | F46: 2.7964769 | G46: 0.72552349 | H46: 0.0022417888 | I46: BH (DM-HLN) | J46: output/v8/M4/fuera_muestra.csv | K46: =F46/G46
A47: M6 | B47: compra | C47: nacional | D47: completo (n_oos=40) | E47: ar4 | F47: 1.0382 | G47: 1.0382 | I47: Holm (DM-HLN) | J47: output/v8/M6/fuera_muestra.csv | K47: =F47/G47
A48: M6 | B48: compra | C48: nacional | D48: completo (n_oos=40) | E48: ecm_v1 | F48: 3.1078739 | G48: 1.0382 | H48: 0.34798279 | I48: Holm (DM-HLN) | J48: output/v8/M6/fuera_muestra.csv | K48: =F48/G48
A49: M6 | B49: compra | C49: nacional | D49: completo (n_oos=40) | E49: ols_factores | F49: 2.8296942 | G49: 1.0382 | H49: 0.18806262 | I49: Holm (DM-HLN) | J49: output/v8/M6/fuera_muestra.csv | K49: =F49/G49
A50: M6 | B50: compra | C50: nacional | D50: completo (n_oos=40) | E50: ridge | F50: 2.866296 | G50: 1.0382 | H50: 0.32241683 | I50: Holm (DM-HLN) | J50: output/v8/M6/fuera_muestra.csv | K50: =F50/G50
A51: M6 | B51: compra | C51: nacional | D51: completo (n_oos=40) | E51: enet | F51: 1.4671611 | G51: 1.0382 | H51: 0.028337959 | I51: Holm (DM-HLN) | J51: output/v8/M6/fuera_muestra.csv | K51: =F51/G51
A52: M6 | B52: alquiler | C52: nacional | D52: completo (n_oos=40) | E52: ar4 | F52: 0.80442456 | G52: 0.80442456 | I52: Holm (DM-HLN) | J52: output/v8/M6/fuera_muestra.csv | K52: =F52/G52
A53: M6 | B53: alquiler | C53: nacional | D53: completo (n_oos=40) | E53: ecm_v1 | F53: 2.3738367 | G53: 0.80442456 | H53: 0.012697052 | I53: Holm (DM-HLN) | J53: output/v8/M6/fuera_muestra.csv | K53: =F53/G53
A54: M6 | B54: alquiler | C54: nacional | D54: completo (n_oos=40) | E54: ols_factores | F54: 3.8393051 | G54: 0.80442456 | H54: 0.53740205 | I54: Holm (DM-HLN) | J54: output/v8/M6/fuera_muestra.csv | K54: =F54/G54
A55: M6 | B55: alquiler | C55: nacional | D55: completo (n_oos=40) | E55: ridge | F55: 1.7224006 | G55: 0.80442456 | H55: 0.53740205 | I55: Holm (DM-HLN) | J55: output/v8/M6/fuera_muestra.csv | K55: =F55/G55
A56: M6 | B56: alquiler | C56: nacional | D56: completo (n_oos=40) | E56: enet | F56: 1.6310734 | G56: 0.80442456 | H56: 0.53740205 | I56: Holm (DM-HLN) | J56: output/v8/M6/fuera_muestra.csv | K56: =F56/G56
A57: M9 | B57: compra | C57: ccaa_panel | D57: n_test=680 | E57: ar4 | F57: 2.4710496 | G57: 2.4710496 | I57: BH (DM-HLN) | J57: output/v8/M9/oos.csv | K57: =F57/G57
A58: M9 | B58: compra | C58: ccaa_panel | D58: n_test=680 | E58: ar4_fc | F58: 2.141307 | G58: 2.4710496 | H58: 0.010651681 | I58: BH (DM-HLN) | J58: output/v8/M9/oos.csv | K58: =F58/G58
A59: M9 | B59: compra | C59: ccaa_panel | D59: n_test=680 | E59: lgbm_fam_Am | F59: 5.7535579 | G59: 2.4710496 | H59: 0.0051029444 | I59: BH (DM-HLN) | J59: output/v8/M9/oos.csv | K59: =F59/G59
A60: M9 | B60: compra | C60: ccaa_panel | D60: n_test=680 | E60: lgbm_ar_Am | F60: 3.0641621 | G60: 2.4710496 | H60: 0.0896667 | I60: BH (DM-HLN) | J60: output/v8/M9/oos.csv | K60: =F60/G60
A61: M9 | B61: compra | C61: ccaa_panel | D61: n_test=680 | E61: lgbm_fam_An | F61: 5.9857502 | G61: 2.4710496 | H61: 0.0060293067 | I61: BH (DM-HLN) | J61: output/v8/M9/oos.csv | K61: =F61/G61
A62: M9 | B62: compra | C62: ccaa_panel | D62: n_test=680 | E62: lgbm_ar_An | F62: 3.1861265 | G62: 2.4710496 | H62: 0.053517872 | I62: BH (DM-HLN) | J62: output/v8/M9/oos.csv | K62: =F62/G62
A63: M9 | B63: compra | C63: ccaa_panel | D63: n_test=680 | E63: lgbm_fam_Bm | F63: 5.5857137 | G63: 2.4710496 | H63: 0.0060293067 | I63: BH (DM-HLN) | J63: output/v8/M9/oos.csv | K63: =F63/G63
A64: M9 | B64: compra | C64: ccaa_panel | D64: n_test=680 | E64: lgbm_ar_Bm | F64: 3.0070599 | G64: 2.4710496 | H64: 0.14502149 | I64: BH (DM-HLN) | J64: output/v8/M9/oos.csv | K64: =F64/G64
A65: M9 | B65: compra | C65: ccaa_panel | D65: n_test=680 | E65: lgbm_fam_Bn | F65: 5.6875493 | G65: 2.4710496 | H65: 0.0060293067 | I65: BH (DM-HLN) | J65: output/v8/M9/oos.csv | K65: =F65/G65
A66: M9 | B66: compra | C66: ccaa_panel | D66: n_test=680 | E66: lgbm_ar_Bn | F66: 3.067153 | G66: 2.4710496 | H66: 0.13462902 | I66: BH (DM-HLN) | J66: output/v8/M9/oos.csv | K66: =F66/G66
A67: M9 | B67: compra | C67: ccaa_panel | D67: n_test=680 | E67: gam_fam_alfa10 | F67: 5.5153463 | G67: 2.4710496 | H67: 0.0060293067 | I67: BH (DM-HLN) | J67: output/v8/M9/oos.csv | K67: =F67/G67
A68: M9 | B68: compra | C68: ccaa_panel | D68: n_test=680 | E68: gam_ar_alfa10 | F68: 2.5572143 | G68: 2.4710496 | H68: 0.60976912 | I68: BH (DM-HLN) | J68: output/v8/M9/oos.csv | K68: =F68/G68
A69: M9 | B69: compra | C69: ccaa_panel | D69: n_test=680 | E69: gam_fam_alfa100 | F69: 5.0954414 | G69: 2.4710496 | H69: 0.018849115 | I69: BH (DM-HLN) | J69: output/v8/M9/oos.csv | K69: =F69/G69
A70: M9 | B70: compra | C70: ccaa_panel | D70: n_test=680 | E70: gam_ar_alfa100 | F70: 2.4616523 | G70: 2.4710496 | H70: 0.94513707 | I70: BH (DM-HLN) | J70: output/v8/M9/oos.csv | K70: =F70/G70
A71: M9 | B71: compra | C71: nacional | D71: n_test=40 | E71: ar4 | F71: 1.0909422 | G71: 1.0909422 | I71: BH (DM-HLN) | J71: output/v8/M9/oos.csv | K71: =F71/G71
A72: M9 | B72: compra | C72: nacional | D72: n_test=40 | E72: ecm_v1 | F72: 2.7574424 | G72: 1.0909422 | H72: 0.31009839 | I72: BH (DM-HLN) | J72: output/v8/M9/oos.csv | K72: =F72/G72
A73: M9 | B73: compra | C73: nacional | D73: n_test=40 | E73: lgbm_fam_Am | F73: 4.8144237 | G73: 1.0909422 | H73: 0.018849115 | I73: BH (DM-HLN) | J73: output/v8/M9/oos.csv | K73: =F73/G73
A74: M9 | B74: compra | C74: nacional | D74: n_test=40 | E74: lgbm_ar_Am | F74: 2.6174218 | G74: 1.0909422 | H74: 0.0025411045 | I74: BH (DM-HLN) | J74: output/v8/M9/oos.csv | K74: =F74/G74
A75: M9 | B75: compra | C75: nacional | D75: n_test=40 | E75: lgbm_fam_An | F75: 4.8660382 | G75: 1.0909422 | H75: 0.015381797 | I75: BH (DM-HLN) | J75: output/v8/M9/oos.csv | K75: =F75/G75
A76: M9 | B76: compra | C76: nacional | D76: n_test=40 | E76: lgbm_ar_An | F76: 2.8296137 | G76: 1.0909422 | H76: 0.00017744709 | I76: BH (DM-HLN) | J76: output/v8/M9/oos.csv | K76: =F76/G76
A77: M9 | B77: compra | C77: nacional | D77: n_test=40 | E77: lgbm_fam_Bm | F77: 4.5521481 | G77: 1.0909422 | H77: 0.018849115 | I77: BH (DM-HLN) | J77: output/v8/M9/oos.csv | K77: =F77/G77
A78: M9 | B78: compra | C78: nacional | D78: n_test=40 | E78: lgbm_ar_Bm | F78: 2.7668043 | G78: 1.0909422 | H78: 0.00017744709 | I78: BH (DM-HLN) | J78: output/v8/M9/oos.csv | K78: =F78/G78
A79: M9 | B79: compra | C79: nacional | D79: n_test=40 | E79: lgbm_fam_Bn | F79: 4.6420151 | G79: 1.0909422 | H79: 0.015121279 | I79: BH (DM-HLN) | J79: output/v8/M9/oos.csv | K79: =F79/G79
A80: M9 | B80: compra | C80: nacional | D80: n_test=40 | E80: lgbm_ar_Bn | F80: 2.8900611 | G80: 1.0909422 | H80: 8.9149577e-05 | I80: BH (DM-HLN) | J80: output/v8/M9/oos.csv | K80: =F80/G80
A81: M9 | B81: compra | C81: nacional | D81: n_test=40 | E81: gam_fam_alfa10 | F81: 6.5606021 | G81: 1.0909422 | H81: 0.0066465143 | I81: BH (DM-HLN) | J81: output/v8/M9/oos.csv | K81: =F81/G81
A82: M9 | B82: compra | C82: nacional | D82: n_test=40 | E82: gam_ar_alfa10 | F82: 2.3329849 | G82: 1.0909422 | H82: 0.0051029444 | I82: BH (DM-HLN) | J82: output/v8/M9/oos.csv | K82: =F82/G82
A83: M9 | B83: compra | C83: nacional | D83: n_test=40 | E83: gam_fam_alfa100 | F83: 6.507988 | G83: 1.0909422 | H83: 0.0090792053 | I83: BH (DM-HLN) | J83: output/v8/M9/oos.csv | K83: =F83/G83
A84: M9 | B84: compra | C84: nacional | D84: n_test=40 | E84: gam_ar_alfa100 | F84: 2.2410803 | G84: 1.0909422 | H84: 0.0066465143 | I84: BH (DM-HLN) | J84: output/v8/M9/oos.csv | K84: =F84/G84
A85: M9 | B85: alquiler | C85: ccaa_panel | D85: n_test=680 | E85: ar4 | F85: 0.93080521 | G85: 0.93080521 | I85: BH (DM-HLN) | J85: output/v8/M9/oos.csv | K85: =F85/G85
A86: M9 | B86: alquiler | C86: ccaa_panel | D86: n_test=680 | E86: ar4_fc | F86: 0.93395901 | G86: 0.93080521 | H86: 0.55589531 | I86: BH (DM-HLN) | J86: output/v8/M9/oos.csv | K86: =F86/G86
A87: M9 | B87: alquiler | C87: ccaa_panel | D87: n_test=680 | E87: lgbm_fam_Am | F87: 2.3132356 | G87: 0.93080521 | H87: 0.13462902 | I87: BH (DM-HLN) | J87: output/v8/M9/oos.csv | K87: =F87/G87
A88: M9 | B88: alquiler | C88: ccaa_panel | D88: n_test=680 | E88: lgbm_ar_Am | F88: 1.5663852 | G88: 0.93080521 | H88: 0.14502149 | I88: BH (DM-HLN) | J88: output/v8/M9/oos.csv | K88: =F88/G88
A89: M9 | B89: alquiler | C89: ccaa_panel | D89: n_test=680 | E89: lgbm_fam_An | F89: 2.3006852 | G89: 0.93080521 | H89: 0.13462902 | I89: BH (DM-HLN) | J89: output/v8/M9/oos.csv | K89: =F89/G89
A90: M9 | B90: alquiler | C90: ccaa_panel | D90: n_test=680 | E90: lgbm_ar_An | F90: 1.6591081 | G90: 0.93080521 | H90: 0.13462902 | I90: BH (DM-HLN) | J90: output/v8/M9/oos.csv | K90: =F90/G90
A91: M9 | B91: alquiler | C91: ccaa_panel | D91: n_test=680 | E91: lgbm_fam_Bm | F91: 2.3075187 | G91: 0.93080521 | H91: 0.13462902 | I91: BH (DM-HLN) | J91: output/v8/M9/oos.csv | K91: =F91/G91
A92: M9 | B92: alquiler | C92: ccaa_panel | D92: n_test=680 | E92: lgbm_ar_Bm | F92: 1.4977934 | G92: 0.93080521 | H92: 0.15183779 | I92: BH (DM-HLN) | J92: output/v8/M9/oos.csv | K92: =F92/G92
A93: M9 | B93: alquiler | C93: ccaa_panel | D93: n_test=680 | E93: lgbm_fam_Bn | F93: 2.2329267 | G93: 0.93080521 | H93: 0.13462902 | I93: BH (DM-HLN) | J93: output/v8/M9/oos.csv | K93: =F93/G93
A94: M9 | B94: alquiler | C94: ccaa_panel | D94: n_test=680 | E94: lgbm_ar_Bn | F94: 1.5781547 | G94: 0.93080521 | H94: 0.13462902 | I94: BH (DM-HLN) | J94: output/v8/M9/oos.csv | K94: =F94/G94
A95: M9 | B95: alquiler | C95: ccaa_panel | D95: n_test=680 | E95: gam_fam_alfa10 | F95: 2.4234022 | G95: 0.93080521 | H95: 0.16191229 | I95: BH (DM-HLN) | J95: output/v8/M9/oos.csv | K95: =F95/G95
A96: M9 | B96: alquiler | C96: ccaa_panel | D96: n_test=680 | E96: gam_ar_alfa10 | F96: 1.1080484 | G96: 0.93080521 | H96: 0.13462902 | I96: BH (DM-HLN) | J96: output/v8/M9/oos.csv | K96: =F96/G96
A97: M9 | B97: alquiler | C97: ccaa_panel | D97: n_test=680 | E97: gam_fam_alfa100 | F97: 2.2686178 | G97: 0.93080521 | H97: 0.14502149 | I97: BH (DM-HLN) | J97: output/v8/M9/oos.csv | K97: =F97/G97
A98: M9 | B98: alquiler | C98: ccaa_panel | D98: n_test=680 | E98: gam_ar_alfa100 | F98: 1.0588787 | G98: 0.93080521 | H98: 0.13462902 | I98: BH (DM-HLN) | J98: output/v8/M9/oos.csv | K98: =F98/G98
A99: M9 | B99: alquiler | C99: nacional | D99: n_test=40 | E99: ar4 | F99: 0.94688014 | G99: 0.94688014 | I99: BH (DM-HLN) | J99: output/v8/M9/oos.csv | K99: =F99/G99
A100: M9 | B100: alquiler | C100: nacional | D100: n_test=40 | E100: ecm_v1 | F100: 1.6205754 | G100: 0.94688014 | H100: 0.065511599 | I100: BH (DM-HLN) | J100: output/v8/M9/oos.csv | K100: =F100/G100
A101: M9 | B101: alquiler | C101: nacional | D101: n_test=40 | E101: lgbm_fam_Am | F101: 2.8192523 | G101: 0.94688014 | H101: 0.13462902 | I101: BH (DM-HLN) | J101: output/v8/M9/oos.csv | K101: =F101/G101
A102: M9 | B102: alquiler | C102: nacional | D102: n_test=40 | E102: lgbm_ar_Am | F102: 2.4644482 | G102: 0.94688014 | H102: 0.14502149 | I102: BH (DM-HLN) | J102: output/v8/M9/oos.csv | K102: =F102/G102
...

Sheet Regional
A1: mercado | B1: ambito | C1: periodo | D1: factor | E1: metodo | F1: variante | G1: contribucion_pp | H1: pct_total | I1: b68_lo | J1: b68_hi | K1: delta_y_implicita_pp | L1: rank_c_signo | M1: compite | N1: designacion | O1: nota | P1: fuente
A2: alquiler | B2: ccaa:01 | C2: P2 | D2: factor_comun | E2: regional_ccaa_ols | F2: ols_solo_factor | G2: -3.55904 | H2: 157.163 | I2: -7.72994 | J2: 0.781566 | K2: -2.59207 | M2: no | N2: no designado (contraste C4: no hay svar_hd regional) | O2: CCAA: ranking por c_f·sign(dY) del panel FE (M8); asociacion, sin lectura causal; el factor comun es un resumen de comovimiento (pendiente ~1 mecanica, J23) | P2: output/v8/F5/regional_ranking.csv
A3: alquiler | B3: ccaa:01 | C3: P2 | D3: residuo | E3: regional_ccaa_ols | F3: ols_solo_factor | G3: 1.29449 | H3: -57.1631 | K3: -2.59207 | M3: no | N3: no designado (contraste C4: no hay svar_hd regional) | O3: CCAA: ranking por c_f·sign(dY) del panel FE (M8); asociacion, sin lectura causal; el factor comun es un resumen de comovimiento (pendiente ~1 mecanica, J23) | P3: output/v8/F5/regional_ranking.csv
A4: alquiler | B4: ccaa:01 | C4: P2 | D4: factor_comun | E4: regional_panel | F4: panel_covariables | G4: -3.50963 | H4: 135.398 | I4: -7.73728 | J4: 0.660335 | K4: -2.59207 | M4: no | N4: no designado (contraste C4: no hay svar_hd regional) | O4: CCAA: ranking por c_f·sign(dY) del panel FE (M8); asociacion, sin lectura causal; el factor comun es un resumen de comovimiento (pendiente ~1 mecanica, J23) | P4: output/v8/F5/regional_ranking.csv
A5: alquiler | B5: ccaa:01 | C5: P2 | D5: empleo_renta | E5: regional_panel | F5: panel_covariables | G5: 0.0454272 | H5: -1.75254 | I5: -0.374367 | J5: 0.627229 | K5: -2.59207 | L5: 2 | M5: si | N5: no designado (contraste C4: no hay svar_hd regional) | O5: CCAA: ranking por c_f·sign(dY) del panel FE (M8); asociacion, sin lectura causal; el factor comun es un resumen de comovimiento (pendiente ~1 mecanica, J23) | P5: output/v8/F5/regional_ranking.csv
A6: alquiler | B6: ccaa:01 | C6: P2 | D6: demografia | E6: regional_panel | F6: panel_covariables | G6: 0.918412 | H6: -35.4316 | I6: 0.686297 | J6: 1.333 | K6: -2.59207 | L6: 4 | M6: si | N6: no designado (contraste C4: no hay svar_hd regional) | O6: CCAA: ranking por c_f·sign(dY) del panel FE (M8); asociacion, sin lectura causal; el factor comun es un resumen de comovimiento (pendiente ~1 mecanica, J23) | P6: output/v8/F5/regional_ranking.csv
A7: alquiler | B7: ccaa:01 | C7: P2 | D7: oferta | E7: regional_panel | F7: panel_covariables | G7: 0.285299 | H7: -11.0066 | I7: 0.0373704 | J7: 0.546445 | K7: -2.59207 | L7: 3 | M7: si | N7: no designado (contraste C4: no hay svar_hd regional) | O7: CCAA: ranking por c_f·sign(dY) del panel FE (M8); asociacion, sin lectura causal; el factor comun es un resumen de comovimiento (pendiente ~1 mecanica, J23) | P7: output/v8/F5/regional_ranking.csv
A8: alquiler | B8: ccaa:01 | C8: P2 | D8: demanda_externa | E8: regional_panel | F8: panel_covariables | G8: 0.0397178 | H8: -1.53228 | I8: -0.00264922 | J8: 0.0491875 | K8: -2.59207 | L8: 1 | M8: si | N8: no designado (contraste C4: no hay svar_hd regional) | O8: CCAA: ranking por c_f·sign(dY) del panel FE (M8); asociacion, sin lectura causal; el factor comun es un resumen de comovimiento (pendiente ~1 mecanica, J23) | P8: output/v8/F5/regional_ranking.csv
A9: alquiler | B9: ccaa:01 | C9: P2 | D9: residuo | E9: regional_panel | F9: panel_covariables | G9: -0.371302 | H9: 14.3245 | I9: -1.24927 | J9: 0.230081 | K9: -2.59207 | M9: no | N9: no designado (contraste C4: no hay svar_hd regional) | O9: CCAA: ranking por c_f·sign(dY) del panel FE (M8); asociacion, sin lectura causal; el factor comun es un resumen de comovimiento (pendiente ~1 mecanica, J23) | P9: output/v8/F5/regional_ranking.csv
A10: alquiler | B10: ccaa:01 | C10: P3 | D10: factor_comun | E10: regional_ccaa_ols | F10: ols_solo_factor | G10: -2.70797 | H10: 119.626 | I10: -4.18432 | J10: -1.237 | K10: -1.84167 | M10: no | N10: no designado (contraste C4: no hay svar_hd regional) | O10: CCAA: ranking por c_f·sign(dY) del panel FE (M8); asociacion, sin lectura causal; el factor comun es un resumen de comovimiento (pendiente ~1 mecanica, J23) | P10: output/v8/F5/regional_ranking.csv
A11: alquiler | B11: ccaa:01 | C11: P3 | D11: residuo | E11: regional_ccaa_ols | F11: ols_solo_factor | G11: 0.44428 | H11: -19.6264 | K11: -1.84167 | M11: no | N11: no designado (contraste C4: no hay svar_hd regional) | O11: CCAA: ranking por c_f·sign(dY) del panel FE (M8); asociacion, sin lectura causal; el factor comun es un resumen de comovimiento (pendiente ~1 mecanica, J23) | P11: output/v8/F5/regional_ranking.csv
